Workbook

Sheet Budget
A1: Colonne 1 | B1: Septembre 2026 | C1: Aout 2026 | D1: Juillet 2026 | E1: Juin 2026 | F1: Mai 2026 | G1: Avril 2026 | H1: Mars 2026 | I1: Fevrier 2026 | J1: Janvier 2026 | K1: Décembre 2025 | L1: Novembre 2025 | M1: Octobre 2025 | N1: Septembre 2025 | O1: Aout 2025 | P1: Juillet 2025 | Q1: Juin 2025 | R1: Mai 2025 | S1: Avril 2025 | T1: Mars 2025 | U1: Fevrier 2025 | V1: Janvier 2025
A2: Courses | B2: =SUMIF('Septembre 2026'!$K$3:$K$243,$A2,'Septembre 2026'!$H$3:$H$243) -> 254.23 | C2: =SUMIF('Aout 2026'!$K$3:$K$243,$A2,'Aout 2026'!$H$3:$H$243) -> 2120.04 | D2: =SUMIF('Juillet 2026'!$K$3:$K$241,$A2,'Juillet 2026'!$H$3:$H$241) -> 1639.04 | E2: =SUMIF('Juin 2026'!$K$3:$K$241,$A2,'Juin 2026'!$H$3:$H$241) -> 1872.28 | F2: =SUMIF('Mai 2026'!$K$3:$K$241,$A2,'Mai 2026'!$H$3:$H$241) -> 2139.03 | G2: =SUMIF('Avril 2026'!$K$3:$K$241,$A2,'Avril 2026'!$H$3:$H$241) -> 1775.59 | H2: =SUMIF('Mars 2026'!$K$3:$K$241,$A2,'Mars 2026'!$H$3:$H$241) -> 1241.27 | I2: =SUMIF('Fevrier 2026'!$K$3:$K$241,$A2,'Fevrier 2026'!$H$3:$H$241) -> 1544.09 | J2: =SUMIF('Janvier 2026'!$K$3:$K$241,$A2,'Janvier 2026'!$H$3:$H$241) -> 1114.46 | K2: =SUMIF(#REF!,$A2,#REF!) -> #REF! | L2: =SUMIF(#REF!,$A2,#REF!) -> #REF! | M2: =SUMIF(#REF!,$A2,#REF!) -> #REF! | N2: =SUMIF(#REF!,$A2,#REF!) -> #REF! | O2: =SUMIF(#REF!,$A2,#REF!) -> #REF! | P2: =SUMIF(#REF!,$A2,#REF!) -> #REF! | Q2: =SUMIF(#REF!,$A2,#REF!) -> #REF! | R2: =SUMIF(#REF!,$A2,#REF!) -> #REF! | ... V2: =SUMIF(#REF!,$A2,#REF!) -> #REF!
A3: Logement | B3: =SUMIF('Septembre 2026'!$K$3:$K$243,$A3,'Septembre 2026'!$H$3:$H$243) -> 2582.27 | C3: =SUMIF('Aout 2026'!$K$3:$K$243,$A3,'Aout 2026'!$H$3:$H$243) -> 2842.23 | D3: =SUMIF('Juillet 2026'!$K$3:$K$241,$A3,'Juillet 2026'!$H$3:$H$241) -> 3006.77 | E3: =SUMIF('Juin 2026'!$K$3:$K$241,$A3,'Juin 2026'!$H$3:$H$241) -> 2847.2 | F3: =SUMIF('Mai 2026'!$K$3:$K$241,$A3,'Mai 2026'!$H$3:$H$241) -> 2932.63 | G3: =SUMIF('Avril 2026'!$K$3:$K$241,$A3,'Avril 2026'!$H$3:$H$241) -> 2949.2 | H3: =SUMIF('Mars 2026'!$K$3:$K$241,$A3,'Mars 2026'!$H$3:$H$241) -> 2907.37 | I3: =SUMIF('Fevrier 2026'!$K$3:$K$241,$A3,'Fevrier 2026'!$H$3:$H$241) -> 2805.43 | J3: =SUMIF('Janvier 2026'!$K$3:$K$241,$A3,'Janvier 2026'!$H$3:$H$241) -> 2899.11 | K3: =SUMIF(#REF!,$A3,#REF!) -> #REF! | L3: =SUMIF(#REF!,$A3,#REF!) -> #REF! | M3: =SUMIF(#REF!,$A3,#REF!) -> #REF! | N3: =SUMIF(#REF!,$A3,#REF!) -> #REF! | O3: =SUMIF(#REF!,$A3,#REF!) -> #REF! | P3: =SUMIF(#REF!,$A3,#REF!) -> #REF! | Q3: =SUMIF(#REF!,$A3,#REF!) -> #REF! | R3: =SUMIF(#REF!,$A3,#REF!) -> #REF! | ... V3: =SUMIF(#REF!,$A3,#REF!) -> #REF!
A4: Charges | B4: =SUMIF('Septembre 2026'!$K$3:$K$243,$A4,'Septembre 2026'!$H$3:$H$243) -> 221.32 | C4: =SUMIF('Aout 2026'!$K$3:$K$243,$A4,'Aout 2026'!$H$3:$H$243) -> 400.44 | D4: =SUMIF('Juillet 2026'!$K$3:$K$241,$A4,'Juillet 2026'!$H$3:$H$241) -> 1183.78 | E4: =SUMIF('Juin 2026'!$K$3:$K$241,$A4,'Juin 2026'!$H$3:$H$241) -> 637.86 | F4: =SUMIF('Mai 2026'!$K$3:$K$241,$A4,'Mai 2026'!$H$3:$H$241) -> 905.12 | G4: =SUMIF('Avril 2026'!$K$3:$K$241,$A4,'Avril 2026'!$H$3:$H$241) -> 585.68 | H4: =SUMIF('Mars 2026'!$K$3:$K$241,$A4,'Mars 2026'!$H$3:$H$241) -> 561.59 | I4: =SUMIF('Fevrier 2026'!$K$3:$K$241,$A4,'Fevrier 2026'!$H$3:$H$241) -> 724.03 | J4: =SUMIF('Janvier 2026'!$K$3:$K$241,$A4,'Janvier 2026'!$H$3:$H$241) -> 1632.2 | K4: =SUMIF(#REF!,$A4,#REF!) -> #REF! | L4: =SUMIF(#REF!,$A4,#REF!) -> #REF! | M4: =SUMIF(#REF!,$A4,#REF!) -> #REF! | N4: =SUMIF(#REF!,$A4,#REF!) -> #REF! | O4: =SUMIF(#REF!,$A4,#REF!) -> #REF! | P4: =SUMIF(#REF!,$A4,#REF!) -> #REF! | Q4: =SUMIF(#REF!,$A4,#REF!) -> #REF! | R4: =SUMIF(#REF!,$A4,#REF!) -> #REF! | ... V4: =SUMIF(#REF!,$A4,#REF!) -> #REF!
A5: Internet/Téléphone | B5: =SUMIF('Septembre 2026'!$K$3:$K$243,$A5,'Septembre 2026'!$H$3:$H$243) -> 0.99 | C5: =SUMIF('Aout 2026'!$K$3:$K$243,$A5,'Aout 2026'!$H$3:$H$243) -> 132.89 | D5: =SUMIF('Juillet 2026'!$K$3:$K$241,$A5,'Juillet 2026'!$H$3:$H$241) -> 113.91 | E5: =SUMIF('Juin 2026'!$K$3:$K$241,$A5,'Juin 2026'!$H$3:$H$241) -> 162.8 | F5: =SUMIF('Mai 2026'!$K$3:$K$241,$A5,'Mai 2026'!$H$3:$H$241) -> 169.14 | G5: =SUMIF('Avril 2026'!$K$3:$K$241,$A5,'Avril 2026'!$H$3:$H$241) -> 123.9 | H5: =SUMIF('Mars 2026'!$K$3:$K$241,$A5,'Mars 2026'!$H$3:$H$241) -> 137.89 | I5: =SUMIF('Fevrier 2026'!$K$3:$K$241,$A5,'Fevrier 2026'!$H$3:$H$241) -> 183.92 | J5: =SUMIF('Janvier 2026'!$K$3:$K$241,$A5,'Janvier 2026'!$H$3:$H$241) -> 752.48 | K5: =SUMIF(#REF!,$A5,#REF!) -> #REF! | L5: =SUMIF(#REF!,$A5,#REF!) -> #REF! | M5: =SUMIF(#REF!,$A5,#REF!) -> #REF! | N5: =SUMIF(#REF!,$A5,#REF!) -> #REF! | O5: =SUMIF(#REF!,$A5,#REF!) -> #REF! | P5: =SUMIF(#REF!,$A5,#REF!) -> #REF! | Q5: =SUMIF(#REF!,$A5,#REF!) -> #REF! | R5: =SUMIF(#REF!,$A5,#REF!) -> #REF! | ... V5: =SUMIF(#REF!,$A5,#REF!) -> #REF!
A6: Assurances/Mutuelle | B6: =SUMIF('Septembre 2026'!$K$3:$K$243,$A6,'Septembre 2026'!$H$3:$H$243) -> 0 | C6: =SUMIF('Aout 2026'!$K$3:$K$243,$A6,'Aout 2026'!$H$3:$H$243) -> 274.88 | D6: =SUMIF('Juillet 2026'!$K$3:$K$241,$A6,'Juillet 2026'!$H$3:$H$241) -> 274.88 | E6: =SUMIF('Juin 2026'!$K$3:$K$241,$A6,'Juin 2026'!$H$3:$H$241) -> 255.89 | F6: =SUMIF('Mai 2026'!$K$3:$K$241,$A6,'Mai 2026'!$H$3:$H$241) -> 269.31 | G6: =SUMIF('Avril 2026'!$K$3:$K$241,$A6,'Avril 2026'!$H$3:$H$241) -> 356.17 | H6: =SUMIF('Mars 2026'!$K$3:$K$241,$A6,'Mars 2026'!$H$3:$H$241) -> 328.74 | I6: =SUMIF('Fevrier 2026'!$K$3:$K$241,$A6,'Fevrier 2026'!$H$3:$H$241) -> 328.74 | J6: =SUMIF('Janvier 2026'!$K$3:$K$241,$A6,'Janvier 2026'!$H$3:$H$241) -> 281 | K6: =SUMIF(#REF!,$A6,#REF!) -> #REF! | L6: =SUMIF(#REF!,$A6,#REF!) -> #REF! | M6: =SUMIF(#REF!,$A6,#REF!) -> #REF! | N6: =SUMIF(#REF!,$A6,#REF!) -> #REF! | O6: =SUMIF(#REF!,$A6,#REF!) -> #REF! | P6: =SUMIF(#REF!,$A6,#REF!) -> #REF! | Q6: =SUMIF(#REF!,$A6,#REF!) -> #REF! | R6: =SUMIF(#REF!,$A6,#REF!) -> #REF! | ... V6: =SUMIF(#REF!,$A6,#REF!) -> #REF!
A7: Voiture/Déplacement | B7: =SUMIF('Septembre 2026'!$K$3:$K$243,$A7,'Septembre 2026'!$H$3:$H$243) -> 0 | C7: =SUMIF('Aout 2026'!$K$3:$K$243,$A7,'Aout 2026'!$H$3:$H$243) -> 516.41 | D7: =SUMIF('Juillet 2026'!$K$3:$K$241,$A7,'Juillet 2026'!$H$3:$H$241) -> 485.89 | E7: =SUMIF('Juin 2026'!$K$3:$K$241,$A7,'Juin 2026'!$H$3:$H$241) -> 600.4 | F7: =SUMIF('Mai 2026'!$K$3:$K$241,$A7,'Mai 2026'!$H$3:$H$241) -> 512.85 | G7: =SUMIF('Avril 2026'!$K$3:$K$241,$A7,'Avril 2026'!$H$3:$H$241) -> 428.15 | H7: =SUMIF('Mars 2026'!$K$3:$K$241,$A7,'Mars 2026'!$H$3:$H$241) -> 742.95 | I7: =SUMIF('Fevrier 2026'!$K$3:$K$241,$A7,'Fevrier 2026'!$H$3:$H$241) -> 443.85 | J7: =SUMIF('Janvier 2026'!$K$3:$K$241,$A7,'Janvier 2026'!$H$3:$H$241) -> 600.11 | K7: =SUMIF(#REF!,$A7,#REF!) -> #REF! | L7: =SUMIF(#REF!,$A7,#REF!) -> #REF! | M7: =SUMIF(#REF!,$A7,#REF!) -> #REF! | N7: =SUMIF(#REF!,$A7,#REF!) -> #REF! | O7: =SUMIF(#REF!,$A7,#REF!) -> #REF! | P7: =SUMIF(#REF!,$A7,#REF!) -> #REF! | Q7: =SUMIF(#REF!,$A7,#REF!) -> #REF! | R7: =SUMIF(#REF!,$A7,#REF!) -> #REF! | ... V7: =SUMIF(#REF!,$A7,#REF!) -> #REF!
A8: Scolarité | B8: =SUMIF('Septembre 2026'!$K$3:$K$243,$A8,'Septembre 2026'!$H$3:$H$243) -> 118.97 | C8: =SUMIF('Aout 2026'!$K$3:$K$243,$A8,'Aout 2026'!$H$3:$H$243) -> 414.32 | D8: =SUMIF('Juillet 2026'!$K$3:$K$241,$A8,'Juillet 2026'!$H$3:$H$241) -> 816.3 | E8: =SUMIF('Juin 2026'!$K$3:$K$241,$A8,'Juin 2026'!$H$3:$H$241) -> 196.9 | F8: =SUMIF('Mai 2026'!$K$3:$K$241,$A8,'Mai 2026'!$H$3:$H$241) -> 278.3 | G8: =SUMIF('Avril 2026'!$K$3:$K$241,$A8,'Avril 2026'!$H$3:$H$241) -> 178.3 | H8: =SUMIF('Mars 2026'!$K$3:$K$241,$A8,'Mars 2026'!$H$3:$H$241) -> 220.18 | I8: =SUMIF('Fevrier 2026'!$K$3:$K$241,$A8,'Fevrier 2026'!$H$3:$H$241) -> 172.1 | J8: =SUMIF('Janvier 2026'!$K$3:$K$241,$A8,'Janvier 2026'!$H$3:$H$241) -> 178.3 | K8: =SUMIF(#REF!,$A8,#REF!) -> #REF! | L8: =SUMIF(#REF!,$A8,#REF!) -> #REF! | M8: =SUMIF(#REF!,$A8,#REF!) -> #REF! | N8: =SUMIF(#REF!,$A8,#REF!) -> #REF! | O8: =SUMIF(#REF!,$A8,#REF!) -> #REF! | P8: =SUMIF(#REF!,$A8,#REF!) -> #REF! | Q8: =SUMIF(#REF!,$A8,#REF!) -> #REF! | R8: =SUMIF(#REF!,$A8,#REF!) -> #REF! | ... V8: =SUMIF(#REF!,$A8,#REF!) -> #REF!
A9: Vêtements | B9: =SUMIF('Septembre 2026'!$K$3:$K$243,$A9,'Septembre 2026'!$H$3:$H$243) -> 69.08 | C9: =SUMIF('Aout 2026'!$K$3:$K$243,$A9,'Aout 2026'!$H$3:$H$243) -> 375.16 | D9: =SUMIF('Juillet 2026'!$K$3:$K$241,$A9,'Juillet 2026'!$H$3:$H$241) -> 570.47 | E9: =SUMIF('Juin 2026'!$K$3:$K$241,$A9,'Juin 2026'!$H$3:$H$241) -> 311.51 | F9: =SUMIF('Mai 2026'!$K$3:$K$241,$A9,'Mai 2026'!$H$3:$H$241) -> 150.66 | G9: =SUMIF('Avril 2026'!$K$3:$K$241,$A9,'Avril 2026'!$H$3:$H$241) -> 226.77 | H9: =SUMIF('Mars 2026'!$K$3:$K$241,$A9,'Mars 2026'!$H$3:$H$241) -> 274.9 | I9: =SUMIF('Fevrier 2026'!$K$3:$K$241,$A9,'Fevrier 2026'!$H$3:$H$241) -> 229.95 | J9: =SUMIF('Janvier 2026'!$K$3:$K$241,$A9,'Janvier 2026'!$H$3:$H$241) -> 85 | K9: =SUMIF(#REF!,$A9,#REF!) -> #REF! | L9: =SUMIF(#REF!,$A9,#REF!) -> #REF! | M9: =SUMIF(#REF!,$A9,#REF!) -> #REF! | N9: =SUMIF(#REF!,$A9,#REF!) -> #REF! | O9: =SUMIF(#REF!,$A9,#REF!) -> #REF! | P9: =SUMIF(#REF!,$A9,#REF!) -> #REF! | Q9: =SUMIF(#REF!,$A9,#REF!) -> #REF! | R9: =SUMIF(#REF!,$A9,#REF!) -> #REF! | ... V9: =SUMIF(#REF!,$A9,#REF!) -> #REF!
A10: Bricolage/Travaux | B10: =SUMIF('Septembre 2026'!$K$3:$K$243,$A10,'Septembre 2026'!$H$3:$H$243) -> 62.92 | C10: =SUMIF('Aout 2026'!$K$3:$K$243,$A10,'Aout 2026'!$H$3:$H$243) -> 1467.81 | D10: =SUMIF('Juillet 2026'!$K$3:$K$241,$A10,'Juillet 2026'!$H$3:$H$241) -> 1051.41 | E10: =SUMIF('Juin 2026'!$K$3:$K$241,$A10,'Juin 2026'!$H$3:$H$241) -> 330.75 | F10: =SUMIF('Mai 2026'!$K$3:$K$241,$A10,'Mai 2026'!$H$3:$H$241) -> 402.83 | G10: =SUMIF('Avril 2026'!$K$3:$K$241,$A10,'Avril 2026'!$H$3:$H$241) -> 418.51 | H10: =SUMIF('Mars 2026'!$K$3:$K$241,$A10,'Mars 2026'!$H$3:$H$241) -> 988.72 | I10: =SUMIF('Fevrier 2026'!$K$3:$K$241,$A10,'Fevrier 2026'!$H$3:$H$241) -> 118.29 | J10: =SUMIF('Janvier 2026'!$K$3:$K$241,$A10,'Janvier 2026'!$H$3:$H$241) -> 748.33 | K10: =SUMIF(#REF!,$A10,#REF!) -> #REF! | L10: =SUMIF(#REF!,$A10,#REF!) -> #REF! | M10: =SUMIF(#REF!,$A10,#REF!) -> #REF! | N10: =SUMIF(#REF!,$A10,#REF!) -> #REF! | O10: =SUMIF(#REF!,$A10,#REF!) -> #REF! | P10: =SUMIF(#REF!,$A10,#REF!) -> #REF! | Q10: =SUMIF(#REF!,$A10,#REF!) -> #REF! | R10: =SUMIF(#REF!,$A10,#REF!) -> #REF! | ... V10: =SUMIF(#REF!,$A10,#REF!) -> #REF!
A11: Loisirs | B11: =SUMIF('Septembre 2026'!$K$3:$K$243,$A11,'Septembre 2026'!$H$3:$H$243) -> 0 | C11: =SUMIF('Aout 2026'!$K$3:$K$243,$A11,'Aout 2026'!$H$3:$H$243) -> 1159.87 | D11: =SUMIF('Juillet 2026'!$K$3:$K$241,$A11,'Juillet 2026'!$H$3:$H$241) -> 626.8 | E11: =SUMIF('Juin 2026'!$K$3:$K$241,$A11,'Juin 2026'!$H$3:$H$241) -> 331.86 | F11: =SUMIF('Mai 2026'!$K$3:$K$241,$A11,'Mai 2026'!$H$3:$H$241) -> 176.04 | G11: =SUMIF('Avril 2026'!$K$3:$K$241,$A11,'Avril 2026'!$H$3:$H$241) -> 351.58 | H11: =SUMIF('Mars 2026'!$K$3:$K$241,$A11,'Mars 2026'!$H$3:$H$241) -> 433.49 | I11: =SUMIF('Fevrier 2026'!$K$3:$K$241,$A11,'Fevrier 2026'!$H$3:$H$241) -> 673.55 | J11: =SUMIF('Janvier 2026'!$K$3:$K$241,$A11,'Janvier 2026'!$H$3:$H$241) -> 109.17 | K11: =SUMIF(#REF!,$A11,#REF!) -> #REF! | L11: =SUMIF(#REF!,$A11,#REF!) -> #REF! | M11: =SUMIF(#REF!,$A11,#REF!) -> #REF! | N11: =SUMIF(#REF!,$A11,#REF!) -> #REF! | O11: =SUMIF(#REF!,$A11,#REF!) -> #REF! | P11: =SUMIF(#REF!,$A11,#REF!) -> #REF! | Q11: =SUMIF(#REF!,$A11,#REF!) -> #REF! | R11: =SUMIF(#REF!,$A11,#REF!) -> #REF! | ... V11: =SUMIF(#REF!,$A11,#REF!) -> #REF!
A12: Divers | B12: =SUMIF('Septembre 2026'!$K$3:$K$243,$A12,'Septembre 2026'!$H$3:$H$243) -> 73.69 | C12: =SUMIF('Aout 2026'!$K$3:$K$243,$A12,'Aout 2026'!$H$3:$H$243) -> 983.25 | D12: =SUMIF('Juillet 2026'!$K$3:$K$241,$A12,'Juillet 2026'!$H$3:$H$241) -> 314.19 | E12: =SUMIF('Juin 2026'!$K$3:$K$241,$A12,'Juin 2026'!$H$3:$H$241) -> 313.62 | F12: =SUMIF('Mai 2026'!$K$3:$K$241,$A12,'Mai 2026'!$H$3:$H$241) -> 673.22 | G12: =SUMIF('Avril 2026'!$K$3:$K$241,$A12,'Avril 2026'!$H$3:$H$241) -> 698.32 | H12: =SUMIF('Mars 2026'!$K$3:$K$241,$A12,'Mars 2026'!$H$3:$H$241) -> 144.51 | I12: =SUMIF('Fevrier 2026'!$K$3:$K$241,$A12,'Fevrier 2026'!$H$3:$H$241) -> 430.68 | J12: =SUMIF('Janvier 2026'!$K$3:$K$241,$A12,'Janvier 2026'!$H$3:$H$241) -> 103.22 | K12: =SUMIF(#REF!,$A12,#REF!) -> #REF! | L12: =SUMIF(#REF!,$A12,#REF!) -> #REF! | M12: =SUMIF(#REF!,$A12,#REF!) -> #REF! | N12: =SUMIF(#REF!,$A12,#REF!) -> #REF! | O12: =SUMIF(#REF!,$A12,#REF!) -> #REF! | P12: =SUMIF(#REF!,$A12,#REF!) -> #REF! | Q12: =SUMIF(#REF!,$A12,#REF!) -> #REF! | R12: =SUMIF(#REF!,$A12,#REF!) -> #REF! | ... V12: =SUMIF(#REF!,$A12,#REF!) -> #REF!
A13: Medical | B13: =SUMIF('Septembre 2026'!$K$3:$K$243,$A13,'Septembre 2026'!$H$3:$H$243) -> 38.2 | C13: =SUMIF('Aout 2026'!$K$3:$K$243,$A13,'Aout 2026'!$H$3:$H$243) -> 465.55 | D13: =SUMIF('Juillet 2026'!$K$3:$K$241,$A13,'Juillet 2026'!$H$3:$H$241) -> 119.3 | E13: =SUMIF('Juin 2026'!$K$3:$K$241,$A13,'Juin 2026'!$H$3:$H$241) -> 53.25 | F13: =SUMIF('Mai 2026'!$K$3:$K$241,$A13,'Mai 2026'!$H$3:$H$241) -> 178.48 | G13: =SUMIF('Avril 2026'!$K$3:$K$241,$A13,'Avril 2026'!$H$3:$H$241) -> 0 | H13: =SUMIF('Mars 2026'!$K$3:$K$241,$A13,'Mars 2026'!$H$3:$H$241) -> 178.29 | I13: =SUMIF('Fevrier 2026'!$K$3:$K$241,$A13,'Fevrier 2026'!$H$3:$H$241) -> 117.78 | J13: =SUMIF('Janvier 2026'!$K$3:$K$241,$A13,'Janvier 2026'!$H$3:$H$241) -> 481.7 | K13: =SUMIF(#REF!,$A13,#REF!) -> #REF! | L13: =SUMIF(#REF!,$A13,#REF!) -> #REF! | M13: =SUMIF(#REF!,$A13,#REF!) -> #REF! | N13: =SUMIF(#REF!,$A13,#REF!) -> #REF! | O13: =SUMIF(#REF!,$A13,#REF!) -> #REF! | P13: =SUMIF(#REF!,$A13,#REF!) -> #REF! | Q13: =SUMIF(#REF!,$A13,#REF!) -> #REF! | R13: =SUMIF(#REF!,$A13,#REF!) -> #REF! | ... V13: =SUMIF(#REF!,$A13,#REF!) -> #REF!
... A16: Cadeau | B16: =SUMIF('Septembre 2026'!$K$3:$K$243,$A16,'Septembre 2026'!$H$3:$H$243) -> 0 | C16: =SUMIF('Aout 2026'!$K$3:$K$243,$A16,'Aout 2026'!$H$3:$H$243) -> 0 | D16: =SUMIF('Juillet 2026'!$K$3:$K$241,$A16,'Juillet 2026'!$H$3:$H$241) -> 0 | E16: =SUMIF('Juin 2026'!$K$3:$K$241,$A16,'Juin 2026'!$H$3:$H$241) -> 88.69 | F16: =SUMIF('Mai 2026'!$K$3:$K$241,$A16,'Mai 2026'!$H$3:$H$241) -> 197.89 | G16: =SUMIF('Avril 2026'!$K$3:$K$241,$A16,'Avril 2026'!$H$3:$H$241) -> 166.99 | H16: =SUMIF('Mars 2026'!$K$3:$K$241,$A16,'Mars 2026'!$H$3:$H$241) -> 183.8 | I16: =SUMIF('Fevrier 2026'!$K$3:$K$241,$A16,'Fevrier 2026'!$H$3:$H$241) -> 290 | J16: =SUMIF('Janvier 2026'!$K$3:$K$241,$A16,'Janvier 2026'!$H$3:$H$241) -> 469.35 | K16: =SUMIF(#REF!,$A16,#REF!) -> #REF! | L16: =SUMIF(#REF!,$A16,#REF!) -> #REF! | M16: =SUMIF(#REF!,$A16,#REF!) -> #REF! | N16: =SUMIF(#REF!,$A16,#REF!) -> #REF! | O16: =SUMIF(#REF!,$A16,#REF!) -> #REF! | P16: =SUMIF(#REF!,$A16,#REF!) -> #REF! | Q16: =SUMIF(#REF!,$A16,#REF!) -> #REF! | R16: =SUMIF(#REF!,$A16,#REF!) -> #REF! | ... V16: =SUMIF(#REF!,$A16,#REF!) -> #REF!
A17: Total | B17: =SUM(B2:B14) -> 3421.67 | C17: =SUM(C2:C14) -> 11152.85 | D17: =SUM(D2:D14) -> 10202.74 | E17: =SUM(E2:E14) -> 7984.32 | F17: =SUM(F2:F14) -> 8976.51 | G17: =SUM(G2:G14) -> 8313.81 | H17: =SUM(H2:H14) -> 8183 | I17: =SUM(I2:I14) -> 7834.87 | ... V17: =SUM(V2:V14) -> #REF!
A18: Bilan Fin de mois | B18: =INDIRECT(B1&"!D43")-INDIRECT(B1&"!C39") -> #REF! | C18: =INDIRECT(C1&"!D43")-INDIRECT(C1&"!C39") -> #REF! | D18: =INDIRECT(D1&"!D43")-INDIRECT(D1&"!C39") -> #REF! | E18: =INDIRECT(E1&"!D43")-INDIRECT(E1&"!C39") -> #REF! | F18: =INDIRECT(F1&"!D43")-INDIRECT(F1&"!C39") -> #REF! | G18: =INDIRECT(G1&"!D43")-INDIRECT(G1&"!C39") -> #REF! | H18: =INDIRECT(H1&"!D43")-INDIRECT(H1&"!C39") -> #REF! | I18: =INDIRECT(I1&"!D43")-INDIRECT(I1&"!C39") -> #REF! | ... V18: =INDIRECT(V1&"!D43")-INDIRECT(V1&"!C39") -> #REF!

Sheet Septembre 2026
B1: Recettes | E1: Dépenses | K1: Cadeau
B3: Salaire Pierre | C3: 5226.16 | E3: Loyer Elouen | F3: 669.7 | G3: x | H3: =IF(G3="x",F3,0) -> 669.7 | K3: Logement
B4: Salaire Sterenn | C4: 2086.77 | E4: Argent de poche Elouen | H4: =IF(G4="x",F4,0) -> 0 | K4: Charges
B5: CAF | E5: Engie Elouen | F5: 66.32 | G5: x | H5: =IF(G5="x",F5,0) -> 66.32 | K5: Charges
E6: Argent de poche Arthur | F6: 155 | G6: x | H6: =IF(G6="x",F6,0) -> 155 | K6: Charges
E7: Prêt 25 | F7: 995.15 | G7: x | H7: =IF(G7="x",F7,0) -> 995.15 | K7: Logement
B8: Note de frais Igienair | C8: 160.89 | E8: Prêt 15 | F8: 883.42 | G8: x | H8: =IF(G8="x",F8,0) -> 883.42 | K8: Logement
B9: Remboursement Padel Edouard | C9: 4 | E9: Assurances prêt | F9: 11.46 | H9: =IF(G9="x",F9,0) -> 0 | K9: Logement
E10: Assurances prêt | F10: 32.57 | H10: =IF(G10="x",F10,0) -> 0 | K10: Logement
E11: Assurances prêt | F11: 79.98 | H11: =IF(G11="x",F11,0) -> 0 | K11: Logement
E12: Assurances prêt | F12: 28.49 | H12: =IF(G12="x",F12,0) -> 0 | K12: Logement
E13: Disney | F13: 6.99 | H13: =IF(G13="x",F13,0) -> 0 | K13: Internet/Téléphone
E14: EDF Arthur | F14: 65 | H14: =IF(G14="x",F14,0) -> 0 | K14: Charges
E15: EkWateur | F15: 208 | H15: =IF(G15="x",F15,0) -> 0 | K15: Charges
E16: Sosh Maison | F16: 24.99 | H16: =IF(G16="x",F16,0) -> 0 | K16: Internet/Téléphone
H17: =IF(G17="x",F17,0) -> 0 | K17: Internet/Téléphone
E18: Sosh Ael | F18: 14.99 | H18: =IF(G18="x",F18,0) -> 0 | K18: Internet/Téléphone
E19: Sosh Elouen | F19: 14.99 | H19: =IF(G19="x",F19,0) -> 0 | K19: Internet/Téléphone
E20: Sosh Sterenn | F20: 10.99 | H20: =IF(G20="x",F20,0) -> 0 | K20: Internet/Téléphone
E21: Mutuelle | F21: 104.98 | H21: =IF(G21="x",F21,0) -> 0 | K21: Assurances/Mutuelle
E23: AxaHabitation | F23: 62.88 | H23: =IF(G23="x",F23,0) -> 0 | K23: Assurances/Mutuelle
E24: VW LLD | F24: 331.65 | H24: =IF(G24="x",F24,0) -> 0 | K24: Voiture/Déplacement
E25: Axa Voiture | F25: 88.03 | H25: =IF(G25="x",F25,0) -> 0 | K25: Assurances/Mutuelle
E26: Suravenir Garanties Vie | F26: 18.99 | H26: =IF(G26="x",F26,0) -> 0 | K26: Assurances/Mutuelle
E27: Joséphine | F27: 20 | G27: x | H27: =IF(G27="x",F27,0) -> 20 | K27: Divers
E28: Canal Plus | F28: 21.99 | H28: =IF(G28="x",F28,0) -> 0 | K28: Internet/Téléphone
H29: =IF(G29="x",F29,0) -> 0 | K29: Voiture/Déplacement
E30: Keolis Elouen | F30: 21.4 | H30: =IF(G30="x",F30,0) -> 0 | K30: Voiture/Déplacement
E31: Apple | F31: 0.99 | H31: =IF(G31="x",F31,0) -> 0 | K31: Internet/Téléphone
E32: Apple | F32: 0.99 | G32: x | H32: =IF(G32="x",F32,0) -> 0.99 | K32: Internet/Téléphone
E33: Apple | F33: 16.99 | H33: =IF(G33="x",F33,0) -> 0 | K33: Internet/Téléphone
E34: Lycée | F34: 450 | H34: =IF(G34="x",F34,0) -> 0 | K34: Scolarité
E35: Ménage | F35: 170 | H35: =IF(G35="x",F35,0) -> 0 | K35: Logement
E36: Urssaaf | F36: 34 | G36: x | H36: =IF(G36="x",F36,0) -> 34 | K36: Logement
E37: Cotisation Eurocompte | F37: 19.03 | H37: =IF(G37="x",F37,0) -> 0 | K37: Charges
E38: Indivision | F38: 33.89 | H38: =IF(G38="x",F38,0) -> 0 | K38: Charges
A39: Etat mois précédent | C39: ='Aout 2026'!D43 -> #REF!
A40: Recettes fixes | C40: =SUM(C2:C6) -> 7312.93 | E40: Somme dépenses prévues | F40: =SUM(F2:F38) -> 4663.85 | G40: Somme dépenses réelles | H40: =SUM(H2:H38) -> 2824.58 | I40: Delta moins les exceptions
A41: Recettes additionnelles du mois | C41: =SUM(C8:C35) -> 164.89 | E41: Reste previsionnel | F41: =C42-F40 -> #REF! | G41: Delta du mois | H41: =C39+C40+C41-H40-F42 -> #REF!
A42: Total Recettes | C42: =SUM(C39:C41) -> #REF! | E42: Somme dépenses non prévues | F42: =SUM(J44:J247) -> 597.09
A43: Reste prévu | B43: =$C$42-$F$40-$F$42 -> #REF! | C43: Reste réel | D43: =$C$42-$H$40-$F$42 -> #REF!
A44: =IF(AND(NOT(ISBLANK(#REF!)),ISBLANK(G44)),"Reste prévu","") | B44: =IF(AND(NOT(ISBLANK(#REF!)),ISBLANK($G44)),$C$42-$F$40-$F$42,"") | C44: =IF(AND(NOT(ISBLANK(#REF!)),ISBLANK($G44)),"Reste réel","") | D44: =IF(AND(NOT(ISBLANK(#REF!)),ISBLANK($G44)),$C$42-$H$40-$F$42,"") | G44: Vinted | H44: 22.59 | I44: x | J44: =IF(I44="x",H44,0) -> 22.59 | K44: Vêtements
A45: =IF(AND(NOT(ISBLANK(G44)),ISBLANK(G45)),"Reste prévu","") | B45: =IF(AND(NOT(ISBLANK($G44)),ISBLANK($G45)),$C$42-$F$40-$F$42,"") | C45: =IF(AND(NOT(ISBLANK($G44)),ISBLANK($G45)),"Reste réel","") | D45: =IF(AND(NOT(ISBLANK($G44)),ISBLANK($G45)),$C$42-$H$40-$F$42,"") | G45: Pharmacie | H45: 38.2 | I45: x | J45: =IF(I45="x",H45,0) -> 38.2 | K45: Medical
A46: =IF(AND(NOT(ISBLANK(G45)),ISBLANK(G46)),"Reste prévu","") | B46: =IF(AND(NOT(ISBLANK($G45)),ISBLANK($G46)),$C$42-$F$40-$F$42,"") | C46: =IF(AND(NOT(ISBLANK($G45)),ISBLANK($G46)),"Reste réel","") | D46: =IF(AND(NOT(ISBLANK($G45)),ISBLANK($G46)),$C$42-$H$40-$F$42,"") | G46: Amazon | H46: 9.99 | I46: x | J46: =IF(I46="x",H46,0) -> 9.99 | K46: Divers
A47: =IF(AND(NOT(ISBLANK(G46)),ISBLANK(G47)),"Reste prévu","") | B47: =IF(AND(NOT(ISBLANK($G46)),ISBLANK($G47)),$C$42-$F$40-$F$42,"") | C47: =IF(AND(NOT(ISBLANK($G46)),ISBLANK($G47)),"Reste réel","") | D47: =IF(AND(NOT(ISBLANK($G46)),ISBLANK($G47)),$C$42-$H$40-$F$42,"") | G47: Vinted | H47: 46.49 | I47: x | J47: =IF(I47="x",H47,0) -> 46.49 | K47: Vêtements
A48: =IF(AND(NOT(ISBLANK(G47)),ISBLANK(G48)),"Reste prévu","") | B48: =IF(AND(NOT(ISBLANK($G47)),ISBLANK($G48)),$C$42-$F$40-$F$42,"") | C48: =IF(AND(NOT(ISBLANK($G47)),ISBLANK($G48)),"Reste réel","") | D48: =IF(AND(NOT(ISBLANK($G47)),ISBLANK($G48)),$C$42-$H$40-$F$42,"") | G48: Leclerc | H48: 37.92 | I48: x | J48: =IF(I48="x",H48,0) -> 37.92 | K48: Courses
A49: =IF(AND(NOT(ISBLANK(G48)),ISBLANK(G49)),"Reste prévu","") | B49: =IF(AND(NOT(ISBLANK($G48)),ISBLANK($G49)),$C$42-$F$40-$F$42,"") | C49: =IF(AND(NOT(ISBLANK($G48)),ISBLANK($G49)),"Reste réel","") | D49: =IF(AND(NOT(ISBLANK($G48)),ISBLANK($G49)),$C$42-$H$40-$F$42,"") | G49: Leclerc | H49: 38.72 | I49: x | J49: =IF(I49="x",H49,0) -> 38.72 | K49: Courses
A50: =IF(AND(NOT(ISBLANK(G49)),ISBLANK(G50)),"Reste prévu","") | B50: =IF(AND(NOT(ISBLANK($G49)),ISBLANK($G50)),$C$42-$F$40-$F$42,"") | C50: =IF(AND(NOT(ISBLANK($G49)),ISBLANK($G50)),"Reste réel","") | D50: =IF(AND(NOT(ISBLANK($G49)),ISBLANK($G50)),$C$42-$H$40-$F$42,"") | G50: Materiel Compresseur | H50: 52.92 | I50: x | J50: =IF(I50="x",H50,0) -> 52.92 | K50: Bricolage/Travaux
A51: =IF(AND(NOT(ISBLANK(G50)),ISBLANK(G51)),"Reste prévu","") | B51: =IF(AND(NOT(ISBLANK($G50)),ISBLANK($G51)),$C$42-$F$40-$F$42,"") | C51: =IF(AND(NOT(ISBLANK($G50)),ISBLANK($G51)),"Reste réel","") | D51: =IF(AND(NOT(ISBLANK($G50)),ISBLANK($G51)),$C$42-$H$40-$F$42,"") | G51: OVH Site Internet Hand | H51: 18.7 | I51: x | J51: =IF(I51="x",H51,0) -> 18.7 | K51: Divers
A52: =IF(AND(NOT(ISBLANK(G51)),ISBLANK(G52)),"Reste prévu","") | B52: =IF(AND(NOT(ISBLANK($G51)),ISBLANK($G52)),$C$42-$F$40-$F$42,"") | C52: =IF(AND(NOT(ISBLANK($G51)),ISBLANK($G52)),"Reste réel","") | D52: =IF(AND(NOT(ISBLANK($G51)),ISBLANK($G52)),$C$42-$H$40-$F$42,"") | G52: Coiffeur Ael | H52: 25 | I52: x | J52: =IF(I52="x",H52,0) -> 25 | K52: Divers
A53: =IF(AND(NOT(ISBLANK(G52)),ISBLANK(G53)),"Reste prévu","") | B53: =IF(AND(NOT(ISBLANK($G52)),ISBLANK($G53)),$C$42-$F$40-$F$42,"") | C53: =IF(AND(NOT(ISBLANK($G52)),ISBLANK($G53)),"Reste réel","") | D53: =IF(AND(NOT(ISBLANK($G52)),ISBLANK($G53)),$C$42-$H$40-$F$42,"") | G53: Lidl | H53: 11.75 | I53: x | J53: =IF(I53="x",H53,0) -> 11.75 | K53: Courses
A54: =IF(AND(NOT(ISBLANK(G53)),ISBLANK(G54)),"Reste prévu","") | B54: =IF(AND(NOT(ISBLANK($G53)),ISBLANK($G54)),$C$42-$F$40-$F$42,"") | C54: =IF(AND(NOT(ISBLANK($G53)),ISBLANK($G54)),"Reste réel","") | D54: =IF(AND(NOT(ISBLANK($G53)),ISBLANK($G54)),$C$42-$H$40-$F$42,"") | G54: Cafran | H54: 98.37 | I54: x | J54: =IF(I54="x",H54,0) -> 98.37 | K54: Courses
A55: =IF(AND(NOT(ISBLANK(G54)),ISBLANK(G55)),"Reste prévu","") | B55: =IF(AND(NOT(ISBLANK($G54)),ISBLANK($G55)),$C$42-$F$40-$F$42,"") | C55: =IF(AND(NOT(ISBLANK($G54)),ISBLANK($G55)),"Reste réel","") | D55: =IF(AND(NOT(ISBLANK($G54)),ISBLANK($G55)),$C$42-$H$40-$F$42,"") | G55: Cultura | H55: 118.97 | I55: x | J55: =IF(I55="x",H55,0) -> 118.97 | K55: Scolarité
A56: =IF(AND(NOT(ISBLANK(G55)),ISBLANK(G56)),"Reste prévu","") | B56: =IF(AND(NOT(ISBLANK($G55)),ISBLANK($G56)),$C$42-$F$40-$F$42,"") | C56: =IF(AND(NOT(ISBLANK($G55)),ISBLANK($G56)),"Reste réel","") | D56: =IF(AND(NOT(ISBLANK($G55)),ISBLANK($G56)),$C$42-$H$40-$F$42,"") | G56: Plan Etabli | H56: 10 | I56: x | J56: =IF(I56="x",H56,0) -> 10 | K56: Bricolage/Travaux
... A58: =IF(AND(NOT(ISBLANK(G57)),ISBLANK(G58)),"Reste prévu","") | B58: =IF(AND(NOT(ISBLANK($G57)),ISBLANK($G58)),$C$42-$F$40-$F$42,"") | C58: =IF(AND(NOT(ISBLANK($G57)),ISBLANK($G58)),"Reste réel","") | D58: =IF(AND(NOT(ISBLANK($G57)),ISBLANK($G58)),$C$42-$H$40-$F$42,"") | G58: SuperU | H58: 63.74 | I58: x | J58: =IF(I58="x",H58,0) -> 63.74 | K58: Courses
A59: =IF(AND(NOT(ISBLANK(G58)),ISBLANK(G59)),"Reste prévu","") -> Reste prévu | B59: =IF(AND(NOT(ISBLANK($G58)),ISBLANK($G59)),$C$42-$F$40-$F$42,"") -> #REF! | C59: =IF(AND(NOT(ISBLANK($G58)),ISBLANK($G59)),"Reste réel","") -> Reste réel | D59: =IF(AND(NOT(ISBLANK($G58)),ISBLANK($G59)),$C$42-$H$40-$F$42,"") -> #REF! | J59: =IF(I59="x",H59,0) -> 0 | K59: Bricolage/Travaux
A60: =IF(AND(NOT(ISBLANK(G59)),ISBLANK(G60)),"Reste prévu","") | B60: =IF(AND(NOT(ISBLANK($G59)),ISBLANK($G60)),$C$42-$F$40-$F$42,"") | C60: =IF(AND(NOT(ISBLANK($G59)),ISBLANK($G60)),"Reste réel","") | D60: =IF(AND(NOT(ISBLANK($G59)),ISBLANK($G60)),$C$42-$H$40-$F$42,"") | J60: =IF(I60="x",H60,0) -> 0 | K60: Courses
A61: =IF(AND(NOT(ISBLANK(G60)),ISBLANK(G61)),"Reste prévu","") | B61: =IF(AND(NOT(ISBLANK($G60)),ISBLANK($G61)),$C$42-$F$40-$F$42,"") | C61: =IF(AND(NOT(ISBLANK($G60)),ISBLANK($G61)),"Reste réel","") | D61: =IF(AND(NOT(ISBLANK($G60)),ISBLANK($G61)),$C$42-$H$40-$F$42,"") | J61: =IF(I61="x",H61,0) -> 0 | K61: Bricolage/Travaux
A62: =IF(AND(NOT(ISBLANK(G61)),ISBLANK(G62)),"Reste prévu","") | B62: =IF(AND(NOT(ISBLANK($G61)),ISBLANK($G62)),$C$42-$F$40-$F$42,"") | C62: =IF(AND(NOT(ISBLANK($G61)),ISBLANK($G62)),"Reste réel","") | D62: =IF(AND(NOT(ISBLANK($G61)),ISBLANK($G62)),$C$42-$H$40-$F$42,"") | J62: =IF(I62="x",H62,0) -> 0 | K62: Courses
A63: =IF(AND(NOT(ISBLANK(G62)),ISBLANK(G63)),"Reste prévu","") | B63: =IF(AND(NOT(ISBLANK($G62)),ISBLANK($G63)),$C$42-$F$40-$F$42,"") | C63: =IF(AND(NOT(ISBLANK($G62)),ISBLANK($G63)),"Reste réel","") | D63: =IF(AND(NOT(ISBLANK($G62)),ISBLANK($G63)),$C$42-$H$40-$F$42,"") | J63: =IF(I63="x",H63,0) -> 0 | K63: Courses
A64: =IF(AND(NOT(ISBLANK(G63)),ISBLANK(G64)),"Reste prévu","") | B64: =IF(AND(NOT(ISBLANK($G63)),ISBLANK($G64)),$C$42-$F$40-$F$42,"") | C64: =IF(AND(NOT(ISBLANK($G63)),ISBLANK($G64)),"Reste réel","") | D64: =IF(AND(NOT(ISBLANK($G63)),ISBLANK($G64)),$C$42-$H$40-$F$42,"") | J64: =IF(I64="x",H64,0) -> 0 | K64: Courses
A65: =IF(AND(NOT(ISBLANK(G64)),ISBLANK(G65)),"Reste prévu","") | B65: =IF(AND(NOT(ISBLANK($G64)),ISBLANK($G65)),$C$42-$F$40-$F$42,"") | C65: =IF(AND(NOT(ISBLANK($G64)),ISBLANK($G65)),"Reste réel","") | D65: =IF(AND(NOT(ISBLANK($G64)),ISBLANK($G65)),$C$42-$H$40-$F$42,"") | J65: =IF(I65="x",H65,0) -> 0 | K65: Divers
A66: =IF(AND(NOT(ISBLANK(G65)),ISBLANK(G66)),"Reste prévu","") | B66: =IF(AND(NOT(ISBLANK($G65)),ISBLANK($G66)),$C$42-$F$40-$F$42,"") | C66: =IF(AND(NOT(ISBLANK($G65)),ISBLANK($G66)),"Reste réel","") | D66: =IF(AND(NOT(ISBLANK($G65)),ISBLANK($G66)),$C$42-$H$40-$F$42,"") | J66: =IF(I66="x",H66,0) -> 0 | K66: Divers
A67: =IF(AND(NOT(ISBLANK(G66)),ISBLANK(G67)),"Reste prévu","") | B67: =IF(AND(NOT(ISBLANK($G66)),ISBLANK($G67)),$C$42-$F$40-$F$42,"") | C67: =IF(AND(NOT(ISBLANK($G66)),ISBLANK($G67)),"Reste réel","") | D67: =IF(AND(NOT(ISBLANK($G66)),ISBLANK($G67)),$C$42-$H$40-$F$42,"") | J67: =IF(I67="x",H67,0) -> 0 | K67: Medical
A68: =IF(AND(NOT(ISBLANK(G67)),ISBLANK(G68)),"Reste prévu","") | B68: =IF(AND(NOT(ISBLANK($G67)),ISBLANK($G68)),$C$42-$F$40-$F$42,"") | C68: =IF(AND(NOT(ISBLANK($G67)),ISBLANK($G68)),"Reste réel","") | D68: =IF(AND(NOT(ISBLANK($G67)),ISBLANK($G68)),$C$42-$H$40-$F$42,"") | J68: =IF(I68="x",H68,0) -> 0 | K68: Courses
A69: =IF(AND(NOT(ISBLANK(G68)),ISBLANK(G69)),"Reste prévu","") | B69: =IF(AND(NOT(ISBLANK($G68)),ISBLANK($G69)),$C$42-$F$40-$F$42,"") | C69: =IF(AND(NOT(ISBLANK($G68)),ISBLANK($G69)),"Reste réel","") | D69: =IF(AND(NOT(ISBLANK($G68)),ISBLANK($G69)),$C$42-$H$40-$F$42,"") | J69: =IF(I69="x",H69,0) -> 0 | K69: Courses
A70: =IF(AND(NOT(ISBLANK(G69)),ISBLANK(G70)),"Reste prévu","") | B70: =IF(AND(NOT(ISBLANK($G69)),ISBLANK($G70)),$C$42-$F$40-$F$42,"") | C70: =IF(AND(NOT(ISBLANK($G69)),ISBLANK($G70)),"Reste réel","") | D70: =IF(AND(NOT(ISBLANK($G69)),ISBLANK($G70)),$C$42-$H$40-$F$42,"") | J70: =IF(I70="x",H70,0) -> 0 | K70: Courses
... A78: =IF(AND(NOT(ISBLANK(G77)),ISBLANK(G78)),"Reste prévu","") | B78: =IF(AND(NOT(ISBLANK($G77)),ISBLANK($G78)),$C$42-$F$40-$F$42,"") | C78: =IF(AND(NOT(ISBLANK($G77)),ISBLANK($G78)),"Reste réel","") | D78: =IF(AND(NOT(ISBLANK($G77)),ISBLANK($G78)),$C$42-$H$40-$F$42,"") | J78: =IF(I78="x",H78,0) -> 0 | K78: Courses
J79: =IF(I79="x",H79,0) -> 0 | K79: Medical
A80: =IF(AND(NOT(ISBLANK(G78)),ISBLANK(G80)),"Reste prévu","") | B80: =IF(AND(NOT(ISBLANK($G78)),ISBLANK($G80)),$C$42-$F$40-$F$42,"") | C80: =IF(AND(NOT(ISBLANK($G78)),ISBLANK($G80)),"Reste réel","") | D80: =IF(AND(NOT(ISBLANK($G78)),ISBLANK($G80)),$C$42-$H$40-$F$42,"") | J80: =IF(I80="x",H80,0) -> 0 | K80: Courses
A81: =IF(AND(NOT(ISBLANK(G80)),ISBLANK(G81)),"Reste prévu","") | B81: =IF(AND(NOT(ISBLANK($G80)),ISBLANK($G81)),$C$42-$F$40-$F$42,"") | C81: =IF(AND(NOT(ISBLANK($G80)),ISBLANK($G81)),"Reste réel","") | D81: =IF(AND(NOT(ISBLANK($G80)),ISBLANK($G81)),$C$42-$H$40-$F$42,"") | J81: =IF(I81="x",H81,0) -> 0 | K81: Courses
A82: =IF(AND(NOT(ISBLANK(G81)),ISBLANK(G82)),"Reste prévu","") | B82: =IF(AND(NOT(ISBLANK($G81)),ISBLANK($G82)),$C$42-$F$40-$F$42,"") | C82: =IF(AND(NOT(ISBLANK($G81)),ISBLANK($G82)),"Reste réel","") | D82: =IF(AND(NOT(ISBLANK($G81)),ISBLANK($G82)),$C$42-$H$40-$F$42,"") | J82: =IF(I82="x",H82,0) -> 0 | K82: Courses
A83: =IF(AND(NOT(ISBLANK(G82)),ISBLANK(G83)),"Reste prévu","") | B83: =IF(AND(NOT(ISBLANK($G82)),ISBLANK($G83)),$C$42-$F$40-$F$42,"") | C83: =IF(AND(NOT(ISBLANK($G82)),ISBLANK($G83)),"Reste réel","") | D83: =IF(AND(NOT(ISBLANK($G82)),ISBLANK($G83)),$C$42-$H$40-$F$42,"") | J83: =IF(I83="x",H83,0) -> 0 | K83: Divers
A84: =IF(AND(NOT(ISBLANK(G83)),ISBLANK(G84)),"Reste prévu","") | B84: =IF(AND(NOT(ISBLANK($G83)),ISBLANK($G84)),$C$42-$F$40-$F$42,"") | C84: =IF(AND(NOT(ISBLANK($G83)),ISBLANK($G84)),"Reste réel","") | D84: =IF(AND(NOT(ISBLANK($G83)),ISBLANK($G84)),$C$42-$H$40-$F$42,"") | J84: =IF(I84="x",H84,0) -> 0 | K84: Courses
A85: =IF(AND(NOT(ISBLANK(G84)),ISBLANK(G85)),"Reste prévu","") | B85: =IF(AND(NOT(ISBLANK($G84)),ISBLANK($G85)),$C$42-$F$40-$F$42,"") | C85: =IF(AND(NOT(ISBLANK($G84)),ISBLANK($G85)),"Reste réel","") | D85: =IF(AND(NOT(ISBLANK($G84)),ISBLANK($G85)),$C$42-$H$40-$F$42,"") | J85: =IF(I85="x",H85,0) -> 0 | K85: Courses
A86: =IF(AND(NOT(ISBLANK(G85)),ISBLANK(G86)),"Reste prévu","") | B86: =IF(AND(NOT(ISBLANK($G85)),ISBLANK($G86)),$C$42-$F$40-$F$42,"") | C86: =IF(AND(NOT(ISBLANK($G85)),ISBLANK($G86)),"Reste réel","") | D86: =IF(AND(NOT(ISBLANK($G85)),ISBLANK($G86)),$C$42-$H$40-$F$42,"") | J86: =IF(I86="x",H86,0) -> 0 | K86: Courses
A87: =IF(AND(NOT(ISBLANK(G86)),ISBLANK(G87)),"Reste prévu","") | B87: =IF(AND(NOT(ISBLANK($G86)),ISBLANK($G87)),$C$42-$F$40-$F$42,"") | C87: =IF(AND(NOT(ISBLANK($G86)),ISBLANK($G87)),"Reste réel","") | D87: =IF(AND(NOT(ISBLANK($G86)),ISBLANK($G87)),$C$42-$H$40-$F$42,"") | J87: =IF(I87="x",H87,0) -> 0 | K87: Medical
A88: =IF(AND(NOT(ISBLANK(G87)),ISBLANK(G88)),"Reste prévu","") | B88: =IF(AND(NOT(ISBLANK($G87)),ISBLANK($G88)),$C$42-$F$40-$F$42,"") | C88: =IF(AND(NOT(ISBLANK($G87)),ISBLANK($G88)),"Reste réel","") | D88: =IF(AND(NOT(ISBLANK($G87)),ISBLANK($G88)),$C$42-$H$40-$F$42,"") | J88: =IF(I88="x",H88,0) -> 0 | K88: Loisirs
A89: =IF(AND(NOT(ISBLANK(G88)),ISBLANK(G89)),"Reste prévu","") | B89: =IF(AND(NOT(ISBLANK($G88)),ISBLANK($G89)),$C$42-$F$40-$F$42,"") | C89: =IF(AND(NOT(ISBLANK($G88)),ISBLANK($G89)),"Reste réel","") | D89: =IF(AND(NOT(ISBLANK($G88)),ISBLANK($G89)),$C$42-$H$40-$F$42,"") | J89: =IF(I89="x",H89,0) -> 0 | K89: Courses
A90: =IF(AND(NOT(ISBLANK(G89)),ISBLANK(G90)),"Reste prévu","") | B90: =IF(AND(NOT(ISBLANK($G89)),ISBLANK($G90)),$C$42-$F$40-$F$42,"") | C90: =IF(AND(NOT(ISBLANK($G89)),ISBLANK($G90)),"Reste réel","") | D90: =IF(AND(NOT(ISBLANK($G89)),ISBLANK($G90)),$C$42-$H$40-$F$42,"") | J90: =IF(I90="x",H90,0) -> 0 | K90: Courses
A91: =IF(AND(NOT(ISBLANK(G90)),ISBLANK(G91)),"Reste prévu","") | B91: =IF(AND(NOT(ISBLANK($G90)),ISBLANK($G91)),$C$42-$F$40-$F$42,"") | C91: =IF(AND(NOT(ISBLANK($G90)),ISBLANK($G91)),"Reste réel","") | D91: =IF(AND(NOT(ISBLANK($G90)),ISBLANK($G91)),$C$42-$H$40-$F$42,"") | J91: =IF(I91="x",H91,0) -> 0 | K91: Courses
A92: =IF(AND(NOT(ISBLANK(G91)),ISBLANK(G92)),"Reste prévu","") | B92: =IF(AND(NOT(ISBLANK($G91)),ISBLANK($G92)),$C$42-$F$40-$F$42,"") | C92: =IF(AND(NOT(ISBLANK($G91)),ISBLANK($G92)),"Reste réel","") | D92: =IF(AND(NOT(ISBLANK($G91)),ISBLANK($G92)),$C$42-$H$40-$F$42,"") | J92: =IF(I92="x",H92,0) -> 0 | K92: Scolarité
... A155: =IF(AND(NOT(ISBLANK(G154)),ISBLANK(G155)),"Reste prévu","") | B155: =IF(AND(NOT(ISBLANK($G154)),ISBLANK($G155)),$C$42-$F$40-$F$42,"") | C155: =IF(AND(NOT(ISBLANK($G154)),ISBLANK($G155)),"Reste réel","") | D155: =IF(AND(NOT(ISBLANK($G154)),ISBLANK($G155)),$C$42-$H$40-$F$42,"") | J155: =IF(I155="x",H155,0) -> 0 | K155: Charges
A156: =IF(AND(NOT(ISBLANK(G155)),ISBLANK(G156)),"Reste prévu","") | B156: =IF(AND(NOT(ISBLANK($G155)),ISBLANK($G156)),$C$42-$F$40-$F$42,"") | C156: =IF(AND(NOT(ISBLANK($G155)),ISBLANK($G156)),"Reste réel","") | D156: =IF(AND(NOT(ISBLANK($G155)),ISBLANK($G156)),$C$42-$H$40-$F$42,"") | J156: =IF(I156="x",H156,0) -> 0
A157: =IF(AND(NOT(ISBLANK(G156)),ISBLANK(G157)),"Reste prévu","") | B157: =IF(AND(NOT(ISBLANK($G156)),ISBLANK($G157)),$C$42-$F$40-$F$42,"") | C157: =IF(AND(NOT(ISBLANK($G156)),ISBLANK($G157)),"Reste réel","") | D157: =IF(AND(NOT(ISBLANK($G156)),ISBLANK($G157)),$C$42-$H$40-$F$42,"") | J157: =IF(I157="x",H157,0) -> 0
A158: =IF(AND(NOT(ISBLANK(G157)),ISBLANK(G158)),"Reste prévu","") | B158: =IF(AND(NOT(ISBLANK($G157)),ISBLANK($G158)),$C$42-$F$40-$F$42,"") | C158: =IF(AND(NOT(ISBLANK($G157)),ISBLANK($G158)),"Reste réel","") | D158: =IF(AND(NOT(ISBLANK($G157)),ISBLANK($G158)),$C$42-$H$40-$F$42,"") | J158: =IF(I158="x",H158,0) -> 0
A159: =IF(AND(NOT(ISBLANK(G158)),ISBLANK(G159)),"Reste prévu","") | B159: =IF(AND(NOT(ISBLANK($G158)),ISBLANK($G159)),$C$42-$F$40-$F$42,"") | C159: =IF(AND(NOT(ISBLANK($G158)),ISBLANK($G159)),"Reste réel","") | D159: =IF(AND(NOT(ISBLANK($G158)),ISBLANK($G159)),$C$42-$H$40-$F$42,"") | J159: =IF(I159="x",H159,0) -> 0
A160: =IF(AND(NOT(ISBLANK(G159)),ISBLANK(G160)),"Reste prévu","") | B160: =IF(AND(NOT(ISBLANK($G159)),ISBLANK($G160)),$C$42-$F$40-$F$42,"") | C160: =IF(AND(NOT(ISBLANK($G159)),ISBLANK($G160)),"Reste réel","") | D160: =IF(AND(NOT(ISBLANK($G159)),ISBLANK($G160)),$C$42-$H$40-$F$42,"") | J160: =IF(I160="x",H160,0) -> 0
A161: =IF(AND(NOT(ISBLANK(G160)),ISBLANK(G161)),"Reste prévu","") | B161: =IF(AND(NOT(ISBLANK($G160)),ISBLANK($G161)),$C$42-$F$40-$F$42,"") | C161: =IF(AND(NOT(ISBLANK($G160)),ISBLANK($G161)),"Reste réel","") | D161: =IF(AND(NOT(ISBLANK($G160)),ISBLANK($G161)),$C$42-$H$40-$F$42,"") | J161: =IF(I161="x",H161,0) -> 0
A162: =IF(AND(NOT(ISBLANK(G161)),ISBLANK(G162)),"Reste prévu","") | B162: =IF(AND(NOT(ISBLANK($G161)),ISBLANK($G162)),$C$42-$F$40-$F$42,"") | C162: =IF(AND(NOT(ISBLANK($G161)),ISBLANK($G162)),"Reste réel","") | D162: =IF(AND(NOT(ISBLANK($G161)),ISBLANK($G162)),$C$42-$H$40-$F$42,"") | J162: =IF(I162="x",H162,0) -> 0
A163: =IF(AND(NOT(ISBLANK(G162)),ISBLANK(G163)),"Reste prévu","") | B163: =IF(AND(NOT(ISBLANK($G162)),ISBLANK($G163)),$C$42-$F$40-$F$42,"") | C163: =IF(AND(NOT(ISBLANK($G162)),ISBLANK($G163)),"Reste réel","") | D163: =IF(AND(NOT(ISBLANK($G162)),ISBLANK($G163)),$C$42-$H$40-$F$42,"") | J163: =IF(I163="x",H163,0) -> 0
A164: =IF(AND(NOT(ISBLANK(G163)),ISBLANK(G164)),"Reste prévu","") | B164: =IF(AND(NOT(ISBLANK($G163)),ISBLANK($G164)),$C$42-$F$40-$F$42,"") | C164: =IF(AND(NOT(ISBLANK($G163)),ISBLANK($G164)),"Reste réel","") | D164: =IF(AND(NOT(ISBLANK($G163)),ISBLANK($G164)),$C$42-$H$40-$F$42,"") | J164: =IF(I164="x",H164,0) -> 0
A165: =IF(AND(NOT(ISBLANK(G164)),ISBLANK(G165)),"Reste prévu","") | B165: =IF(AND(NOT(ISBLANK($G164)),ISBLANK($G165)),$C$42-$F$40-$F$42,"") | C165: =IF(AND(NOT(ISBLANK($G164)),ISBLANK($G165)),"Reste réel","") | D165: =IF(AND(NOT(ISBLANK($G164)),ISBLANK($G165)),$C$42-$H$40-$F$42,"") | J165: =IF(I165="x",H165,0) -> 0
A166: =IF(AND(NOT(ISBLANK(G165)),ISBLANK(G166)),"Reste prévu","") | B166: =IF(AND(NOT(ISBLANK($G165)),ISBLANK($G166)),$C$42-$F$40-$F$42,"") | C166: =IF(AND(NOT(ISBLANK($G165)),ISBLANK($G166)),"Reste réel","") | D166: =IF(AND(NOT(ISBLANK($G165)),ISBLANK($G166)),$C$42-$H$40-$F$42,"") | J166: =IF(I166="x",H166,0) -> 0
A167: =IF(AND(NOT(ISBLANK(G166)),ISBLANK(G167)),"Reste prévu","") | B167: =IF(AND(NOT(ISBLANK($G166)),ISBLANK($G167)),$C$42-$F$40-$F$42,"") | C167: =IF(AND(NOT(ISBLANK($G166)),ISBLANK($G167)),"Reste réel","") | D167: =IF(AND(NOT(ISBLANK($G166)),ISBLANK($G167)),$C$42-$H$40-$F$42,"") | J167: =IF(I167="x",H167,0) -> 0
... A214: =IF(AND(NOT(ISBLANK(G213)),ISBLANK(G214)),"Reste prévu","") | B214: =IF(AND(NOT(ISBLANK($G213)),ISBLANK($G214)),$C$42-$F$40-$F$42,"") | C214: =IF(AND(NOT(ISBLANK($G213)),ISBLANK($G214)),"Reste réel","") | D214: =IF(AND(NOT(ISBLANK($G213)),ISBLANK($G214)),$C$42-$H$40-$F$42,"") | J214: =IF(I214="x",H214,0) -> 0
A215: =IF(AND(NOT(ISBLANK(G214)),ISBLANK(G215)),"Reste prévu","") | B215: =IF(AND(NOT(ISBLANK($G214)),ISBLANK($G215)),$C$42-$F$40-$F$42,"") | C215: =IF(AND(NOT(ISBLANK($G214)),ISBLANK($G215)),"Reste réel","") | D215: =IF(AND(NOT(ISBLANK($G214)),ISBLANK($G215)),$C$42-$H$40-$F$42,"")
A216: =IF(AND(NOT(ISBLANK(G215)),ISBLANK(G216)),"Reste prévu","") | B216: =IF(AND(NOT(ISBLANK($G215)),ISBLANK($G216)),$C$42-$F$40-$F$42,"") | C216: =IF(AND(NOT(ISBLANK($G215)),ISBLANK($G216)),"Reste réel","") | D216: =IF(AND(NOT(ISBLANK($G215)),ISBLANK($G216)),$C$42-$H$40-$F$42,"")
A217: =IF(AND(NOT(ISBLANK(G216)),ISBLANK(G217)),"Reste prévu","") | B217: =IF(AND(NOT(ISBLANK($G216)),ISBLANK($G217)),$C$42-$F$40-$F$42,"") | C217: =IF(AND(NOT(ISBLANK($G216)),ISBLANK($G217)),"Reste réel","") | D217: =IF(AND(NOT(ISBLANK($G216)),ISBLANK($G217)),$C$42-$H$40-$F$42,"")
A218: =IF(AND(NOT(ISBLANK(G217)),ISBLANK(G218)),"Reste prévu","") | B218: =IF(AND(NOT(ISBLANK($G217)),ISBLANK($G218)),$C$42-$F$40-$F$42,"") | C218: =IF(AND(NOT(ISBLANK($G217)),ISBLANK($G218)),"Reste réel","") | D218: =IF(AND(NOT(ISBLANK($G217)),ISBLANK($G218)),$C$42-$H$40-$F$42,"")
...

Sheet Aout 2026
B1: Recettes | E1: Dépenses | K1: Cadeau
B3: Salaire Pierre | C3: 5393.99 | E3: Loyer Elouen | F3: 669.7 | G3: x | H3: =IF(G3="x",F3,0) -> 669.7 | K3: Logement
B4: Salaire Sterenn | C4: 1828.73 | E4: Argent de poche Elouen | H4: =IF(G4="x",F4,0) -> 0 | K4: Charges
B5: CAF | C5: 114.19 | E5: Engie Elouen | F5: 70 | G5: x | H5: =IF(G5="x",F5,0) -> 70 | K5: Charges
E6: Argent de poche Arthur | F6: 14.99 | G6: x | H6: =IF(G6="x",F6,0) -> 14.99 | K6: Charges
E7: Prêt 25 | F7: 995.15 | G7: x | H7: =IF(G7="x",F7,0) -> 995.15 | K7: Logement
E8: Prêt 15 | F8: 883.42 | G8: x | H8: =IF(G8="x",F8,0) -> 883.42 | K8: Logement
B9: Remboursement Leroy | C9: 27.06 | E9: Assurances prêt | F9: 11.46 | G9: x | H9: =IF(G9="x",F9,0) -> 11.46 | K9: Logement
B10: Epargne Travaux | C10: 742 | E10: Assurances prêt | F10: 32.57 | G10: x | H10: =IF(G10="x",F10,0) -> 32.57 | K10: Logement
B11: Epargne Travaux | C11: 520 | E11: Assurances prêt | F11: 79.98 | G11: x | H11: =IF(G11="x",F11,0) -> 79.98 | K11: Logement
B12: Remboursement Axa | C12: 264.09 | E12: Assurances prêt | F12: 28.49 | G12: x | H12: =IF(G12="x",F12,0) -> 28.49 | K12: Logement
B13: Remboursement Notaire | C13: 789.8 | E13: Disney | F13: 6.99 | G13: x | H13: =IF(G13="x",F13,0) -> 6.99 | K13: Internet/Téléphone
B14: Epargne Compresseur | C14: 523.7 | E14: EDF Arthur | F14: 65 | H14: =IF(G14="x",F14,0) -> 0 | K14: Charges
B15: Scolarité Pret Arthur | C15: 726.96 | E15: EkWateur | F15: 208 | G15: x | H15: =IF(G15="x",F15,0) -> 208 | K15: Charges
E16: Sosh Maison | F16: 24.99 | G16: x | H16: =IF(G16="x",F16,0) -> 24.99 | K16: Internet/Téléphone
H17: =IF(G17="x",F17,0) -> 0 | K17: Internet/Téléphone
E18: Sosh Ael | F18: 14.99 | G18: x | H18: =IF(G18="x",F18,0) -> 14.99 | K18: Internet/Téléphone
E19: Sosh Elouen | F19: 14.99 | G19: x | H19: =IF(G19="x",F19,0) -> 14.99 | K19: Internet/Téléphone
E20: Sosh Sterenn | F20: 10.99 | G20: x | H20: =IF(G20="x",F20,0) -> 10.99 | K20: Internet/Téléphone
E21: Mutuelle | F21: 104.98 | G21: x | H21: =IF(G21="x",F21,0) -> 104.98 | K21: Assurances/Mutuelle
E23: AxaHabitation | F23: 62.88 | G23: x | H23: =IF(G23="x",F23,0) -> 62.88 | K23: Assurances/Mutuelle
E24: VW LDD | F24: 331.65 | G24: x | H24: =IF(G24="x",F24,0) -> 331.65 | K24: Voiture/Déplacement
E25: Axa Voiture | F25: 88.03 | G25: x | H25: =IF(G25="x",F25,0) -> 88.03 | K25: Assurances/Mutuelle
E26: Suravenir Garanties Vie | F26: 18.99 | G26: x | H26: =IF(G26="x",F26,0) -> 18.99 | K26: Assurances/Mutuelle
E27: Joséphine | F27: 20 | G27: x | H27: =IF(G27="x",F27,0) -> 20 | K27: Divers
E28: Canal Plus | F28: 21.99 | G28: x | H28: =IF(G28="x",F28,0) -> 21.99 | K28: Internet/Téléphone
H29: =IF(G29="x",F29,0) -> 0 | K29: Voiture/Déplacement
E30: Keolis Elouen | F30: 21.4 | G30: x | H30: =IF(G30="x",F30,0) -> 21.4 | K30: Voiture/Déplacement
E31: Apple | F31: 0.99 | G31: x | H31: =IF(G31="x",F31,0) -> 0.99 | K31: Internet/Téléphone
E32: Apple | F32: 0.99 | G32: x | H32: =IF(G32="x",F32,0) -> 0.99 | K32: Internet/Téléphone
E33: Apple | F33: 16.99 | G33: x | H33: =IF(G33="x",F33,0) -> 16.99 | K33: Internet/Téléphone
E34: St Charles | F34: 278.3 | H34: =IF(G34="x",F34,0) -> 0 | K34: Scolarité
E35: Ménage | F35: 170 | H35: =IF(G35="x",F35,0) -> 0 | K35: Logement
E36: Urssaaf | F36: 129.86 | G36: x | H36: =IF(G36="x",F36,0) -> 129.86 | K36: Logement
E37: Cotisation Eurocompte | F37: 19.03 | G37: x | H37: =IF(G37="x",F37,0) -> 19.03 | K37: Charges
E38: Indivision | F38: 33.89 | G38: x | H38: =IF(G38="x",F38,0) -> 33.89 | K38: Charges
A39: Etat mois précédent | C39: ='Juillet 2026'!D43 -> #REF!
A40: Recettes fixes | C40: =SUM(C2:C6) -> 7336.91 | E40: Somme dépenses prévues | F40: =SUM(F2:F38) -> 4451.68 | G40: Somme dépenses réelles | H40: =SUM(H2:H38) -> 3938.38 | I40: Delta moins les exceptions
A41: Recettes additionnelles du mois | C41: =SUM(C8:C35) -> 3593.61 | E41: Reste previsionnel | F41: =C42-F40 -> #REF! | G41: Delta du mois | H41: =C39+C40+C41-H40-F42 -> #REF!
A42: Total Recettes | C42: =SUM(C39:C41) -> #REF! | E42: Somme dépenses non prévues | F42: =SUM(J44:J249) -> 7214.47
A43: Reste prévu | B43: =$C$42-$F$40-$F$42 -> #REF! | C43: Reste réel | D43: =$C$42-$H$40-$F$42 -> #REF!
A44: =IF(AND(NOT(ISBLANK(#REF!)),ISBLANK(G44)),"Reste prévu","") -> Reste prévu | B44: =IF(AND(NOT(ISBLANK(#REF!)),ISBLANK($G44)),$C$42-$F$40-$F$42,"") -> #REF! | C44: =IF(AND(NOT(ISBLANK(#REF!)),ISBLANK($G44)),"Reste réel","") -> Reste réel | D44: =IF(AND(NOT(ISBLANK(#REF!)),ISBLANK($G44)),$C$42-$H$40-$F$42,"") -> #REF! | J44: =IF(I44="x",H44,0) -> 0 | K44: Loisirs
A45: =IF(AND(NOT(ISBLANK(G44)),ISBLANK(G45)),"Reste prévu","") | B45: =IF(AND(NOT(ISBLANK($G44)),ISBLANK($G45)),$C$42-$F$40-$F$42,"") | C45: =IF(AND(NOT(ISBLANK($G44)),ISBLANK($G45)),"Reste réel","") | D45: =IF(AND(NOT(ISBLANK($G44)),ISBLANK($G45)),$C$42-$H$40-$F$42,"") | G45: Mademoiselle | H45: 146 | I45: x | J45: =IF(I45="x",H45,0) -> 146 | K45: Vêtements
A46: =IF(AND(NOT(ISBLANK(G45)),ISBLANK(G46)),"Reste prévu","") | B46: =IF(AND(NOT(ISBLANK($G45)),ISBLANK($G46)),$C$42-$F$40-$F$42,"") | C46: =IF(AND(NOT(ISBLANK($G45)),ISBLANK($G46)),"Reste réel","") | D46: =IF(AND(NOT(ISBLANK($G45)),ISBLANK($G46)),$C$42-$H$40-$F$42,"") | G46: Maryannick | H46: 21.9 | I46: x | J46: =IF(I46="x",H46,0) -> 21.9 | K46: Vêtements
A47: =IF(AND(NOT(ISBLANK(G46)),ISBLANK(G47)),"Reste prévu","") | B47: =IF(AND(NOT(ISBLANK($G46)),ISBLANK($G47)),$C$42-$F$40-$F$42,"") | C47: =IF(AND(NOT(ISBLANK($G46)),ISBLANK($G47)),"Reste réel","") | D47: =IF(AND(NOT(ISBLANK($G46)),ISBLANK($G47)),$C$42-$H$40-$F$42,"") | G47: Buvette Estivales | H47: 14 | I47: x | J47: =IF(I47="x",H47,0) -> 14 | K47: Loisirs
A48: =IF(AND(NOT(ISBLANK(G47)),ISBLANK(G48)),"Reste prévu","") | B48: =IF(AND(NOT(ISBLANK($G47)),ISBLANK($G48)),$C$42-$F$40-$F$42,"") | C48: =IF(AND(NOT(ISBLANK($G47)),ISBLANK($G48)),"Reste réel","") | D48: =IF(AND(NOT(ISBLANK($G47)),ISBLANK($G48)),$C$42-$H$40-$F$42,"") | G48: Panzini | H48: 25 | I48: x | J48: =IF(I48="x",H48,0) -> 25 | K48: Vêtements
A49: =IF(AND(NOT(ISBLANK(G48)),ISBLANK(G49)),"Reste prévu","") | B49: =IF(AND(NOT(ISBLANK($G48)),ISBLANK($G49)),$C$42-$F$40-$F$42,"") | C49: =IF(AND(NOT(ISBLANK($G48)),ISBLANK($G49)),"Reste réel","") | D49: =IF(AND(NOT(ISBLANK($G48)),ISBLANK($G49)),$C$42-$H$40-$F$42,"") | G49: Boulangerie | H49: 13.2 | I49: x | J49: =IF(I49="x",H49,0) -> 13.2 | K49: Courses
A50: =IF(AND(NOT(ISBLANK(G49)),ISBLANK(G50)),"Reste prévu","") | B50: =IF(AND(NOT(ISBLANK($G49)),ISBLANK($G50)),$C$42-$F$40-$F$42,"") | C50: =IF(AND(NOT(ISBLANK($G49)),ISBLANK($G50)),"Reste réel","") | D50: =IF(AND(NOT(ISBLANK($G49)),ISBLANK($G50)),$C$42-$H$40-$F$42,"") | G50: Leclerc | H50: 48.21 | I50: x | J50: =IF(I50="x",H50,0) -> 48.21 | K50: Courses
A51: =IF(AND(NOT(ISBLANK(G50)),ISBLANK(G51)),"Reste prévu","") | B51: =IF(AND(NOT(ISBLANK($G50)),ISBLANK($G51)),$C$42-$F$40-$F$42,"") | C51: =IF(AND(NOT(ISBLANK($G50)),ISBLANK($G51)),"Reste réel","") | D51: =IF(AND(NOT(ISBLANK($G50)),ISBLANK($G51)),$C$42-$H$40-$F$42,"") | G51: Mr Bricolage | H51: 23.85 | I51: x | J51: =IF(I51="x",H51,0) -> 23.85 | K51: Bricolage/Travaux
A52: =IF(AND(NOT(ISBLANK(G51)),ISBLANK(G52)),"Reste prévu","") | B52: =IF(AND(NOT(ISBLANK($G51)),ISBLANK($G52)),$C$42-$F$40-$F$42,"") | C52: =IF(AND(NOT(ISBLANK($G51)),ISBLANK($G52)),"Reste réel","") | D52: =IF(AND(NOT(ISBLANK($G51)),ISBLANK($G52)),$C$42-$H$40-$F$42,"") | G52: ChargeMap | H52: 8.76 | I52: x | J52: =IF(I52="x",H52,0) -> 8.76 | K52: Voiture/Déplacement
A53: =IF(AND(NOT(ISBLANK(G52)),ISBLANK(G53)),"Reste prévu","") | B53: =IF(AND(NOT(ISBLANK($G52)),ISBLANK($G53)),$C$42-$F$40-$F$42,"") | C53: =IF(AND(NOT(ISBLANK($G52)),ISBLANK($G53)),"Reste réel","") | D53: =IF(AND(NOT(ISBLANK($G52)),ISBLANK($G53)),$C$42-$H$40-$F$42,"") | G53: Pharmacie | H53: 78.7 | I53: x | J53: =IF(I53="x",H53,0) -> 78.7 | K53: Medical
A54: =IF(AND(NOT(ISBLANK(G53)),ISBLANK(G54)),"Reste prévu","") | B54: =IF(AND(NOT(ISBLANK($G53)),ISBLANK($G54)),$C$42-$F$40-$F$42,"") | C54: =IF(AND(NOT(ISBLANK($G53)),ISBLANK($G54)),"Reste réel","") | D54: =IF(AND(NOT(ISBLANK($G53)),ISBLANK($G54)),$C$42-$H$40-$F$42,"") | G54: Ikea | H54: 60.91 | I54: x | J54: =IF(I54="x",H54,0) -> 60.91 | K54: Bricolage/Travaux
A55: =IF(AND(NOT(ISBLANK(G54)),ISBLANK(G55)),"Reste prévu","") | B55: =IF(AND(NOT(ISBLANK($G54)),ISBLANK($G55)),$C$42-$F$40-$F$42,"") | C55: =IF(AND(NOT(ISBLANK($G54)),ISBLANK($G55)),"Reste réel","") | D55: =IF(AND(NOT(ISBLANK($G54)),ISBLANK($G55)),$C$42-$H$40-$F$42,"") | G55: Mr Bricolage | H55: 11.9 | I55: x | J55: =IF(I55="x",H55,0) -> 11.9 | K55: Bricolage/Travaux
A56: =IF(AND(NOT(ISBLANK(G55)),ISBLANK(G56)),"Reste prévu","") | B56: =IF(AND(NOT(ISBLANK($G55)),ISBLANK($G56)),$C$42-$F$40-$F$42,"") | C56: =IF(AND(NOT(ISBLANK($G55)),ISBLANK($G56)),"Reste réel","") | D56: =IF(AND(NOT(ISBLANK($G55)),ISBLANK($G56)),$C$42-$H$40-$F$42,"") | G56: Cigarettes | H56: 13 | I56: x | J56: =IF(I56="x",H56,0) -> 13 | K56: Divers
... A78: =IF(AND(NOT(ISBLANK(G77)),ISBLANK(G78)),"Reste prévu","") | B78: =IF(AND(NOT(ISBLANK($G77)),ISBLANK($G78)),$C$42-$F$40-$F$42,"") | C78: =IF(AND(NOT(ISBLANK($G77)),ISBLANK($G78)),"Reste réel","") | D78: =IF(AND(NOT(ISBLANK($G77)),ISBLANK($G78)),$C$42-$H$40-$F$42,"") | G78: Leclerc | H78: 6.51 | I78: x | J78: =IF(I78="x",H78,0) -> 6.51 | K78: Courses
G79: Pharmacie | H79: 15.4 | I79: x | J79: =IF(I79="x",H79,0) -> 15.4 | K79: Medical
A80: =IF(AND(NOT(ISBLANK(G78)),ISBLANK(G80)),"Reste prévu","") | B80: =IF(AND(NOT(ISBLANK($G78)),ISBLANK($G80)),$C$42-$F$40-$F$42,"") | C80: =IF(AND(NOT(ISBLANK($G78)),ISBLANK($G80)),"Reste réel","") | D80: =IF(AND(NOT(ISBLANK($G78)),ISBLANK($G80)),$C$42-$H$40-$F$42,"") | G80: Boulangerie | H80: 6.5 | I80: x | J80: =IF(I80="x",H80,0) -> 6.5 | K80: Courses
A81: =IF(AND(NOT(ISBLANK(G80)),ISBLANK(G81)),"Reste prévu","") | B81: =IF(AND(NOT(ISBLANK($G80)),ISBLANK($G81)),$C$42-$F$40-$F$42,"") | C81: =IF(AND(NOT(ISBLANK($G80)),ISBLANK($G81)),"Reste réel","") | D81: =IF(AND(NOT(ISBLANK($G80)),ISBLANK($G81)),$C$42-$H$40-$F$42,"") | G81: Biscuiterie | H81: 54.3 | I81: x | J81: =IF(I81="x",H81,0) -> 54.3 | K81: Courses
A82: =IF(AND(NOT(ISBLANK(G81)),ISBLANK(G82)),"Reste prévu","") | B82: =IF(AND(NOT(ISBLANK($G81)),ISBLANK($G82)),$C$42-$F$40-$F$42,"") | C82: =IF(AND(NOT(ISBLANK($G81)),ISBLANK($G82)),"Reste réel","") | D82: =IF(AND(NOT(ISBLANK($G81)),ISBLANK($G82)),$C$42-$H$40-$F$42,"") | G82: Leclerc | H82: 11.78 | I82: x | J82: =IF(I82="x",H82,0) -> 11.78 | K82: Courses
A83: =IF(AND(NOT(ISBLANK(G82)),ISBLANK(G83)),"Reste prévu","") | B83: =IF(AND(NOT(ISBLANK($G82)),ISBLANK($G83)),$C$42-$F$40-$F$42,"") | C83: =IF(AND(NOT(ISBLANK($G82)),ISBLANK($G83)),"Reste réel","") | D83: =IF(AND(NOT(ISBLANK($G82)),ISBLANK($G83)),$C$42-$H$40-$F$42,"") | G83: Cigarettes | H83: 13 | I83: x | J83: =IF(I83="x",H83,0) -> 13 | K83: Divers
A84: =IF(AND(NOT(ISBLANK(G83)),ISBLANK(G84)),"Reste prévu","") | B84: =IF(AND(NOT(ISBLANK($G83)),ISBLANK($G84)),$C$42-$F$40-$F$42,"") | C84: =IF(AND(NOT(ISBLANK($G83)),ISBLANK($G84)),"Reste réel","") | D84: =IF(AND(NOT(ISBLANK($G83)),ISBLANK($G84)),$C$42-$H$40-$F$42,"") | G84: Arthur Rennes | H84: 50 | I84: x | J84: =IF(I84="x",H84,0) -> 50 | K84: Courses
A85: =IF(AND(NOT(ISBLANK(G84)),ISBLANK(G85)),"Reste prévu","") | B85: =IF(AND(NOT(ISBLANK($G84)),ISBLANK($G85)),$C$42-$F$40-$F$42,"") | C85: =IF(AND(NOT(ISBLANK($G84)),ISBLANK($G85)),"Reste réel","") | D85: =IF(AND(NOT(ISBLANK($G84)),ISBLANK($G85)),$C$42-$H$40-$F$42,"") | G85: Leclerc | H85: 33.49 | I85: x | J85: =IF(I85="x",H85,0) -> 33.49 | K85: Courses
A86: =IF(AND(NOT(ISBLANK(G85)),ISBLANK(G86)),"Reste prévu","") | B86: =IF(AND(NOT(ISBLANK($G85)),ISBLANK($G86)),$C$42-$F$40-$F$42,"") | C86: =IF(AND(NOT(ISBLANK($G85)),ISBLANK($G86)),"Reste réel","") | D86: =IF(AND(NOT(ISBLANK($G85)),ISBLANK($G86)),$C$42-$H$40-$F$42,"") | G86: Leclerc | H86: 43.24 | I86: x | J86: =IF(I86="x",H86,0) -> 43.24 | K86: Courses
G87: Train Arthur | H87: 19.6 | I87: x | J87: =IF(I87="x",H87,0) -> 19.6 | K87: Voiture/Déplacement
G88: Leclerc | H88: 180.89 | I88: x | J88: =IF(I88="x",H88,0) -> 180.89 | K88: Courses
A89: =IF(AND(NOT(ISBLANK(G86)),ISBLANK(G89)),"Reste prévu","") | B89: =IF(AND(NOT(ISBLANK($G86)),ISBLANK($G89)),$C$42-$F$40-$F$42,"") | C89: =IF(AND(NOT(ISBLANK($G86)),ISBLANK($G89)),"Reste réel","") | D89: =IF(AND(NOT(ISBLANK($G86)),ISBLANK($G89)),$C$42-$H$40-$F$42,"") | G89: Elouen Psy | H89: 180 | I89: x | J89: =IF(I89="x",H89,0) -> 180 | K89: Medical
A90: =IF(AND(NOT(ISBLANK(G89)),ISBLANK(G90)),"Reste prévu","") | B90: =IF(AND(NOT(ISBLANK($G89)),ISBLANK($G90)),$C$42-$F$40-$F$42,"") | C90: =IF(AND(NOT(ISBLANK($G89)),ISBLANK($G90)),"Reste réel","") | D90: =IF(AND(NOT(ISBLANK($G89)),ISBLANK($G90)),$C$42-$H$40-$F$42,"") | G90: Lunette | H90: 149 | I90: x | J90: =IF(I90="x",H90,0) -> 149 | K90: Medical
A91: =IF(AND(NOT(ISBLANK(G90)),ISBLANK(G91)),"Reste prévu","") | B91: =IF(AND(NOT(ISBLANK($G90)),ISBLANK($G91)),$C$42-$F$40-$F$42,"") | C91: =IF(AND(NOT(ISBLANK($G90)),ISBLANK($G91)),"Reste réel","") | D91: =IF(AND(NOT(ISBLANK($G90)),ISBLANK($G91)),$C$42-$H$40-$F$42,"") | G91: Epargne | H91: 700 | I91: x | J91: =IF(I91="x",H91,0) -> 700 | K91: Divers
A92: =IF(AND(NOT(ISBLANK(G91)),ISBLANK(G92)),"Reste prévu","") | B92: =IF(AND(NOT(ISBLANK($G91)),ISBLANK($G92)),$C$42-$F$40-$F$42,"") | C92: =IF(AND(NOT(ISBLANK($G91)),ISBLANK($G92)),"Reste réel","") | D92: =IF(AND(NOT(ISBLANK($G91)),ISBLANK($G92)),$C$42-$H$40-$F$42,"") | G92: Boulangerie | H92: 5.2 | I92: x | J92: =IF(I92="x",H92,0) -> 5.2 | K92: Courses
A93: =IF(AND(NOT(ISBLANK(G92)),ISBLANK(G93)),"Reste prévu","") | B93: =IF(AND(NOT(ISBLANK($G92)),ISBLANK($G93)),$C$42-$F$40-$F$42,"") | C93: =IF(AND(NOT(ISBLANK($G92)),ISBLANK($G93)),"Reste réel","") | D93: =IF(AND(NOT(ISBLANK($G92)),ISBLANK($G93)),$C$42-$H$40-$F$42,"") | G93: VSM | H93: 23.3 | I93: x | J93: =IF(I93="x",H93,0) -> 23.3 | K93: Courses
A94: =IF(AND(NOT(ISBLANK(G93)),ISBLANK(G94)),"Reste prévu","") | B94: =IF(AND(NOT(ISBLANK($G93)),ISBLANK($G94)),$C$42-$F$40-$F$42,"") | C94: =IF(AND(NOT(ISBLANK($G93)),ISBLANK($G94)),"Reste réel","") | D94: =IF(AND(NOT(ISBLANK($G93)),ISBLANK($G94)),$C$42-$H$40-$F$42,"") | G94: PPG | H94: 46.4 | I94: x | J94: =IF(I94="x",H94,0) -> 46.4 | K94: Vêtements
A95: =IF(AND(NOT(ISBLANK(G94)),ISBLANK(G95)),"Reste prévu","") | B95: =IF(AND(NOT(ISBLANK($G94)),ISBLANK($G95)),$C$42-$F$40-$F$42,"") | C95: =IF(AND(NOT(ISBLANK($G94)),ISBLANK($G95)),"Reste réel","") | D95: =IF(AND(NOT(ISBLANK($G94)),ISBLANK($G95)),$C$42-$H$40-$F$42,"") | G95: Leclerc | H95: 8 | I95: x | J95: =IF(I95="x",H95,0) -> 8 | K95: Courses
A96: =IF(AND(NOT(ISBLANK(G95)),ISBLANK(G96)),"Reste prévu","") | B96: =IF(AND(NOT(ISBLANK($G95)),ISBLANK($G96)),$C$42-$F$40-$F$42,"") | C96: =IF(AND(NOT(ISBLANK($G95)),ISBLANK($G96)),"Reste réel","") | D96: =IF(AND(NOT(ISBLANK($G95)),ISBLANK($G96)),$C$42-$H$40-$F$42,"") | G96: Leclerc | H96: 59.88 | I96: x | J96: =IF(I96="x",H96,0) -> 59.88 | K96: Courses
A97: =IF(AND(NOT(ISBLANK(G96)),ISBLANK(G97)),"Reste prévu","") | B97: =IF(AND(NOT(ISBLANK($G96)),ISBLANK($G97)),$C$42-$F$40-$F$42,"") | C97: =IF(AND(NOT(ISBLANK($G96)),ISBLANK($G97)),"Reste réel","") | D97: =IF(AND(NOT(ISBLANK($G96)),ISBLANK($G97)),$C$42-$H$40-$F$42,"") | G97: Boulangerie | H97: 15.2 | I97: x | J97: =IF(I97="x",H97,0) -> 15.2 | K97: Courses
A98: =IF(AND(NOT(ISBLANK(G97)),ISBLANK(G98)),"Reste prévu","") | B98: =IF(AND(NOT(ISBLANK($G97)),ISBLANK($G98)),$C$42-$F$40-$F$42,"") | C98: =IF(AND(NOT(ISBLANK($G97)),ISBLANK($G98)),"Reste réel","") | D98: =IF(AND(NOT(ISBLANK($G97)),ISBLANK($G98)),$C$42-$H$40-$F$42,"") | G98: Bevan | H98: 27.1 | I98: x | J98: =IF(I98="x",H98,0) -> 27.1 | K98: Loisirs
A99: =IF(AND(NOT(ISBLANK(G98)),ISBLANK(G99)),"Reste prévu","") | B99: =IF(AND(NOT(ISBLANK($G98)),ISBLANK($G99)),$C$42-$F$40-$F$42,"") | C99: =IF(AND(NOT(ISBLANK($G98)),ISBLANK($G99)),"Reste réel","") | D99: =IF(AND(NOT(ISBLANK($G98)),ISBLANK($G99)),$C$42-$H$40-$F$42,"") | G99: Baramoules | H99: 127.9 | I99: x | J99: =IF(I99="x",H99,0) -> 127.9 | K99: Loisirs
A100: =IF(AND(NOT(ISBLANK(G99)),ISBLANK(G100)),"Reste prévu","") | B100: =IF(AND(NOT(ISBLANK($G99)),ISBLANK($G100)),$C$42-$F$40-$F$42,"") | C100: =IF(AND(NOT(ISBLANK($G99)),ISBLANK($G100)),"Reste réel","") | D100: =IF(AND(NOT(ISBLANK($G99)),ISBLANK($G100)),$C$42-$H$40-$F$42,"") | G100: Cagnotte Pascal | H100: 30 | I100: x | J100: =IF(I100="x",H100,0) -> 30 | K100: Divers
A101: =IF(AND(NOT(ISBLANK(G100)),ISBLANK(G101)),"Reste prévu","") | B101: =IF(AND(NOT(ISBLANK($G100)),ISBLANK($G101)),$C$42-$F$40-$F$42,"") | C101: =IF(AND(NOT(ISBLANK($G100)),ISBLANK($G101)),"Reste réel","") | D101: =IF(AND(NOT(ISBLANK($G100)),ISBLANK($G101)),$C$42-$H$40-$F$42,"") | G101: Librairie | H101: 8.9 | I101: x | J101: =IF(I101="x",H101,0) -> 8.9 | K101: Loisirs
... A153: =IF(AND(NOT(ISBLANK(G152)),ISBLANK(G153)),"Reste prévu","") | B153: =IF(AND(NOT(ISBLANK($G152)),ISBLANK($G153)),$C$42-$F$40-$F$42,"") | C153: =IF(AND(NOT(ISBLANK($G152)),ISBLANK($G153)),"Reste réel","") | D153: =IF(AND(NOT(ISBLANK($G152)),ISBLANK($G153)),$C$42-$H$40-$F$42,"") | G153: Boulangerie | H153: 20 | I153: x | J153: =IF(I153="x",H153,0) -> 20 | K153: Courses
A154: =IF(AND(NOT(ISBLANK(G153)),ISBLANK(G154)),"Reste prévu","") -> Reste prévu | B154: =IF(AND(NOT(ISBLANK($G153)),ISBLANK($G154)),$C$42-$F$40-$F$42,"") -> #REF! | C154: =IF(AND(NOT(ISBLANK($G153)),ISBLANK($G154)),"Reste réel","") -> Reste réel | D154: =IF(AND(NOT(ISBLANK($G153)),ISBLANK($G154)),$C$42-$H$40-$F$42,"") -> #REF! | J154: =IF(I154="x",H154,0) -> 0 | K154: Bricolage/Travaux
A155: =IF(AND(NOT(ISBLANK(G154)),ISBLANK(G155)),"Reste prévu","") | B155: =IF(AND(NOT(ISBLANK($G154)),ISBLANK($G155)),$C$42-$F$40-$F$42,"") | C155: =IF(AND(NOT(ISBLANK($G154)),ISBLANK($G155)),"Reste réel","") | D155: =IF(AND(NOT(ISBLANK($G154)),ISBLANK($G155)),$C$42-$H$40-$F$42,"") | J155: =IF(I155="x",H155,0) -> 0 | K155: Loisirs
A156: =IF(AND(NOT(ISBLANK(G155)),ISBLANK(G156)),"Reste prévu","") | B156: =IF(AND(NOT(ISBLANK($G155)),ISBLANK($G156)),$C$42-$F$40-$F$42,"") | C156: =IF(AND(NOT(ISBLANK($G155)),ISBLANK($G156)),"Reste réel","") | D156: =IF(AND(NOT(ISBLANK($G155)),ISBLANK($G156)),$C$42-$H$40-$F$42,"") | J156: =IF(I156="x",H156,0) -> 0 | K156: Bricolage/Travaux
A157: =IF(AND(NOT(ISBLANK(G156)),ISBLANK(G157)),"Reste prévu","") | B157: =IF(AND(NOT(ISBLANK($G156)),ISBLANK($G157)),$C$42-$F$40-$F$42,"") | C157: =IF(AND(NOT(ISBLANK($G156)),ISBLANK($G157)),"Reste réel","") | D157: =IF(AND(NOT(ISBLANK($G156)),ISBLANK($G157)),$C$42-$H$40-$F$42,"") | J157: =IF(I157="x",H157,0) -> 0 | K157: Charges
A158: =IF(AND(NOT(ISBLANK(G157)),ISBLANK(G158)),"Reste prévu","") | B158: =IF(AND(NOT(ISBLANK($G157)),ISBLANK($G158)),$C$42-$F$40-$F$42,"") | C158: =IF(AND(NOT(ISBLANK($G157)),ISBLANK($G158)),"Reste réel","") | D158: =IF(AND(NOT(ISBLANK($G157)),ISBLANK($G158)),$C$42-$H$40-$F$42,"") | J158: =IF(I158="x",H158,0) -> 0
A159: =IF(AND(NOT(ISBLANK(G158)),ISBLANK(G159)),"Reste prévu","") | B159: =IF(AND(NOT(ISBLANK($G158)),ISBLANK($G159)),$C$42-$F$40-$F$42,"") | C159: =IF(AND(NOT(ISBLANK($G158)),ISBLANK($G159)),"Reste réel","") | D159: =IF(AND(NOT(ISBLANK($G158)),ISBLANK($G159)),$C$42-$H$40-$F$42,"") | J159: =IF(I159="x",H159,0) -> 0
A160: =IF(AND(NOT(ISBLANK(G159)),ISBLANK(G160)),"Reste prévu","") | B160: =IF(AND(NOT(ISBLANK($G159)),ISBLANK($G160)),$C$42-$F$40-$F$42,"") | C160: =IF(AND(NOT(ISBLANK($G159)),ISBLANK($G160)),"Reste réel","") | D160: =IF(AND(NOT(ISBLANK($G159)),ISBLANK($G160)),$C$42-$H$40-$F$42,"") | J160: =IF(I160="x",H160,0) -> 0
A161: =IF(AND(NOT(ISBLANK(G160)),ISBLANK(G161)),"Reste prévu","") | B161: =IF(AND(NOT(ISBLANK($G160)),ISBLANK($G161)),$C$42-$F$40-$F$42,"") | C161: =IF(AND(NOT(ISBLANK($G160)),ISBLANK($G161)),"Reste réel","") | D161: =IF(AND(NOT(ISBLANK($G160)),ISBLANK($G161)),$C$42-$H$40-$F$42,"") | J161: =IF(I161="x",H161,0) -> 0
A162: =IF(AND(NOT(ISBLANK(G161)),ISBLANK(G162)),"Reste prévu","") | B162: =IF(AND(NOT(ISBLANK($G161)),ISBLANK($G162)),$C$42-$F$40-$F$42,"") | C162: =IF(AND(NOT(ISBLANK($G161)),ISBLANK($G162)),"Reste réel","") | D162: =IF(AND(NOT(ISBLANK($G161)),ISBLANK($G162)),$C$42-$H$40-$F$42,"") | J162: =IF(I162="x",H162,0) -> 0
A163: =IF(AND(NOT(ISBLANK(G162)),ISBLANK(G163)),"Reste prévu","") | B163: =IF(AND(NOT(ISBLANK($G162)),ISBLANK($G163)),$C$42-$F$40-$F$42,"") | C163: =IF(AND(NOT(ISBLANK($G162)),ISBLANK($G163)),"Reste réel","") | D163: =IF(AND(NOT(ISBLANK($G162)),ISBLANK($G163)),$C$42-$H$40-$F$42,"") | J163: =IF(I163="x",H163,0) -> 0
A164: =IF(AND(NOT(ISBLANK(G163)),ISBLANK(G164)),"Reste prévu","") | B164: =IF(AND(NOT(ISBLANK($G163)),ISBLANK($G164)),$C$42-$F$40-$F$42,"") | C164: =IF(AND(NOT(ISBLANK($G163)),ISBLANK($G164)),"Reste réel","") | D164: =IF(AND(NOT(ISBLANK($G163)),ISBLANK($G164)),$C$42-$H$40-$F$42,"") | J164: =IF(I164="x",H164,0) -> 0
A165: =IF(AND(NOT(ISBLANK(G164)),ISBLANK(G165)),"Reste prévu","") | B165: =IF(AND(NOT(ISBLANK($G164)),ISBLANK($G165)),$C$42-$F$40-$F$42,"") | C165: =IF(AND(NOT(ISBLANK($G164)),ISBLANK($G165)),"Reste réel","") | D165: =IF(AND(NOT(ISBLANK($G164)),ISBLANK($G165)),$C$42-$H$40-$F$42,"") | J165: =IF(I165="x",H165,0) -> 0
A166: =IF(AND(NOT(ISBLANK(G165)),ISBLANK(G166)),"Reste prévu","") | B166: =IF(AND(NOT(ISBLANK($G165)),ISBLANK($G166)),$C$42-$F$40-$F$42,"") | C166: =IF(AND(NOT(ISBLANK($G165)),ISBLANK($G166)),"Reste réel","") | D166: =IF(AND(NOT(ISBLANK($G165)),ISBLANK($G166)),$C$42-$H$40-$F$42,"") | J166: =IF(I166="x",H166,0) -> 0
A167: =IF(AND(NOT(ISBLANK(G166)),ISBLANK(G167)),"Reste prévu","") | B167: =IF(AND(NOT(ISBLANK($G166)),ISBLANK($G167)),$C$42-$F$40-$F$42,"") | C167: =IF(AND(NOT(ISBLANK($G166)),ISBLANK($G167)),"Reste réel","") | D167: =IF(AND(NOT(ISBLANK($G166)),ISBLANK($G167)),$C$42-$H$40-$F$42,"") | J167: =IF(I167="x",H167,0) -> 0
A168: =IF(AND(NOT(ISBLANK(G167)),ISBLANK(G168)),"Reste prévu","") | B168: =IF(AND(NOT(ISBLANK($G167)),ISBLANK($G168)),$C$42-$F$40-$F$42,"") | C168: =IF(AND(NOT(ISBLANK($G167)),ISBLANK($G168)),"Reste réel","") | D168: =IF(AND(NOT(ISBLANK($G167)),ISBLANK($G168)),$C$42-$H$40-$F$42,"") | J168: =IF(I168="x",H168,0) -> 0
A169: =IF(AND(NOT(ISBLANK(G168)),ISBLANK(G169)),"Reste prévu","") | B169: =IF(AND(NOT(ISBLANK($G168)),ISBLANK($G169)),$C$42-$F$40-$F$42,"") | C169: =IF(AND(NOT(ISBLANK($G168)),ISBLANK($G169)),"Reste réel","") | D169: =IF(AND(NOT(ISBLANK($G168)),ISBLANK($G169)),$C$42-$H$40-$F$42,"") | J169: =IF(I169="x",H169,0) -> 0
... A216: =IF(AND(NOT(ISBLANK(G215)),ISBLANK(G216)),"Reste prévu","") | B216: =IF(AND(NOT(ISBLANK($G215)),ISBLANK($G216)),$C$42-$F$40-$F$42,"") | C216: =IF(AND(NOT(ISBLANK($G215)),ISBLANK($G216)),"Reste réel","") | D216: =IF(AND(NOT(ISBLANK($G215)),ISBLANK($G216)),$C$42-$H$40-$F$42,"") | J216: =IF(I216="x",H216,0) -> 0
A217: =IF(AND(NOT(ISBLANK(G216)),ISBLANK(G217)),"Reste prévu","") | B217: =IF(AND(NOT(ISBLANK($G216)),ISBLANK($G217)),$C$42-$F$40-$F$42,"") | C217: =IF(AND(NOT(ISBLANK($G216)),ISBLANK($G217)),"Reste réel","") | D217: =IF(AND(NOT(ISBLANK($G216)),ISBLANK($G217)),$C$42-$H$40-$F$42,"")
A218: =IF(AND(NOT(ISBLANK(G217)),ISBLANK(G218)),"Reste prévu","") | B218: =IF(AND(NOT(ISBLANK($G217)),ISBLANK($G218)),$C$42-$F$40-$F$42,"") | C218: =IF(AND(NOT(ISBLANK($G217)),ISBLANK($G218)),"Reste réel","") | D218: =IF(AND(NOT(ISBLANK($G217)),ISBLANK($G218)),$C$42-$H$40-$F$42,"")
A219: =IF(AND(NOT(ISBLANK(G218)),ISBLANK(G219)),"Reste prévu","") | B219: =IF(AND(NOT(ISBLANK($G218)),ISBLANK($G219)),$C$42-$F$40-$F$42,"") | C219: =IF(AND(NOT(ISBLANK($G218)),ISBLANK($G219)),"Reste réel","") | D219: =IF(AND(NOT(ISBLANK($G218)),ISBLANK($G219)),$C$42-$H$40-$F$42,"")
A220: =IF(AND(NOT(ISBLANK(G219)),ISBLANK(G220)),"Reste prévu","") | B220: =IF(AND(NOT(ISBLANK($G219)),ISBLANK($G220)),$C$42-$F$40-$F$42,"") | C220: =IF(AND(NOT(ISBLANK($G219)),ISBLANK($G220)),"Reste réel","") | D220: =IF(AND(NOT(ISBLANK($G219)),ISBLANK($G220)),$C$42-$H$40-$F$42,"")
...

Sheet Juillet 2026
B1: Recettes | E1: Dépenses | K1: Cadeau
B3: Salaire Pierre | C3: 5651.76 | E3: Loyer Elouen | F3: 669.7 | G3: x | H3: =IF(G3="x",F3,0) -> 669.7 | K3: Logement
B4: Salaire Sterenn | C4: 1938.46 | E4: Argent de poche Elouen | H4: =IF(G4="x",F4,0) -> 0 | K4: Charges
B5: CAF | C5: 114.19 | E5: Engie Elouen | F5: 70 | G5: x | H5: =IF(G5="x",F5,0) -> 70 | K5: Charges
E6: Argent de poche Arthur | F6: 14.99 | G6: x | H6: =IF(G6="x",F6,0) -> 14.99 | K6: Charges
E7: Prêt 25 | F7: 995.15 | G7: x | H7: =IF(G7="x",F7,0) -> 995.15 | K7: Logement
B8: Note de frais Igienair | C8: 261.76 | E8: Prêt 15 | F8: 883.42 | G8: x | H8: =IF(G8="x",F8,0) -> 883.42 | K8: Logement
B9: Note de Frais Altran | C9: 69.75 | E9: Assurances prêt | F9: 11.46 | G9: x | H9: =IF(G9="x",F9,0) -> 11.46 | K9: Logement
B10: Pret Arthur Scolarité | C10: 105 | E10: Assurances prêt | F10: 32.57 | G10: x | H10: =IF(G10="x",F10,0) -> 32.57 | K10: Logement
B11: Pret Arthur Scolarité | C11: 178 | E11: Assurances prêt | F11: 79.98 | G11: x | H11: =IF(G11="x",F11,0) -> 79.98 | K11: Logement
B12: Cadeau copains | C12: 580 | E12: Assurances prêt | F12: 28.49 | G12: x | H12: =IF(G12="x",F12,0) -> 28.49 | K12: Logement
B13: Scolarité Arthur/Elouen | C13: 720 | E13: Disney | F13: 6.99 | G13: x | H13: =IF(G13="x",F13,0) -> 6.99 | K13: Internet/Téléphone
B14: Baby Sitting Arthur | C14: 40 | E14: EDF Arthur | F14: 65 | G14: x | H14: =IF(G14="x",F14,0) -> 65 | K14: Charges
B15: Virement Impots | C15: 3165 | E15: EkWateur | F15: 208 | G15: x | H15: =IF(G15="x",F15,0) -> 208 | K15: Charges
E16: Sosh Maison | F16: 24.99 | G16: x | H16: =IF(G16="x",F16,0) -> 24.99 | K16: Internet/Téléphone
E17: Sosh Arthur | F17: 14.99 | G17: x | H17: =IF(G17="x",F17,0) -> 14.99 | K17: Internet/Téléphone
E18: Sosh Ael | F18: 14.99 | H18: =IF(G18="x",F18,0) -> 0 | K18: Internet/Téléphone
E19: Sosh Elouen | F19: 14.99 | G19: x | H19: =IF(G19="x",F19,0) -> 14.99 | K19: Internet/Téléphone
E20: Sosh Sterenn | F20: 10.99 | G20: x | H20: =IF(G20="x",F20,0) -> 10.99 | K20: Internet/Téléphone
E21: Mutuelle | F21: 104.98 | G21: x | H21: =IF(G21="x",F21,0) -> 104.98 | K21: Assurances/Mutuelle
E23: AxaHabitation | F23: 62.88 | G23: x | H23: =IF(G23="x",F23,0) -> 62.88 | K23: Assurances/Mutuelle
E24: VW LDD | F24: 331.65 | G24: x | H24: =IF(G24="x",F24,0) -> 331.65 | K24: Voiture/Déplacement
E25: Axa Voiture | F25: 88.03 | G25: x | H25: =IF(G25="x",F25,0) -> 88.03 | K25: Assurances/Mutuelle
E26: Suravenir Garanties Vie | F26: 18.99 | G26: x | H26: =IF(G26="x",F26,0) -> 18.99 | K26: Assurances/Mutuelle
E27: Joséphine | F27: 20 | G27: x | H27: =IF(G27="x",F27,0) -> 20 | K27: Divers
E28: Canal Plus | F28: 21.99 | G28: x | H28: =IF(G28="x",F28,0) -> 21.99 | K28: Internet/Téléphone
H29: =IF(G29="x",F29,0) -> 0 | K29: Voiture/Déplacement
E30: Keolis Elouen | F30: 21.4 | G30: x | H30: =IF(G30="x",F30,0) -> 21.4 | K30: Voiture/Déplacement
E31: Apple | F31: 0.99 | G31: x | H31: =IF(G31="x",F31,0) -> 0.99 | K31: Internet/Téléphone
E32: Apple | F32: 0.99 | G32: x | H32: =IF(G32="x",F32,0) -> 0.99 | K32: Internet/Téléphone
E33: Apple | F33: 16.99 | G33: x | H33: =IF(G33="x",F33,0) -> 16.99 | K33: Internet/Téléphone
E34: St Charles | F34: 278.3 | G34: x | H34: =IF(G34="x",F34,0) -> 278.3 | K34: Scolarité
E35: Ménage | F35: 170 | G35: x | H35: =IF(G35="x",F35,0) -> 170 | K35: Logement
E36: Urssaaf | F36: 136 | G36: x | H36: =IF(G36="x",F36,0) -> 136 | K36: Logement
E37: Cotisation Eurocompte | F37: 19.03 | G37: x | H37: =IF(G37="x",F37,0) -> 19.03 | K37: Charges
E38: Indivision | F38: 33.89 | G38: x | H38: =IF(G38="x",F38,0) -> 33.89 | K38: Charges
A39: Etat mois précédent | C39: ='Juin 2026'!D43 -> #REF!
A40: Recettes fixes | C40: =SUM(C2:C6) -> 7704.41 | E40: Somme dépenses prévues | F40: =SUM(F2:F38) -> 4472.81 | G40: Somme dépenses réelles | H40: =SUM(H2:H38) -> 4457.82 | I40: Delta moins les exceptions
A41: Recettes additionnelles du mois | C41: =SUM(C8:C35) -> 5119.51 | E41: Reste previsionnel | F41: =C42-F40 -> #REF! | G41: Delta du mois | H41: =C39+C40+C41-H40-F42 -> #REF!
A42: Total Recettes | C42: =SUM(C39:C41) -> #REF! | E42: Somme dépenses non prévues | F42: =SUM(J44:J247) -> 8324.92
A43: Reste prévu | B43: =$C$42-$F$40-$F$42 -> #REF! | C43: Reste réel | D43: =$C$42-$H$40-$F$42 -> #REF!
A44: =IF(AND(NOT(ISBLANK(#REF!)),ISBLANK(G44)),"Reste prévu","") -> Reste prévu | B44: =IF(AND(NOT(ISBLANK(#REF!)),ISBLANK($G44)),$C$42-$F$40-$F$42,"") -> #REF! | C44: =IF(AND(NOT(ISBLANK(#REF!)),ISBLANK($G44)),"Reste réel","") -> Reste réel | D44: =IF(AND(NOT(ISBLANK(#REF!)),ISBLANK($G44)),$C$42-$H$40-$F$42,"") -> #REF! | J44: =IF(I44="x",H44,0) -> 0 | K44: Loisirs
A45: =IF(AND(NOT(ISBLANK(G44)),ISBLANK(G45)),"Reste prévu","") | B45: =IF(AND(NOT(ISBLANK($G44)),ISBLANK($G45)),$C$42-$F$40-$F$42,"") | C45: =IF(AND(NOT(ISBLANK($G44)),ISBLANK($G45)),"Reste réel","") | D45: =IF(AND(NOT(ISBLANK($G44)),ISBLANK($G45)),$C$42-$H$40-$F$42,"") | G45: Feuillette Repas Tregeux | H45: 26.89 | I45: x | J45: =IF(I45="x",H45,0) -> 26.89 | K45: Courses
A46: =IF(AND(NOT(ISBLANK(G45)),ISBLANK(G46)),"Reste prévu","") | B46: =IF(AND(NOT(ISBLANK($G45)),ISBLANK($G46)),$C$42-$F$40-$F$42,"") | C46: =IF(AND(NOT(ISBLANK($G45)),ISBLANK($G46)),"Reste réel","") | D46: =IF(AND(NOT(ISBLANK($G45)),ISBLANK($G46)),$C$42-$H$40-$F$42,"") | G46: Apero BreizhIzel | H46: 4 | I46: x | J46: =IF(I46="x",H46,0) -> 4 | K46: Loisirs
A47: =IF(AND(NOT(ISBLANK(G46)),ISBLANK(G47)),"Reste prévu","") | B47: =IF(AND(NOT(ISBLANK($G46)),ISBLANK($G47)),$C$42-$F$40-$F$42,"") | C47: =IF(AND(NOT(ISBLANK($G46)),ISBLANK($G47)),"Reste réel","") | D47: =IF(AND(NOT(ISBLANK($G46)),ISBLANK($G47)),$C$42-$H$40-$F$42,"") | G47: Apero BreizhIzel | H47: 13.5 | I47: x | J47: =IF(I47="x",H47,0) -> 13.5 | K47: Loisirs
A48: =IF(AND(NOT(ISBLANK(G47)),ISBLANK(G48)),"Reste prévu","") | B48: =IF(AND(NOT(ISBLANK($G47)),ISBLANK($G48)),$C$42-$F$40-$F$42,"") | C48: =IF(AND(NOT(ISBLANK($G47)),ISBLANK($G48)),"Reste réel","") | D48: =IF(AND(NOT(ISBLANK($G47)),ISBLANK($G48)),$C$42-$H$40-$F$42,"") | G48: Apero BreizhIzel | H48: 13.5 | I48: x | J48: =IF(I48="x",H48,0) -> 13.5 | K48: Loisirs
A49: =IF(AND(NOT(ISBLANK(G48)),ISBLANK(G49)),"Reste prévu","") | B49: =IF(AND(NOT(ISBLANK($G48)),ISBLANK($G49)),$C$42-$F$40-$F$42,"") | C49: =IF(AND(NOT(ISBLANK($G48)),ISBLANK($G49)),"Reste réel","") | D49: =IF(AND(NOT(ISBLANK($G48)),ISBLANK($G49)),$C$42-$H$40-$F$42,"") | G49: Apero BreizhIzel | H49: 26.5 | I49: x | J49: =IF(I49="x",H49,0) -> 26.5 | K49: Loisirs
A50: =IF(AND(NOT(ISBLANK(G49)),ISBLANK(G50)),"Reste prévu","") | B50: =IF(AND(NOT(ISBLANK($G49)),ISBLANK($G50)),$C$42-$F$40-$F$42,"") | C50: =IF(AND(NOT(ISBLANK($G49)),ISBLANK($G50)),"Reste réel","") | D50: =IF(AND(NOT(ISBLANK($G49)),ISBLANK($G50)),$C$42-$H$40-$F$42,"") | G50: Apero BreizhIzel | H50: 13.5 | I50: x | J50: =IF(I50="x",H50,0) -> 13.5 | K50: Loisirs
A51: =IF(AND(NOT(ISBLANK(G50)),ISBLANK(G51)),"Reste prévu","") | B51: =IF(AND(NOT(ISBLANK($G50)),ISBLANK($G51)),$C$42-$F$40-$F$42,"") | C51: =IF(AND(NOT(ISBLANK($G50)),ISBLANK($G51)),"Reste réel","") | D51: =IF(AND(NOT(ISBLANK($G50)),ISBLANK($G51)),$C$42-$H$40-$F$42,"") | G51: Metro Rennes | H51: 3.4 | I51: x | J51: =IF(I51="x",H51,0) -> 3.4 | K51: Voiture/Déplacement
A52: =IF(AND(NOT(ISBLANK(G51)),ISBLANK(G52)),"Reste prévu","") | B52: =IF(AND(NOT(ISBLANK($G51)),ISBLANK($G52)),$C$42-$F$40-$F$42,"") | C52: =IF(AND(NOT(ISBLANK($G51)),ISBLANK($G52)),"Reste réel","") | D52: =IF(AND(NOT(ISBLANK($G51)),ISBLANK($G52)),$C$42-$H$40-$F$42,"") | G52: Concert Ael | H52: 131.45 | I52: x | J52: =IF(I52="x",H52,0) -> 131.45 | K52: Loisirs
A53: =IF(AND(NOT(ISBLANK(G52)),ISBLANK(G53)),"Reste prévu","") | B53: =IF(AND(NOT(ISBLANK($G52)),ISBLANK($G53)),$C$42-$F$40-$F$42,"") | C53: =IF(AND(NOT(ISBLANK($G52)),ISBLANK($G53)),"Reste réel","") | D53: =IF(AND(NOT(ISBLANK($G52)),ISBLANK($G53)),$C$42-$H$40-$F$42,"") | G53: Café CapG | H53: 0.5 | I53: x | J53: =IF(I53="x",H53,0) -> 0.5 | K53: Divers
A54: =IF(AND(NOT(ISBLANK(G53)),ISBLANK(G54)),"Reste prévu","") | B54: =IF(AND(NOT(ISBLANK($G53)),ISBLANK($G54)),$C$42-$F$40-$F$42,"") | C54: =IF(AND(NOT(ISBLANK($G53)),ISBLANK($G54)),"Reste réel","") | D54: =IF(AND(NOT(ISBLANK($G53)),ISBLANK($G54)),$C$42-$H$40-$F$42,"") | G54: Boulangerie Rennes | H54: 6.7 | I54: x | J54: =IF(I54="x",H54,0) -> 6.7 | K54: Courses
A55: =IF(AND(NOT(ISBLANK(G54)),ISBLANK(G55)),"Reste prévu","") | B55: =IF(AND(NOT(ISBLANK($G54)),ISBLANK($G55)),$C$42-$F$40-$F$42,"") | C55: =IF(AND(NOT(ISBLANK($G54)),ISBLANK($G55)),"Reste réel","") | D55: =IF(AND(NOT(ISBLANK($G54)),ISBLANK($G55)),$C$42-$H$40-$F$42,"") | G55: Apero BreizhIzel | H55: 8 | I55: x | J55: =IF(I55="x",H55,0) -> 8 | K55: Loisirs
A56: =IF(AND(NOT(ISBLANK(G55)),ISBLANK(G56)),"Reste prévu","") | B56: =IF(AND(NOT(ISBLANK($G55)),ISBLANK($G56)),$C$42-$F$40-$F$42,"") | C56: =IF(AND(NOT(ISBLANK($G55)),ISBLANK($G56)),"Reste réel","") | D56: =IF(AND(NOT(ISBLANK($G55)),ISBLANK($G56)),$C$42-$H$40-$F$42,"") | G56: Cigarettes | H56: 13 | I56: x | J56: =IF(I56="x",H56,0) -> 13 | K56: Divers
... A78: =IF(AND(NOT(ISBLANK(G77)),ISBLANK(G78)),"Reste prévu","") | B78: =IF(AND(NOT(ISBLANK($G77)),ISBLANK($G78)),$C$42-$F$40-$F$42,"") | C78: =IF(AND(NOT(ISBLANK($G77)),ISBLANK($G78)),"Reste réel","") | D78: =IF(AND(NOT(ISBLANK($G77)),ISBLANK($G78)),$C$42-$H$40-$F$42,"") | G78: Leclerc | H78: 7.34 | I78: x | J78: =IF(I78="x",H78,0) -> 7.34 | K78: Courses
G79: Intermarché Trégeux | H79: 75.49 | I79: x | J79: =IF(I79="x",H79,0) -> 75.49 | K79: Courses
A80: =IF(AND(NOT(ISBLANK(G78)),ISBLANK(G80)),"Reste prévu","") | B80: =IF(AND(NOT(ISBLANK($G78)),ISBLANK($G80)),$C$42-$F$40-$F$42,"") | C80: =IF(AND(NOT(ISBLANK($G78)),ISBLANK($G80)),"Reste réel","") | D80: =IF(AND(NOT(ISBLANK($G78)),ISBLANK($G80)),$C$42-$H$40-$F$42,"") | G80: Lidl | H80: 32.07 | I80: x | J80: =IF(I80="x",H80,0) -> 32.07 | K80: Courses
A81: =IF(AND(NOT(ISBLANK(G80)),ISBLANK(G81)),"Reste prévu","") | B81: =IF(AND(NOT(ISBLANK($G80)),ISBLANK($G81)),$C$42-$F$40-$F$42,"") | C81: =IF(AND(NOT(ISBLANK($G80)),ISBLANK($G81)),"Reste réel","") | D81: =IF(AND(NOT(ISBLANK($G80)),ISBLANK($G81)),$C$42-$H$40-$F$42,"") | G81: Multistore | H81: 46 | I81: x | J81: =IF(I81="x",H81,0) -> 46 | K81: Vêtements
A82: =IF(AND(NOT(ISBLANK(G81)),ISBLANK(G82)),"Reste prévu","") | B82: =IF(AND(NOT(ISBLANK($G81)),ISBLANK($G82)),$C$42-$F$40-$F$42,"") | C82: =IF(AND(NOT(ISBLANK($G81)),ISBLANK($G82)),"Reste réel","") | D82: =IF(AND(NOT(ISBLANK($G81)),ISBLANK($G82)),$C$42-$H$40-$F$42,"") | G82: Decathlon | H82: 123.97 | I82: x | J82: =IF(I82="x",H82,0) -> 123.97 | K82: Vêtements
A83: =IF(AND(NOT(ISBLANK(G82)),ISBLANK(G83)),"Reste prévu","") | B83: =IF(AND(NOT(ISBLANK($G82)),ISBLANK($G83)),$C$42-$F$40-$F$42,"") | C83: =IF(AND(NOT(ISBLANK($G82)),ISBLANK($G83)),"Reste réel","") | D83: =IF(AND(NOT(ISBLANK($G82)),ISBLANK($G83)),$C$42-$H$40-$F$42,"") | G83: Vinted | H83: 41.95 | I83: x | J83: =IF(I83="x",H83,0) -> 41.95 | K83: Vêtements
A84: =IF(AND(NOT(ISBLANK(G83)),ISBLANK(G84)),"Reste prévu","") | B84: =IF(AND(NOT(ISBLANK($G83)),ISBLANK($G84)),$C$42-$F$40-$F$42,"") | C84: =IF(AND(NOT(ISBLANK($G83)),ISBLANK($G84)),"Reste réel","") | D84: =IF(AND(NOT(ISBLANK($G83)),ISBLANK($G84)),$C$42-$H$40-$F$42,"") | G84: Inscription Fac Elouen | H84: 255 | I84: x | J84: =IF(I84="x",H84,0) -> 255 | K84: Scolarité
A85: =IF(AND(NOT(ISBLANK(G84)),ISBLANK(G85)),"Reste prévu","") | B85: =IF(AND(NOT(ISBLANK($G84)),ISBLANK($G85)),$C$42-$F$40-$F$42,"") | C85: =IF(AND(NOT(ISBLANK($G84)),ISBLANK($G85)),"Reste réel","") | D85: =IF(AND(NOT(ISBLANK($G84)),ISBLANK($G85)),$C$42-$H$40-$F$42,"") | G85: Breizh | H85: 11 | I85: x | J85: =IF(I85="x",H85,0) -> 11 | K85: Loisirs
A86: =IF(AND(NOT(ISBLANK(G85)),ISBLANK(G86)),"Reste prévu","") | B86: =IF(AND(NOT(ISBLANK($G85)),ISBLANK($G86)),$C$42-$F$40-$F$42,"") | C86: =IF(AND(NOT(ISBLANK($G85)),ISBLANK($G86)),"Reste réel","") | D86: =IF(AND(NOT(ISBLANK($G85)),ISBLANK($G86)),$C$42-$H$40-$F$42,"") | G86: Leclerc | H86: 12.64 | I86: x | J86: =IF(I86="x",H86,0) -> 12.64 | K86: Courses
A87: =IF(AND(NOT(ISBLANK(G86)),ISBLANK(G87)),"Reste prévu","") | B87: =IF(AND(NOT(ISBLANK($G86)),ISBLANK($G87)),$C$42-$F$40-$F$42,"") | C87: =IF(AND(NOT(ISBLANK($G86)),ISBLANK($G87)),"Reste réel","") | D87: =IF(AND(NOT(ISBLANK($G86)),ISBLANK($G87)),$C$42-$H$40-$F$42,"") | G87: Breizh | H87: 8 | I87: x | J87: =IF(I87="x",H87,0) -> 8 | K87: Loisirs
A88: =IF(AND(NOT(ISBLANK(G87)),ISBLANK(G88)),"Reste prévu","") | B88: =IF(AND(NOT(ISBLANK($G87)),ISBLANK($G88)),$C$42-$F$40-$F$42,"") | C88: =IF(AND(NOT(ISBLANK($G87)),ISBLANK($G88)),"Reste réel","") | D88: =IF(AND(NOT(ISBLANK($G87)),ISBLANK($G88)),$C$42-$H$40-$F$42,"") | G88: Baramoules | H88: 129 | I88: x | J88: =IF(I88="x",H88,0) -> 129 | K88: Loisirs
A89: =IF(AND(NOT(ISBLANK(G88)),ISBLANK(G89)),"Reste prévu","") | B89: =IF(AND(NOT(ISBLANK($G88)),ISBLANK($G89)),$C$42-$F$40-$F$42,"") | C89: =IF(AND(NOT(ISBLANK($G88)),ISBLANK($G89)),"Reste réel","") | D89: =IF(AND(NOT(ISBLANK($G88)),ISBLANK($G89)),$C$42-$H$40-$F$42,"") | G89: Galettes GDD | H89: 23.4 | I89: x | J89: =IF(I89="x",H89,0) -> 23.4 | K89: Courses
A90: =IF(AND(NOT(ISBLANK(G89)),ISBLANK(G90)),"Reste prévu","") | B90: =IF(AND(NOT(ISBLANK($G89)),ISBLANK($G90)),$C$42-$F$40-$F$42,"") | C90: =IF(AND(NOT(ISBLANK($G89)),ISBLANK($G90)),"Reste réel","") | D90: =IF(AND(NOT(ISBLANK($G89)),ISBLANK($G90)),$C$42-$H$40-$F$42,"") | G90: Biscuiterie | H90: 36.5 | I90: x | J90: =IF(I90="x",H90,0) -> 36.5 | K90: Courses
A91: =IF(AND(NOT(ISBLANK(G90)),ISBLANK(G91)),"Reste prévu","") | B91: =IF(AND(NOT(ISBLANK($G90)),ISBLANK($G91)),$C$42-$F$40-$F$42,"") | C91: =IF(AND(NOT(ISBLANK($G90)),ISBLANK($G91)),"Reste réel","") | D91: =IF(AND(NOT(ISBLANK($G90)),ISBLANK($G91)),$C$42-$H$40-$F$42,"") | G91: Leclerc | H91: 34.94 | I91: x | J91: =IF(I91="x",H91,0) -> 34.94 | K91: Courses
A92: =IF(AND(NOT(ISBLANK(G91)),ISBLANK(G92)),"Reste prévu","") | B92: =IF(AND(NOT(ISBLANK($G91)),ISBLANK($G92)),$C$42-$F$40-$F$42,"") | C92: =IF(AND(NOT(ISBLANK($G91)),ISBLANK($G92)),"Reste réel","") | D92: =IF(AND(NOT(ISBLANK($G91)),ISBLANK($G92)),$C$42-$H$40-$F$42,"") | G92: Inscription Fac Arthur | H92: 105 | I92: x | J92: =IF(I92="x",H92,0) -> 105 | K92: Scolarité
... A155: =IF(AND(NOT(ISBLANK(G154)),ISBLANK(G155)),"Reste prévu","") | B155: =IF(AND(NOT(ISBLANK($G154)),ISBLANK($G155)),$C$42-$F$40-$F$42,"") | C155: =IF(AND(NOT(ISBLANK($G154)),ISBLANK($G155)),"Reste réel","") | D155: =IF(AND(NOT(ISBLANK($G154)),ISBLANK($G155)),$C$42-$H$40-$F$42,"") | G155: Urssaaf | H155: 52.31 | I155: x | J155: =IF(I155="x",H155,0) -> 52.31 | K155: Charges
A156: =IF(AND(NOT(ISBLANK(G155)),ISBLANK(G156)),"Reste prévu","") -> Reste prévu | B156: =IF(AND(NOT(ISBLANK($G155)),ISBLANK($G156)),$C$42-$F$40-$F$42,"") -> #REF! | C156: =IF(AND(NOT(ISBLANK($G155)),ISBLANK($G156)),"Reste réel","") -> Reste réel | D156: =IF(AND(NOT(ISBLANK($G155)),ISBLANK($G156)),$C$42-$H$40-$F$42,"") -> #REF! | J156: =IF(I156="x",H156,0) -> 0
A157: =IF(AND(NOT(ISBLANK(G156)),ISBLANK(G157)),"Reste prévu","") | B157: =IF(AND(NOT(ISBLANK($G156)),ISBLANK($G157)),$C$42-$F$40-$F$42,"") | C157: =IF(AND(NOT(ISBLANK($G156)),ISBLANK($G157)),"Reste réel","") | D157: =IF(AND(NOT(ISBLANK($G156)),ISBLANK($G157)),$C$42-$H$40-$F$42,"") | J157: =IF(I157="x",H157,0) -> 0
A158: =IF(AND(NOT(ISBLANK(G157)),ISBLANK(G158)),"Reste prévu","") | B158: =IF(AND(NOT(ISBLANK($G157)),ISBLANK($G158)),$C$42-$F$40-$F$42,"") | C158: =IF(AND(NOT(ISBLANK($G157)),ISBLANK($G158)),"Reste réel","") | D158: =IF(AND(NOT(ISBLANK($G157)),ISBLANK($G158)),$C$42-$H$40-$F$42,"") | J158: =IF(I158="x",H158,0) -> 0
A159: =IF(AND(NOT(ISBLANK(G158)),ISBLANK(G159)),"Reste prévu","") | B159: =IF(AND(NOT(ISBLANK($G158)),ISBLANK($G159)),$C$42-$F$40-$F$42,"") | C159: =IF(AND(NOT(ISBLANK($G158)),ISBLANK($G159)),"Reste réel","") | D159: =IF(AND(NOT(ISBLANK($G158)),ISBLANK($G159)),$C$42-$H$40-$F$42,"") | J159: =IF(I159="x",H159,0) -> 0
A160: =IF(AND(NOT(ISBLANK(G159)),ISBLANK(G160)),"Reste prévu","") | B160: =IF(AND(NOT(ISBLANK($G159)),ISBLANK($G160)),$C$42-$F$40-$F$42,"") | C160: =IF(AND(NOT(ISBLANK($G159)),ISBLANK($G160)),"Reste réel","") | D160: =IF(AND(NOT(ISBLANK($G159)),ISBLANK($G160)),$C$42-$H$40-$F$42,"") | J160: =IF(I160="x",H160,0) -> 0
A161: =IF(AND(NOT(ISBLANK(G160)),ISBLANK(G161)),"Reste prévu","") | B161: =IF(AND(NOT(ISBLANK($G160)),ISBLANK($G161)),$C$42-$F$40-$F$42,"") | C161: =IF(AND(NOT(ISBLANK($G160)),ISBLANK($G161)),"Reste réel","") | D161: =IF(AND(NOT(ISBLANK($G160)),ISBLANK($G161)),$C$42-$H$40-$F$42,"") | J161: =IF(I161="x",H161,0) -> 0
A162: =IF(AND(NOT(ISBLANK(G161)),ISBLANK(G162)),"Reste prévu","") | B162: =IF(AND(NOT(ISBLANK($G161)),ISBLANK($G162)),$C$42-$F$40-$F$42,"") | C162: =IF(AND(NOT(ISBLANK($G161)),ISBLANK($G162)),"Reste réel","") | D162: =IF(AND(NOT(ISBLANK($G161)),ISBLANK($G162)),$C$42-$H$40-$F$42,"") | J162: =IF(I162="x",H162,0) -> 0
A163: =IF(AND(NOT(ISBLANK(G162)),ISBLANK(G163)),"Reste prévu","") | B163: =IF(AND(NOT(ISBLANK($G162)),ISBLANK($G163)),$C$42-$F$40-$F$42,"") | C163: =IF(AND(NOT(ISBLANK($G162)),ISBLANK($G163)),"Reste réel","") | D163: =IF(AND(NOT(ISBLANK($G162)),ISBLANK($G163)),$C$42-$H$40-$F$42,"") | J163: =IF(I163="x",H163,0) -> 0
A164: =IF(AND(NOT(ISBLANK(G163)),ISBLANK(G164)),"Reste prévu","") | B164: =IF(AND(NOT(ISBLANK($G163)),ISBLANK($G164)),$C$42-$F$40-$F$42,"") | C164: =IF(AND(NOT(ISBLANK($G163)),ISBLANK($G164)),"Reste réel","") | D164: =IF(AND(NOT(ISBLANK($G163)),ISBLANK($G164)),$C$42-$H$40-$F$42,"") | J164: =IF(I164="x",H164,0) -> 0
A165: =IF(AND(NOT(ISBLANK(G164)),ISBLANK(G165)),"Reste prévu","") | B165: =IF(AND(NOT(ISBLANK($G164)),ISBLANK($G165)),$C$42-$F$40-$F$42,"") | C165: =IF(AND(NOT(ISBLANK($G164)),ISBLANK($G165)),"Reste réel","") | D165: =IF(AND(NOT(ISBLANK($G164)),ISBLANK($G165)),$C$42-$H$40-$F$42,"") | J165: =IF(I165="x",H165,0) -> 0
A166: =IF(AND(NOT(ISBLANK(G165)),ISBLANK(G166)),"Reste prévu","") | B166: =IF(AND(NOT(ISBLANK($G165)),ISBLANK($G166)),$C$42-$F$40-$F$42,"") | C166: =IF(AND(NOT(ISBLANK($G165)),ISBLANK($G166)),"Reste réel","") | D166: =IF(AND(NOT(ISBLANK($G165)),ISBLANK($G166)),$C$42-$H$40-$F$42,"") | J166: =IF(I166="x",H166,0) -> 0
A167: =IF(AND(NOT(ISBLANK(G166)),ISBLANK(G167)),"Reste prévu","") | B167: =IF(AND(NOT(ISBLANK($G166)),ISBLANK($G167)),$C$42-$F$40-$F$42,"") | C167: =IF(AND(NOT(ISBLANK($G166)),ISBLANK($G167)),"Reste réel","") | D167: =IF(AND(NOT(ISBLANK($G166)),ISBLANK($G167)),$C$42-$H$40-$F$42,"") | J167: =IF(I167="x",H167,0) -> 0
... A214: =IF(AND(NOT(ISBLANK(G213)),ISBLANK(G214)),"Reste prévu","") | B214: =IF(AND(NOT(ISBLANK($G213)),ISBLANK($G214)),$C$42-$F$40-$F$42,"") | C214: =IF(AND(NOT(ISBLANK($G213)),ISBLANK($G214)),"Reste réel","") | D214: =IF(AND(NOT(ISBLANK($G213)),ISBLANK($G214)),$C$42-$H$40-$F$42,"") | J214: =IF(I214="x",H214,0) -> 0
A215: =IF(AND(NOT(ISBLANK(G214)),ISBLANK(G215)),"Reste prévu","") | B215: =IF(AND(NOT(ISBLANK($G214)),ISBLANK($G215)),$C$42-$F$40-$F$42,"") | C215: =IF(AND(NOT(ISBLANK($G214)),ISBLANK($G215)),"Reste réel","") | D215: =IF(AND(NOT(ISBLANK($G214)),ISBLANK($G215)),$C$42-$H$40-$F$42,"")
A216: =IF(AND(NOT(ISBLANK(G215)),ISBLANK(G216)),"Reste prévu","") | B216: =IF(AND(NOT(ISBLANK($G215)),ISBLANK($G216)),$C$42-$F$40-$F$42,"") | C216: =IF(AND(NOT(ISBLANK($G215)),ISBLANK($G216)),"Reste réel","") | D216: =IF(AND(NOT(ISBLANK($G215)),ISBLANK($G216)),$C$42-$H$40-$F$42,"")
A217: =IF(AND(NOT(ISBLANK(G216)),ISBLANK(G217)),"Reste prévu","") | B217: =IF(AND(NOT(ISBLANK($G216)),ISBLANK($G217)),$C$42-$F$40-$F$42,"") | C217: =IF(AND(NOT(ISBLANK($G216)),ISBLANK($G217)),"Reste réel","") | D217: =IF(AND(NOT(ISBLANK($G216)),ISBLANK($G217)),$C$42-$H$40-$F$42,"")
A218: =IF(AND(NOT(ISBLANK(G217)),ISBLANK(G218)),"Reste prévu","") | B218: =IF(AND(NOT(ISBLANK($G217)),ISBLANK($G218)),$C$42-$F$40-$F$42,"") | C218: =IF(AND(NOT(ISBLANK($G217)),ISBLANK($G218)),"Reste réel","") | D218: =IF(AND(NOT(ISBLANK($G217)),ISBLANK($G218)),$C$42-$H$40-$F$42,"")
A219: =IF(AND(NOT(ISBLANK(G218)),ISBLANK(G219)),"Reste prévu","") | B219: =IF(AND(NOT(ISBLANK($G218)),ISBLANK($G219)),$C$42-$F$40-$F$42,"") | C219: =IF(AND(NOT(ISBLANK($G218)),ISBLANK($G219)),"Reste réel","") | D219: =IF(AND(NOT(ISBLANK($G218)),ISBLANK($G219)),$C$42-$H$40-$F$42,"")
A220: =IF(AND(NOT(ISBLANK(G219)),ISBLANK(G220)),"Reste prévu","") | B220: =IF(AND(NOT(ISBLANK($G219)),ISBLANK($G220)),$C$42-$F$40-$F$42,"") | C220: =IF(AND(NOT(ISBLANK($G219)),ISBLANK($G220)),"Reste réel","") | D220: =IF(AND(NOT(ISBLANK($G219)),ISBLANK($G220)),$C$42-$H$40-$F$42,"")
A221: =IF(AND(NOT(ISBLANK(G220)),ISBLANK(G221)),"Reste prévu","") | B221: =IF(AND(NOT(ISBLANK($G220)),ISBLANK($G221)),$C$42-$F$40-$F$42,"") | C221: =IF(AND(NOT(ISBLANK($G220)),ISBLANK($G221)),"Reste réel","") | D221: =IF(AND(NOT(ISBLANK($G220)),ISBLANK($G221)),$C$42-$H$40-$F$42,"")
A222: =IF(AND(NOT(ISBLANK(G221)),ISBLANK(G222)),"Reste prévu","") | B222: =IF(AND(NOT(ISBLANK($G221)),ISBLANK($G222)),$C$42-$F$40-$F$42,"") | C222: =IF(AND(NOT(ISBLANK($G221)),ISBLANK($G222)),"Reste réel","") | D222: =IF(AND(NOT(ISBLANK($G221)),ISBLANK($G222)),$C$42-$H$40-$F$42,"")
A223: =IF(AND(NOT(ISBLANK(G222)),ISBLANK(G223)),"Reste prévu","") | B223: =IF(AND(NOT(ISBLANK($G222)),ISBLANK($G223)),$C$42-$F$40-$F$42,"") | C223: =IF(AND(NOT(ISBLANK($G222)),ISBLANK($G223)),"Reste réel","") | D223: =IF(AND(NOT(ISBLANK($G222)),ISBLANK($G223)),$C$42-$H$40-$F$42,"")
A224: =IF(AND(NOT(ISBLANK(G223)),ISBLANK(G224)),"Reste prévu","") | B224: =IF(AND(NOT(ISBLANK($G223)),ISBLANK($G224)),$C$42-$F$40-$F$42,"") | C224: =IF(AND(NOT(ISBLANK($G223)),ISBLANK($G224)),"Reste réel","") | D224: =IF(AND(NOT(ISBLANK($G223)),ISBLANK($G224)),$C$42-$H$40-$F$42,"")
A225: =IF(AND(NOT(ISBLANK(G224)),ISBLANK(G225)),"Reste prévu","") | B225: =IF(AND(NOT(ISBLANK($G224)),ISBLANK($G225)),$C$42-$F$40-$F$42,"") | C225: =IF(AND(NOT(ISBLANK($G224)),ISBLANK($G225)),"Reste réel","") | D225: =IF(AND(NOT(ISBLANK($G224)),ISBLANK($G225)),$C$42-$H$40-$F$42,"")
A226: =IF(AND(NOT(ISBLANK(G225)),ISBLANK(G226)),"Reste prévu","") | B226: =IF(AND(NOT(ISBLANK($G225)),ISBLANK($G226)),$C$42-$F$40-$F$42,"") | C226: =IF(AND(NOT(ISBLANK($G225)),ISBLANK($G226)),"Reste réel","") | D226: =IF(AND(NOT(ISBLANK($G225)),ISBLANK($G226)),$C$42-$H$40-$F$42,"")
... A237: =IF(AND(NOT(ISBLANK(G236)),ISBLANK(G237)),"Reste prévu","") | B237: =IF(AND(NOT(ISBLANK($G236)),ISBLANK($G237)),$C$42-$F$40-$F$42,"") | C237: =IF(AND(NOT(ISBLANK($G236)),ISBLANK($G237)),"Reste réel","") | D237: =IF(AND(NOT(ISBLANK($G236)),ISBLANK($G237)),$C$42-$H$40-$F$42,"")

Sheet Juin 2026
B1: Recettes | E1: Dépenses | K1: Cadeau
B3: Salaire Pierre | C3: 5273.11 | E3: Loyer Elouen | F3: 669.7 | G3: x | H3: =IF(G3="x",F3,0) -> 669.7 | K3: Logement
B4: Salaire Sterenn | C4: 1828.73 | E4: Argent de poche Elouen | H4: =IF(G4="x",F4,0) -> 0 | K4: Charges
B5: CAF | C5: 114.19 | E5: Engie Elouen | F5: 70 | G5: x | H5: =IF(G5="x",F5,0) -> 70 | K5: Charges
E6: Argent de poche Arthur | F6: 14.99 | G6: x | H6: =IF(G6="x",F6,0) -> 14.99 | K6: Charges
E7: Prêt 25 | F7: 995.15 | G7: x | H7: =IF(G7="x",F7,0) -> 995.15 | K7: Logement
E8: Prêt 15 | F8: 883.42 | G8: x | H8: =IF(G8="x",F8,0) -> 883.42 | K8: Logement
B9: Mutuelle | C9: 9.45 | E9: Assurances prêt | F9: 11.46 | G9: x | H9: =IF(G9="x",F9,0) -> 11.46 | K9: Logement
B10: Note de Frais Igienair | C10: 76.64 | E10: Assurances prêt | F10: 32.57 | G10: x | H10: =IF(G10="x",F10,0) -> 32.57 | K10: Logement
B11: Mutuelle | C11: 9 | E11: Assurances prêt | F11: 79.98 | G11: x | H11: =IF(G11="x",F11,0) -> 79.98 | K11: Logement
B12: Remboursement Amazon | C12: 43.34 | E12: Assurances prêt | F12: 28.49 | G12: x | H12: =IF(G12="x",F12,0) -> 28.49 | K12: Logement
B13: Padel Edouard | C13: 4 | E13: Disney | F13: 6.99 | G13: x | H13: =IF(G13="x",F13,0) -> 6.99 | K13: Internet/Téléphone
B14: Padel Didier | C14: 4 | E14: EDF Arthur | F14: 65 | G14: x | H14: =IF(G14="x",F14,0) -> 65 | K14: Charges
B15: Note de Frais Cap | C15: 57.3 | E15: EkWateur | F15: 208 | G15: x | H15: =IF(G15="x",F15,0) -> 208 | K15: Charges
B16: Mutuelle Elouen | C16: 30.9 | E16: Sosh Maison | F16: 24.99 | G16: x | H16: =IF(G16="x",F16,0) -> 24.99 | K16: Internet/Téléphone
B17: Epargne | C17: 500 | E17: Sosh Arthur | F17: 14.99 | G17: x | H17: =IF(G17="x",F17,0) -> 14.99 | K17: Internet/Téléphone
B18: Epargne | C18: 300 | E18: Sosh Ael | F18: 14.99 | H18: =IF(G18="x",F18,0) -> 0 | K18: Internet/Téléphone
B19: Remboursement MicroOnde Papa | C19: 91 | E19: Sosh Elouen | F19: 14.99 | G19: x | H19: =IF(G19="x",F19,0) -> 14.99 | K19: Internet/Téléphone
B20: CPAM | C20: 4 | E20: Sosh Sterenn | F20: 10.99 | G20: x | H20: =IF(G20="x",F20,0) -> 10.99 | K20: Internet/Téléphone
B21: Remboursement Ael | C21: 168 | E21: Mutuelle | F21: 104.98 | G21: x | H21: =IF(G21="x",F21,0) -> 104.98 | K21: Assurances/Mutuelle
E23: AxaHabitation | F23: 62.88 | G23: x | H23: =IF(G23="x",F23,0) -> 62.88 | K23: Assurances/Mutuelle
E24: VW LDD | F24: 331.65 | G24: x | H24: =IF(G24="x",F24,0) -> 331.65 | K24: Voiture/Déplacement
E25: Axa Voiture | F25: 88.03 | G25: x | H25: =IF(G25="x",F25,0) -> 88.03 | K25: Assurances/Mutuelle
E26: Suravenir Garanties Vie | F26: 19 | H26: =IF(G26="x",F26,0) -> 0 | K26: Assurances/Mutuelle
E27: Joséphine | F27: 20 | G27: x | H27: =IF(G27="x",F27,0) -> 20 | K27: Divers
E28: Canal Plus | F28: 21.99 | G28: x | H28: =IF(G28="x",F28,0) -> 21.99 | K28: Internet/Téléphone
H29: =IF(G29="x",F29,0) -> 0 | K29: Voiture/Déplacement
E30: Keolis Elouen | F30: 21.4 | G30: x | H30: =IF(G30="x",F30,0) -> 21.4 | K30: Voiture/Déplacement
E31: Apple | F31: 0.99 | G31: x | H31: =IF(G31="x",F31,0) -> 0.99 | K31: Internet/Téléphone
E32: Apple | F32: 0.99 | H32: =IF(G32="x",F32,0) -> 0 | K32: Internet/Téléphone
E33: Apple | F33: 16.99 | H33: =IF(G33="x",F33,0) -> 0 | K33: Internet/Téléphone
E34: St Charles | F34: 196.9 | G34: x | H34: =IF(G34="x",F34,0) -> 196.9 | K34: Scolarité
E35: Ménage | F35: 68 | G35: x | H35: =IF(G35="x",F35,0) -> 68 | K35: Logement
E36: Urssaaf | F36: 78.43 | G36: x | H36: =IF(G36="x",F36,0) -> 78.43 | K36: Logement
E37: Cotisation Eurocompte | F37: 19.03 | G37: x | H37: =IF(G37="x",F37,0) -> 19.03 | K37: Charges
E38: Indivision | F38: 33.89 | G38: x | H38: =IF(G38="x",F38,0) -> 33.89 | K38: Charges
A39: Etat mois précédent | C39: ='Mai 2026'!D44 -> #REF!
A40: Recettes fixes | C40: =SUM(C2:C6) -> 7216.03 | E40: Somme dépenses prévues | F40: =SUM(F2:F38) -> 4231.85 | G40: Somme dépenses réelles | H40: =SUM(H2:H38) -> 4179.88 | I40: Delta moins les exceptions
A41: Recettes additionnelles du mois | C41: =SUM(C8:C35) -> 1297.63 | E41: Reste previsionnel | F41: =C42-F40 -> #REF! | G41: Delta du mois | H41: =C39+C40+C41-H40-F42 -> #REF!
A42: Total Recettes | C42: =SUM(C39:C41) -> #REF! | E42: Somme dépenses non prévues | F42: =SUM(J44:J247) -> 3893.13
A43: Reste prévu | B43: =$C$42-$F$40-$F$42 -> #REF! | C43: Reste réel | D43: =$C$42-$H$40-$F$42 -> #REF!
A44: =IF(AND(NOT(ISBLANK(#REF!)),ISBLANK(G44)),"Reste prévu","") -> Reste prévu | B44: =IF(AND(NOT(ISBLANK(#REF!)),ISBLANK($G44)),$C$42-$F$40-$F$42,"") -> #REF! | C44: =IF(AND(NOT(ISBLANK(#REF!)),ISBLANK($G44)),"Reste réel","") -> Reste réel | D44: =IF(AND(NOT(ISBLANK(#REF!)),ISBLANK($G44)),$C$42-$H$40-$F$42,"") -> #REF! | J44: =IF(I44="x",H44,0) -> 0 | K44: Loisirs
A45: =IF(AND(NOT(ISBLANK(G44)),ISBLANK(G45)),"Reste prévu","") | B45: =IF(AND(NOT(ISBLANK($G44)),ISBLANK($G45)),$C$42-$F$40-$F$42,"") | C45: =IF(AND(NOT(ISBLANK($G44)),ISBLANK($G45)),"Reste réel","") | D45: =IF(AND(NOT(ISBLANK($G44)),ISBLANK($G45)),$C$42-$H$40-$F$42,"") | G45: Leroy Merlin | H45: 5.99 | I45: x | J45: =IF(I45="x",H45,0) -> 5.99 | K45: Bricolage/Travaux
A46: =IF(AND(NOT(ISBLANK(G45)),ISBLANK(G46)),"Reste prévu","") | B46: =IF(AND(NOT(ISBLANK($G45)),ISBLANK($G46)),$C$42-$F$40-$F$42,"") | C46: =IF(AND(NOT(ISBLANK($G45)),ISBLANK($G46)),"Reste réel","") | D46: =IF(AND(NOT(ISBLANK($G45)),ISBLANK($G46)),$C$42-$H$40-$F$42,"") | G46: Leroy Merlin | H46: 31.89 | I46: x | J46: =IF(I46="x",H46,0) -> 31.89 | K46: Bricolage/Travaux
A47: =IF(AND(NOT(ISBLANK(G46)),ISBLANK(G47)),"Reste prévu","") | B47: =IF(AND(NOT(ISBLANK($G46)),ISBLANK($G47)),$C$42-$F$40-$F$42,"") | C47: =IF(AND(NOT(ISBLANK($G46)),ISBLANK($G47)),"Reste réel","") | D47: =IF(AND(NOT(ISBLANK($G46)),ISBLANK($G47)),$C$42-$H$40-$F$42,"") | G47: Leroy Merlin | H47: 35.98 | I47: x | J47: =IF(I47="x",H47,0) -> 35.98 | K47: Bricolage/Travaux
A48: =IF(AND(NOT(ISBLANK(G47)),ISBLANK(G48)),"Reste prévu","") | B48: =IF(AND(NOT(ISBLANK($G47)),ISBLANK($G48)),$C$42-$F$40-$F$42,"") | C48: =IF(AND(NOT(ISBLANK($G47)),ISBLANK($G48)),"Reste réel","") | D48: =IF(AND(NOT(ISBLANK($G47)),ISBLANK($G48)),$C$42-$H$40-$F$42,"") | G48: Soirée Hand | H48: 2 | I48: x | J48: =IF(I48="x",H48,0) -> 2 | K48: Loisirs
A49: =IF(AND(NOT(ISBLANK(G48)),ISBLANK(G49)),"Reste prévu","") | B49: =IF(AND(NOT(ISBLANK($G48)),ISBLANK($G49)),$C$42-$F$40-$F$42,"") | C49: =IF(AND(NOT(ISBLANK($G48)),ISBLANK($G49)),"Reste réel","") | D49: =IF(AND(NOT(ISBLANK($G48)),ISBLANK($G49)),$C$42-$H$40-$F$42,"") | G49: Soirée Hand | H49: 4.5 | I49: x | J49: =IF(I49="x",H49,0) -> 4.5 | K49: Loisirs
A50: =IF(AND(NOT(ISBLANK(G49)),ISBLANK(G50)),"Reste prévu","") | B50: =IF(AND(NOT(ISBLANK($G49)),ISBLANK($G50)),$C$42-$F$40-$F$42,"") | C50: =IF(AND(NOT(ISBLANK($G49)),ISBLANK($G50)),"Reste réel","") | D50: =IF(AND(NOT(ISBLANK($G49)),ISBLANK($G50)),$C$42-$H$40-$F$42,"") | G50: Soirée Hand | H50: 5 | I50: x | J50: =IF(I50="x",H50,0) -> 5 | K50: Loisirs
A51: =IF(AND(NOT(ISBLANK(G50)),ISBLANK(G51)),"Reste prévu","") | B51: =IF(AND(NOT(ISBLANK($G50)),ISBLANK($G51)),$C$42-$F$40-$F$42,"") | C51: =IF(AND(NOT(ISBLANK($G50)),ISBLANK($G51)),"Reste réel","") | D51: =IF(AND(NOT(ISBLANK($G50)),ISBLANK($G51)),$C$42-$H$40-$F$42,"") | G51: Soirée Hand | H51: 6 | I51: x | J51: =IF(I51="x",H51,0) -> 6 | K51: Loisirs
A52: =IF(AND(NOT(ISBLANK(G51)),ISBLANK(G52)),"Reste prévu","") | B52: =IF(AND(NOT(ISBLANK($G51)),ISBLANK($G52)),$C$42-$F$40-$F$42,"") | C52: =IF(AND(NOT(ISBLANK($G51)),ISBLANK($G52)),"Reste réel","") | D52: =IF(AND(NOT(ISBLANK($G51)),ISBLANK($G52)),$C$42-$H$40-$F$42,"") | G52: Soirée Hand | H52: 9 | I52: x | J52: =IF(I52="x",H52,0) -> 9 | K52: Loisirs
A53: =IF(AND(NOT(ISBLANK(G52)),ISBLANK(G53)),"Reste prévu","") | B53: =IF(AND(NOT(ISBLANK($G52)),ISBLANK($G53)),$C$42-$F$40-$F$42,"") | C53: =IF(AND(NOT(ISBLANK($G52)),ISBLANK($G53)),"Reste réel","") | D53: =IF(AND(NOT(ISBLANK($G52)),ISBLANK($G53)),$C$42-$H$40-$F$42,"") | G53: Cigarettes | H53: 13 | I53: x | J53: =IF(I53="x",H53,0) -> 13 | K53: Divers
A54: =IF(AND(NOT(ISBLANK(G53)),ISBLANK(G54)),"Reste prévu","") | B54: =IF(AND(NOT(ISBLANK($G53)),ISBLANK($G54)),$C$42-$F$40-$F$42,"") | C54: =IF(AND(NOT(ISBLANK($G53)),ISBLANK($G54)),"Reste réel","") | D54: =IF(AND(NOT(ISBLANK($G53)),ISBLANK($G54)),$C$42-$H$40-$F$42,"") | G54: Tartapain Gateau Mamou | H54: 44.58 | I54: x | J54: =IF(I54="x",H54,0) -> 44.58 | K54: Courses
A55: =IF(AND(NOT(ISBLANK(G54)),ISBLANK(G55)),"Reste prévu","") | B55: =IF(AND(NOT(ISBLANK($G54)),ISBLANK($G55)),$C$42-$F$40-$F$42,"") | C55: =IF(AND(NOT(ISBLANK($G54)),ISBLANK($G55)),"Reste réel","") | D55: =IF(AND(NOT(ISBLANK($G54)),ISBLANK($G55)),$C$42-$H$40-$F$42,"") | G55: Pacotille St Alban | H55: 67.5 | I55: x | J55: =IF(I55="x",H55,0) -> 67.5 | K55: Vêtements
A56: =IF(AND(NOT(ISBLANK(G55)),ISBLANK(G56)),"Reste prévu","") | B56: =IF(AND(NOT(ISBLANK($G55)),ISBLANK($G56)),$C$42-$F$40-$F$42,"") | C56: =IF(AND(NOT(ISBLANK($G55)),ISBLANK($G56)),"Reste réel","") | D56: =IF(AND(NOT(ISBLANK($G55)),ISBLANK($G56)),$C$42-$H$40-$F$42,"") | G56: Leclerc | H56: 15.68 | I56: x | J56: =IF(I56="x",H56,0) -> 15.68 | K56: Courses
... A78: =IF(AND(NOT(ISBLANK(G77)),ISBLANK(G78)),"Reste prévu","") | B78: =IF(AND(NOT(ISBLANK($G77)),ISBLANK($G78)),$C$42-$F$40-$F$42,"") | C78: =IF(AND(NOT(ISBLANK($G77)),ISBLANK($G78)),"Reste réel","") | D78: =IF(AND(NOT(ISBLANK($G77)),ISBLANK($G78)),$C$42-$H$40-$F$42,"") | G78: Leclerc | H78: 41.95 | I78: x | J78: =IF(I78="x",H78,0) -> 41.95 | K78: Courses
G79: Cafran | H79: 76.17 | I79: x | J79: =IF(I79="x",H79,0) -> 76.17 | K79: Courses
A80: =IF(AND(NOT(ISBLANK(G78)),ISBLANK(G80)),"Reste prévu","") | B80: =IF(AND(NOT(ISBLANK($G78)),ISBLANK($G80)),$C$42-$F$40-$F$42,"") | C80: =IF(AND(NOT(ISBLANK($G78)),ISBLANK($G80)),"Reste réel","") | D80: =IF(AND(NOT(ISBLANK($G78)),ISBLANK($G80)),$C$42-$H$40-$F$42,"") | G80: La Poste Solen | H80: 9.29 | I80: x | J80: =IF(I80="x",H80,0) -> 9.29 | K80: Cadeau
A81: =IF(AND(NOT(ISBLANK(G80)),ISBLANK(G81)),"Reste prévu","") | B81: =IF(AND(NOT(ISBLANK($G80)),ISBLANK($G81)),$C$42-$F$40-$F$42,"") | C81: =IF(AND(NOT(ISBLANK($G80)),ISBLANK($G81)),"Reste réel","") | D81: =IF(AND(NOT(ISBLANK($G80)),ISBLANK($G81)),$C$42-$H$40-$F$42,"") | G81: Cigarettes | H81: 13 | I81: x | J81: =IF(I81="x",H81,0) -> 13 | K81: Divers
A82: =IF(AND(NOT(ISBLANK(G81)),ISBLANK(G82)),"Reste prévu","") | B82: =IF(AND(NOT(ISBLANK($G81)),ISBLANK($G82)),$C$42-$F$40-$F$42,"") | C82: =IF(AND(NOT(ISBLANK($G81)),ISBLANK($G82)),"Reste réel","") | D82: =IF(AND(NOT(ISBLANK($G81)),ISBLANK($G82)),$C$42-$H$40-$F$42,"") | G82: Sarenza | H82: 68.9 | I82: x | J82: =IF(I82="x",H82,0) -> 68.9 | K82: Vêtements
A83: =IF(AND(NOT(ISBLANK(G82)),ISBLANK(G83)),"Reste prévu","") | B83: =IF(AND(NOT(ISBLANK($G82)),ISBLANK($G83)),$C$42-$F$40-$F$42,"") | C83: =IF(AND(NOT(ISBLANK($G82)),ISBLANK($G83)),"Reste réel","") | D83: =IF(AND(NOT(ISBLANK($G82)),ISBLANK($G83)),$C$42-$H$40-$F$42,"") | G83: Biscuiterie Mazé | H83: 88.6 | I83: x | J83: =IF(I83="x",H83,0) -> 88.6 | K83: Courses
A84: =IF(AND(NOT(ISBLANK(G83)),ISBLANK(G84)),"Reste prévu","") | B84: =IF(AND(NOT(ISBLANK($G83)),ISBLANK($G84)),$C$42-$F$40-$F$42,"") | C84: =IF(AND(NOT(ISBLANK($G83)),ISBLANK($G84)),"Reste réel","") | D84: =IF(AND(NOT(ISBLANK($G83)),ISBLANK($G84)),$C$42-$H$40-$F$42,"") | G84: Vélo Ael | H84: 1.2 | I84: x | J84: =IF(I84="x",H84,0) -> 1.2 | K84: Loisirs
A85: =IF(AND(NOT(ISBLANK(G84)),ISBLANK(G85)),"Reste prévu","") | B85: =IF(AND(NOT(ISBLANK($G84)),ISBLANK($G85)),$C$42-$F$40-$F$42,"") | C85: =IF(AND(NOT(ISBLANK($G84)),ISBLANK($G85)),"Reste réel","") | D85: =IF(AND(NOT(ISBLANK($G84)),ISBLANK($G85)),$C$42-$H$40-$F$42,"") | G85: Vélo Ael | H85: 1.2 | I85: x | J85: =IF(I85="x",H85,0) -> 1.2 | K85: Loisirs
A86: =IF(AND(NOT(ISBLANK(G85)),ISBLANK(G86)),"Reste prévu","") | B86: =IF(AND(NOT(ISBLANK($G85)),ISBLANK($G86)),$C$42-$F$40-$F$42,"") | C86: =IF(AND(NOT(ISBLANK($G85)),ISBLANK($G86)),"Reste réel","") | D86: =IF(AND(NOT(ISBLANK($G85)),ISBLANK($G86)),$C$42-$H$40-$F$42,"") | G86: L'obele | H86: 13.45 | I86: x | J86: =IF(I86="x",H86,0) -> 13.45 | K86: Loisirs
A87: =IF(AND(NOT(ISBLANK(G86)),ISBLANK(G87)),"Reste prévu","") | B87: =IF(AND(NOT(ISBLANK($G86)),ISBLANK($G87)),$C$42-$F$40-$F$42,"") | C87: =IF(AND(NOT(ISBLANK($G86)),ISBLANK($G87)),"Reste réel","") | D87: =IF(AND(NOT(ISBLANK($G86)),ISBLANK($G87)),$C$42-$H$40-$F$42,"") | G87: Thé Geoffrey | H87: 66 | I87: x | J87: =IF(I87="x",H87,0) -> 66 | K87: Courses
A88: =IF(AND(NOT(ISBLANK(G87)),ISBLANK(G88)),"Reste prévu","") | B88: =IF(AND(NOT(ISBLANK($G87)),ISBLANK($G88)),$C$42-$F$40-$F$42,"") | C88: =IF(AND(NOT(ISBLANK($G87)),ISBLANK($G88)),"Reste réel","") | D88: =IF(AND(NOT(ISBLANK($G87)),ISBLANK($G88)),$C$42-$H$40-$F$42,"") | G88: Amazon | H88: 27.54 | I88: x | J88: =IF(I88="x",H88,0) -> 27.54 | K88: Divers
A89: =IF(AND(NOT(ISBLANK(G88)),ISBLANK(G89)),"Reste prévu","") | B89: =IF(AND(NOT(ISBLANK($G88)),ISBLANK($G89)),$C$42-$F$40-$F$42,"") | C89: =IF(AND(NOT(ISBLANK($G88)),ISBLANK($G89)),"Reste réel","") | D89: =IF(AND(NOT(ISBLANK($G88)),ISBLANK($G89)),$C$42-$H$40-$F$42,"") | G89: Pharmacie | H89: 50.25 | I89: x | J89: =IF(I89="x",H89,0) -> 50.25 | K89: Medical
A90: =IF(AND(NOT(ISBLANK(G89)),ISBLANK(G90)),"Reste prévu","") | B90: =IF(AND(NOT(ISBLANK($G89)),ISBLANK($G90)),$C$42-$F$40-$F$42,"") | C90: =IF(AND(NOT(ISBLANK($G89)),ISBLANK($G90)),"Reste réel","") | D90: =IF(AND(NOT(ISBLANK($G89)),ISBLANK($G90)),$C$42-$H$40-$F$42,"") | G90: Leclerc | H90: 1.93 | I90: x | J90: =IF(I90="x",H90,0) -> 1.93 | K90: Courses
A91: =IF(AND(NOT(ISBLANK(G90)),ISBLANK(G91)),"Reste prévu","") | B91: =IF(AND(NOT(ISBLANK($G90)),ISBLANK($G91)),$C$42-$F$40-$F$42,"") | C91: =IF(AND(NOT(ISBLANK($G90)),ISBLANK($G91)),"Reste réel","") | D91: =IF(AND(NOT(ISBLANK($G90)),ISBLANK($G91)),$C$42-$H$40-$F$42,"") | G91: Estivales Hugo | H91: 45 | I91: x | J91: =IF(I91="x",H91,0) -> 45 | K91: Loisirs
A92: =IF(AND(NOT(ISBLANK(G91)),ISBLANK(G92)),"Reste prévu","") | B92: =IF(AND(NOT(ISBLANK($G91)),ISBLANK($G92)),$C$42-$F$40-$F$42,"") | C92: =IF(AND(NOT(ISBLANK($G91)),ISBLANK($G92)),"Reste réel","") | D92: =IF(AND(NOT(ISBLANK($G91)),ISBLANK($G92)),$C$42-$H$40-$F$42,"") | G92: Estivales Ael | H92: 39 | I92: x | J92: =IF(I92="x",H92,0) -> 39 | K92: Loisirs
... A155: =IF(AND(NOT(ISBLANK(G154)),ISBLANK(G155)),"Reste prévu","") | B155: =IF(AND(NOT(ISBLANK($G154)),ISBLANK($G155)),$C$42-$F$40-$F$42,"") | C155: =IF(AND(NOT(ISBLANK($G154)),ISBLANK($G155)),"Reste réel","") | D155: =IF(AND(NOT(ISBLANK($G154)),ISBLANK($G155)),$C$42-$H$40-$F$42,"") | G155: Leclerc | H155: 26.33 | I155: x | J155: =IF(I155="x",H155,0) -> 26.33 | K155: Courses
A156: =IF(AND(NOT(ISBLANK(G155)),ISBLANK(G156)),"Reste prévu","") -> Reste prévu | B156: =IF(AND(NOT(ISBLANK($G155)),ISBLANK($G156)),$C$42-$F$40-$F$42,"") -> #REF! | C156: =IF(AND(NOT(ISBLANK($G155)),ISBLANK($G156)),"Reste réel","") -> Reste réel | D156: =IF(AND(NOT(ISBLANK($G155)),ISBLANK($G156)),$C$42-$H$40-$F$42,"") -> #REF! | J156: =IF(I156="x",H156,0) -> 0
A157: =IF(AND(NOT(ISBLANK(G156)),ISBLANK(G157)),"Reste prévu","") | B157: =IF(AND(NOT(ISBLANK($G156)),ISBLANK($G157)),$C$42-$F$40-$F$42,"") | C157: =IF(AND(NOT(ISBLANK($G156)),ISBLANK($G157)),"Reste réel","") | D157: =IF(AND(NOT(ISBLANK($G156)),ISBLANK($G157)),$C$42-$H$40-$F$42,"") | J157: =IF(I157="x",H157,0) -> 0
A158: =IF(AND(NOT(ISBLANK(G157)),ISBLANK(G158)),"Reste prévu","") | B158: =IF(AND(NOT(ISBLANK($G157)),ISBLANK($G158)),$C$42-$F$40-$F$42,"") | C158: =IF(AND(NOT(ISBLANK($G157)),ISBLANK($G158)),"Reste réel","") | D158: =IF(AND(NOT(ISBLANK($G157)),ISBLANK($G158)),$C$42-$H$40-$F$42,"") | J158: =IF(I158="x",H158,0) -> 0
A159: =IF(AND(NOT(ISBLANK(G158)),ISBLANK(G159)),"Reste prévu","") | B159: =IF(AND(NOT(ISBLANK($G158)),ISBLANK($G159)),$C$42-$F$40-$F$42,"") | C159: =IF(AND(NOT(ISBLANK($G158)),ISBLANK($G159)),"Reste réel","") | D159: =IF(AND(NOT(ISBLANK($G158)),ISBLANK($G159)),$C$42-$H$40-$F$42,"") | J159: =IF(I159="x",H159,0) -> 0
A160: =IF(AND(NOT(ISBLANK(G159)),ISBLANK(G160)),"Reste prévu","") | B160: =IF(AND(NOT(ISBLANK($G159)),ISBLANK($G160)),$C$42-$F$40-$F$42,"") | C160: =IF(AND(NOT(ISBLANK($G159)),ISBLANK($G160)),"Reste réel","") | D160: =IF(AND(NOT(ISBLANK($G159)),ISBLANK($G160)),$C$42-$H$40-$F$42,"") | J160: =IF(I160="x",H160,0) -> 0
A161: =IF(AND(NOT(ISBLANK(G160)),ISBLANK(G161)),"Reste prévu","") | B161: =IF(AND(NOT(ISBLANK($G160)),ISBLANK($G161)),$C$42-$F$40-$F$42,"") | C161: =IF(AND(NOT(ISBLANK($G160)),ISBLANK($G161)),"Reste réel","") | D161: =IF(AND(NOT(ISBLANK($G160)),ISBLANK($G161)),$C$42-$H$40-$F$42,"") | J161: =IF(I161="x",H161,0) -> 0
A162: =IF(AND(NOT(ISBLANK(G161)),ISBLANK(G162)),"Reste prévu","") | B162: =IF(AND(NOT(ISBLANK($G161)),ISBLANK($G162)),$C$42-$F$40-$F$42,"") | C162: =IF(AND(NOT(ISBLANK($G161)),ISBLANK($G162)),"Reste réel","") | D162: =IF(AND(NOT(ISBLANK($G161)),ISBLANK($G162)),$C$42-$H$40-$F$42,"") | J162: =IF(I162="x",H162,0) -> 0
A163: =IF(AND(NOT(ISBLANK(G162)),ISBLANK(G163)),"Reste prévu","") | B163: =IF(AND(NOT(ISBLANK($G162)),ISBLANK($G163)),$C$42-$F$40-$F$42,"") | C163: =IF(AND(NOT(ISBLANK($G162)),ISBLANK($G163)),"Reste réel","") | D163: =IF(AND(NOT(ISBLANK($G162)),ISBLANK($G163)),$C$42-$H$40-$F$42,"") | J163: =IF(I163="x",H163,0) -> 0
A164: =IF(AND(NOT(ISBLANK(G163)),ISBLANK(G164)),"Reste prévu","") | B164: =IF(AND(NOT(ISBLANK($G163)),ISBLANK($G164)),$C$42-$F$40-$F$42,"") | C164: =IF(AND(NOT(ISBLANK($G163)),ISBLANK($G164)),"Reste réel","") | D164: =IF(AND(NOT(ISBLANK($G163)),ISBLANK($G164)),$C$42-$H$40-$F$42,"") | J164: =IF(I164="x",H164,0) -> 0
A165: =IF(AND(NOT(ISBLANK(G164)),ISBLANK(G165)),"Reste prévu","") | B165: =IF(AND(NOT(ISBLANK($G164)),ISBLANK($G165)),$C$42-$F$40-$F$42,"") | C165: =IF(AND(NOT(ISBLANK($G164)),ISBLANK($G165)),"Reste réel","") | D165: =IF(AND(NOT(ISBLANK($G164)),ISBLANK($G165)),$C$42-$H$40-$F$42,"") | J165: =IF(I165="x",H165,0) -> 0
A166: =IF(AND(NOT(ISBLANK(G165)),ISBLANK(G166)),"Reste prévu","") | B166: =IF(AND(NOT(ISBLANK($G165)),ISBLANK($G166)),$C$42-$F$40-$F$42,"") | C166: =IF(AND(NOT(ISBLANK($G165)),ISBLANK($G166)),"Reste réel","") | D166: =IF(AND(NOT(ISBLANK($G165)),ISBLANK($G166)),$C$42-$H$40-$F$42,"") | J166: =IF(I166="x",H166,0) -> 0
A167: =IF(AND(NOT(ISBLANK(G166)),ISBLANK(G167)),"Reste prévu","") | B167: =IF(AND(NOT(ISBLANK($G166)),ISBLANK($G167)),$C$42-$F$40-$F$42,"") | C167: =IF(AND(NOT(ISBLANK($G166)),ISBLANK($G167)),"Reste réel","") | D167: =IF(AND(NOT(ISBLANK($G166)),ISBLANK($G167)),$C$42-$H$40-$F$42,"") | J167: =IF(I167="x",H167,0) -> 0
... A214: =IF(AND(NOT(ISBLANK(G213)),ISBLANK(G214)),"Reste prévu","") | B214: =IF(AND(NOT(ISBLANK($G213)),ISBLANK($G214)),$C$42-$F$40-$F$42,"") | C214: =IF(AND(NOT(ISBLANK($G213)),ISBLANK($G214)),"Reste réel","") | D214: =IF(AND(NOT(ISBLANK($G213)),ISBLANK($G214)),$C$42-$H$40-$F$42,"") | J214: =IF(I214="x",H214,0) -> 0
A215: =IF(AND(NOT(ISBLANK(G214)),ISBLANK(G215)),"Reste prévu","") | B215: =IF(AND(NOT(ISBLANK($G214)),ISBLANK($G215)),$C$42-$F$40-$F$42,"") | C215: =IF(AND(NOT(ISBLANK($G214)),ISBLANK($G215)),"Reste réel","") | D215: =IF(AND(NOT(ISBLANK($G214)),ISBLANK($G215)),$C$42-$H$40-$F$42,"")
A216: =IF(AND(NOT(ISBLANK(G215)),ISBLANK(G216)),"Reste prévu","") | B216: =IF(AND(NOT(ISBLANK($G215)),ISBLANK($G216)),$C$42-$F$40-$F$42,"") | C216: =IF(AND(NOT(ISBLANK($G215)),ISBLANK($G216)),"Reste réel","") | D216: =IF(AND(NOT(ISBLANK($G215)),ISBLANK($G216)),$C$42-$H$40-$F$42,"")
A217: =IF(AND(NOT(ISBLANK(G216)),ISBLANK(G217)),"Reste prévu","") | B217: =IF(AND(NOT(ISBLANK($G216)),ISBLANK($G217)),$C$42-$F$40-$F$42,"") | C217: =IF(AND(NOT(ISBLANK($G216)),ISBLANK($G217)),"Reste réel","") | D217: =IF(AND(NOT(ISBLANK($G216)),ISBLANK($G217)),$C$42-$H$40-$F$42,"")
A218: =IF(AND(NOT(ISBLANK(G217)),ISBLANK(G218)),"Reste prévu","") | B218: =IF(AND(NOT(ISBLANK($G217)),ISBLANK($G218)),$C$42-$F$40-$F$42,"") | C218: =IF(AND(NOT(ISBLANK($G217)),ISBLANK($G218)),"Reste réel","") | D218: =IF(AND(NOT(ISBLANK($G217)),ISBLANK($G218)),$C$42-$H$40-$F$42,"")
A219: =IF(AND(NOT(ISBLANK(G218)),ISBLANK(G219)),"Reste prévu","") | B219: =IF(AND(NOT(ISBLANK($G218)),ISBLANK($G219)),$C$42-$F$40-$F$42,"") | C219: =IF(AND(NOT(ISBLANK($G218)),ISBLANK($G219)),"Reste réel","") | D219: =IF(AND(NOT(ISBLANK($G218)),ISBLANK($G219)),$C$42-$H$40-$F$42,"")
A220: =IF(AND(NOT(ISBLANK(G219)),ISBLANK(G220)),"Reste prévu","") | B220: =IF(AND(NOT(ISBLANK($G219)),ISBLANK($G220)),$C$42-$F$40-$F$42,"") | C220: =IF(AND(NOT(ISBLANK($G219)),ISBLANK($G220)),"Reste réel","") | D220: =IF(AND(NOT(ISBLANK($G219)),ISBLANK($G220)),$C$42-$H$40-$F$42,"")
A221: =IF(AND(NOT(ISBLANK(G220)),ISBLANK(G221)),"Reste prévu","") | B221: =IF(AND(NOT(ISBLANK($G220)),ISBLANK($G221)),$C$42-$F$40-$F$42,"") | C221: =IF(AND(NOT(ISBLANK($G220)),ISBLANK($G221)),"Reste réel","") | D221: =IF(AND(NOT(ISBLANK($G220)),ISBLANK($G221)),$C$42-$H$40-$F$42,"")
A222: =IF(AND(NOT(ISBLANK(G221)),ISBLANK(G222)),"Reste prévu","") | B222: =IF(AND(NOT(ISBLANK($G221)),ISBLANK($G222)),$C$42-$F$40-$F$42,"") | C222: =IF(AND(NOT(ISBLANK($G221)),ISBLANK($G222)),"Reste réel","") | D222: =IF(AND(NOT(ISBLANK($G221)),ISBLANK($G222)),$C$42-$H$40-$F$42,"")
A223: =IF(AND(NOT(ISBLANK(G222)),ISBLANK(G223)),"Reste prévu","") | B223: =IF(AND(NOT(ISBLANK($G222)),ISBLANK($G223)),$C$42-$F$40-$F$42,"") | C223: =IF(AND(NOT(ISBLANK($G222)),ISBLANK($G223)),"Reste réel","") | D223: =IF(AND(NOT(ISBLANK($G222)),ISBLANK($G223)),$C$42-$H$40-$F$42,"")
A224: =IF(AND(NOT(ISBLANK(G223)),ISBLANK(G224)),"Reste prévu","") | B224: =IF(AND(NOT(ISBLANK($G223)),ISBLANK($G224)),$C$42-$F$40-$F$42,"") | C224: =IF(AND(NOT(ISBLANK($G223)),ISBLANK($G224)),"Reste réel","") | D224: =IF(AND(NOT(ISBLANK($G223)),ISBLANK($G224)),$C$42-$H$40-$F$42,"")
A225: =IF(AND(NOT(ISBLANK(G224)),ISBLANK(G225)),"Reste prévu","") | B225: =IF(AND(NOT(ISBLANK($G224)),ISBLANK($G225)),$C$42-$F$40-$F$42,"") | C225: =IF(AND(NOT(ISBLANK($G224)),ISBLANK($G225)),"Reste réel","") | D225: =IF(AND(NOT(ISBLANK($G224)),ISBLANK($G225)),$C$42-$H$40-$F$42,"")
A226: =IF(AND(NOT(ISBLANK(G225)),ISBLANK(G226)),"Reste prévu","") | B226: =IF(AND(NOT(ISBLANK($G225)),ISBLANK($G226)),$C$42-$F$40-$F$42,"") | C226: =IF(AND(NOT(ISBLANK($G225)),ISBLANK($G226)),"Reste réel","") | D226: =IF(AND(NOT(ISBLANK($G225)),ISBLANK($G226)),$C$42-$H$40-$F$42,"")
... A237: =IF(AND(NOT(ISBLANK(G236)),ISBLANK(G237)),"Reste prévu","") | B237: =IF(AND(NOT(ISBLANK($G236)),ISBLANK($G237)),$C$42-$F$40-$F$42,"") | C237: =IF(AND(NOT(ISBLANK($G236)),ISBLANK($G237)),"Reste réel","") | D237: =IF(AND(NOT(ISBLANK($G236)),ISBLANK($G237)),$C$42-$H$40-$F$42,"")

Sheet Mai 2026
B1: Recettes | E1: Dépenses | K1: Cadeau
B3: Salaire Pierre | C3: 5357.67 | E3: Loyer Elouen | F3: 669.7 | G3: x | H3: =IF(G3="x",F3,0) -> 669.7 | K3: Logement
B4: Salaire Sterenn | C4: 2011.6 | E4: Argent de poche Elouen | H4: =IF(G4="x",F4,0) -> 0 | K4: Charges
B5: CAF | C5: 114.19 | E5: Engie Elouen | F5: 70 | G5: x | H5: =IF(G5="x",F5,0) -> 70 | K5: Charges
E6: Argent de poche Arthur | F6: 164.99 | G6: x | H6: =IF(G6="x",F6,0) -> 164.99 | K6: Charges
E7: Prêt 25 | F7: 995.15 | G7: x | H7: =IF(G7="x",F7,0) -> 995.15 | K7: Logement
E8: Prêt 15 | F8: 883.42 | G8: x | H8: =IF(G8="x",F8,0) -> 883.42 | K8: Logement
B9: Remboursement Suravenir | C9: 51.15 | E9: Assurances prêt | F9: 11.46 | G9: x | H9: =IF(G9="x",F9,0) -> 11.46 | K9: Logement
B10: Note de frais CAP | C10: 55.3 | E10: Assurances prêt | F10: 32.57 | G10: x | H10: =IF(G10="x",F10,0) -> 32.57 | K10: Logement
B11: Remboursement La Redoute | C11: 39.99 | E11: Assurances prêt | F11: 79.98 | G11: x | H11: =IF(G11="x",F11,0) -> 79.98 | K11: Logement
B12: Colle Nolwenn | C12: 5 | E12: Assurances prêt | F12: 28.49 | G12: x | H12: =IF(G12="x",F12,0) -> 28.49 | K12: Logement
B13: Remboursement mutuelle | C13: 9 | E13: Disney | F13: 6.99 | G13: x | H13: =IF(G13="x",F13,0) -> 6.99 | K13: Internet/Téléphone
B14: Epargne | C14: 1000 | E14: EDF Arthur | F14: 65 | G14: x | H14: =IF(G14="x",F14,0) -> 65 | K14: Charges
B15: CPAM | C15: 17 | E15: EkWateur | F15: 208 | G15: x | H15: =IF(G15="x",F15,0) -> 208 | K15: Charges
B16: CPAM | C16: 12 | E16: Sosh Maison | F16: 24.99 | G16: x | H16: =IF(G16="x",F16,0) -> 24.99 | K16: Internet/Téléphone
B17: Mutuelle | C17: 18 | E17: Sosh Arthur | F17: 14.99 | G17: x | H17: =IF(G17="x",F17,0) -> 14.99 | K17: Internet/Téléphone
B18: Mutuelle | C18: 9 | E18: Sosh Ael | F18: 14.99 | H18: =IF(G18="x",F18,0) -> 0 | K18: Internet/Téléphone
B19: CPAM | C19: 20.05 | E19: Sosh Elouen | F19: 14.99 | G19: x | H19: =IF(G19="x",F19,0) -> 14.99 | K19: Internet/Téléphone
E20: Sosh Sterenn | F20: 10.99 | G20: x | H20: =IF(G20="x",F20,0) -> 10.99 | K20: Internet/Téléphone
E21: Mutuelle | F21: 104.98 | G21: x | H21: =IF(G21="x",F21,0) -> 104.98 | K21: Assurances/Mutuelle
E23: AxaHabitation | F23: 69.38 | G23: x | H23: =IF(G23="x",F23,0) -> 69.38 | K23: Assurances/Mutuelle
E24: VW LDD | F24: 331.65 | G24: x | H24: =IF(G24="x",F24,0) -> 331.65 | K24: Voiture/Déplacement
E25: Suravenir Voiture | F25: 94.53 | G25: x | H25: =IF(G25="x",F25,0) -> 94.53 | K25: Assurances/Mutuelle
E26: Suravenir Garanties Vie | F26: 19 | H26: =IF(G26="x",F26,0) -> 0 | K26: Assurances/Mutuelle
E27: Joséphine | F27: 20 | G27: x | H27: =IF(G27="x",F27,0) -> 20 | K27: Divers
E28: Canal Plus | F28: 21.99 | G28: x | H28: =IF(G28="x",F28,0) -> 21.99 | K28: Internet/Téléphone
H29: =IF(G29="x",F29,0) -> 0 | K29: Voiture/Déplacement
E30: Keolis Elouen | F30: 21.4 | G30: x | H30: =IF(G30="x",F30,0) -> 21.4 | K30: Voiture/Déplacement
E31: Apple | F31: 0.99 | G31: x | H31: =IF(G31="x",F31,0) -> 0.99 | K31: Internet/Téléphone
E32: Apple | F32: 0.99 | G32: x | H32: =IF(G32="x",F32,0) -> 0.99 | K32: Internet/Téléphone
E33: Apple | F33: 16.99 | G33: x | H33: =IF(G33="x",F33,0) -> 16.99 | K33: Internet/Téléphone
E34: St Charles | F34: 278.3 | G34: x | H34: =IF(G34="x",F34,0) -> 278.3 | K34: Scolarité
E35: Ménage | F35: 102 | G35: x | H35: =IF(G35="x",F35,0) -> 102 | K35: Logement
E36: Urssaaf | F36: 129.86 | G36: x | H36: =IF(G36="x",F36,0) -> 129.86 | K36: Logement
E37: Cotisation Eurocompte | F37: 19.03 | G37: x | H37: =IF(G37="x",F37,0) -> 19.03 | K37: Charges
E38: Indivision | F38: 33.89 | G38: x | H38: =IF(G38="x",F38,0) -> 33.89 | K38: Charges
A39: Etat mois précédent | C39: ='Avril 2026'!D43 -> #REF!
A40: Recettes fixes | C40: =SUM(C2:C6) -> 7483.46 | E40: Somme dépenses prévues | F40: =SUM(F2:F38) -> 4561.68 | G40: Somme dépenses réelles | H40: =SUM(H2:H38) -> 4527.69 | I40: Delta moins les exceptions
A41: Recettes additionnelles du mois | C41: =SUM(C8:C35) -> 1236.49 | E41: Reste previsionnel | F41: =C42-F40 -> #REF! | G41: Delta du mois | H41: =C39+C40+C41-H40-F42 -> #REF!
A42: Total Recettes | C42: =SUM(C39:C41) -> #REF! | E42: Somme dépenses non prévues | F42: =SUM(J44:J246) -> 4646.71
A43: Reste prévu | B43: =$C$42-$F$40-$F$42 -> #REF! | C43: Reste réel | D43: =$C$42-$H$40-$F$42 -> #REF!
A44: =IF(AND(NOT(ISBLANK(#REF!)),ISBLANK(G44)),"Reste prévu","") -> Reste prévu | B44: =IF(AND(NOT(ISBLANK(#REF!)),ISBLANK($G44)),$C$42-$F$40-$F$42,"") -> #REF! | C44: =IF(AND(NOT(ISBLANK(#REF!)),ISBLANK($G44)),"Reste réel","") -> Reste réel | D44: =IF(AND(NOT(ISBLANK(#REF!)),ISBLANK($G44)),$C$42-$H$40-$F$42,"") -> #REF! | J44: =IF(I44="x",H44,0) -> 0 | K44: Loisirs
A45: =IF(AND(NOT(ISBLANK(G44)),ISBLANK(G45)),"Reste prévu","") | B45: =IF(AND(NOT(ISBLANK($G44)),ISBLANK($G45)),$C$42-$F$40-$F$42,"") | C45: =IF(AND(NOT(ISBLANK($G44)),ISBLANK($G45)),"Reste réel","") | D45: =IF(AND(NOT(ISBLANK($G44)),ISBLANK($G45)),$C$42-$H$40-$F$42,"") | J45: =IF(I45="x",H45,0) -> 0 | K45: Divers
A46: =IF(AND(NOT(ISBLANK(G45)),ISBLANK(G46)),"Reste prévu","") | B46: =IF(AND(NOT(ISBLANK($G45)),ISBLANK($G46)),$C$42-$F$40-$F$42,"") | C46: =IF(AND(NOT(ISBLANK($G45)),ISBLANK($G46)),"Reste réel","") | D46: =IF(AND(NOT(ISBLANK($G45)),ISBLANK($G46)),$C$42-$H$40-$F$42,"") | G46: FoireFouille | H46: 12.98 | I46: x | J46: =IF(I46="x",H46,0) -> 12.98 | K46: Divers
A47: =IF(AND(NOT(ISBLANK(G46)),ISBLANK(G47)),"Reste prévu","") | B47: =IF(AND(NOT(ISBLANK($G46)),ISBLANK($G47)),$C$42-$F$40-$F$42,"") | C47: =IF(AND(NOT(ISBLANK($G46)),ISBLANK($G47)),"Reste réel","") | D47: =IF(AND(NOT(ISBLANK($G46)),ISBLANK($G47)),$C$42-$H$40-$F$42,"") | G47: Leclerc | H47: 66.4 | I47: x | J47: =IF(I47="x",H47,0) -> 66.4 | K47: Courses
A48: =IF(AND(NOT(ISBLANK(G47)),ISBLANK(G48)),"Reste prévu","") | B48: =IF(AND(NOT(ISBLANK($G47)),ISBLANK($G48)),$C$42-$F$40-$F$42,"") | C48: =IF(AND(NOT(ISBLANK($G47)),ISBLANK($G48)),"Reste réel","") | D48: =IF(AND(NOT(ISBLANK($G47)),ISBLANK($G48)),$C$42-$H$40-$F$42,"") | G48: Leclerc | H48: 84.83 | I48: x | J48: =IF(I48="x",H48,0) -> 84.83 | K48: Courses
A49: =IF(AND(NOT(ISBLANK(G48)),ISBLANK(G49)),"Reste prévu","") | B49: =IF(AND(NOT(ISBLANK($G48)),ISBLANK($G49)),$C$42-$F$40-$F$42,"") | C49: =IF(AND(NOT(ISBLANK($G48)),ISBLANK($G49)),"Reste réel","") | D49: =IF(AND(NOT(ISBLANK($G48)),ISBLANK($G49)),$C$42-$H$40-$F$42,"") | G49: Decathlon | H49: 21.98 | I49: x | J49: =IF(I49="x",H49,0) -> 21.98 | K49: Vêtements
A50: =IF(AND(NOT(ISBLANK(G49)),ISBLANK(G50)),"Reste prévu","") | B50: =IF(AND(NOT(ISBLANK($G49)),ISBLANK($G50)),$C$42-$F$40-$F$42,"") | C50: =IF(AND(NOT(ISBLANK($G49)),ISBLANK($G50)),"Reste réel","") | D50: =IF(AND(NOT(ISBLANK($G49)),ISBLANK($G50)),$C$42-$H$40-$F$42,"") | G50: Decathlon Colle Hand | H50: 49.98 | I50: x | J50: =IF(I50="x",H50,0) -> 49.98 | K50: Divers
A51: =IF(AND(NOT(ISBLANK(G50)),ISBLANK(G51)),"Reste prévu","") | B51: =IF(AND(NOT(ISBLANK($G50)),ISBLANK($G51)),$C$42-$F$40-$F$42,"") | C51: =IF(AND(NOT(ISBLANK($G50)),ISBLANK($G51)),"Reste réel","") | D51: =IF(AND(NOT(ISBLANK($G50)),ISBLANK($G51)),$C$42-$H$40-$F$42,"") | G51: Café Station | H51: 1.9 | I51: x | J51: =IF(I51="x",H51,0) -> 1.9 | K51: Courses
A52: =IF(AND(NOT(ISBLANK(G51)),ISBLANK(G52)),"Reste prévu","") | B52: =IF(AND(NOT(ISBLANK($G51)),ISBLANK($G52)),$C$42-$F$40-$F$42,"") | C52: =IF(AND(NOT(ISBLANK($G51)),ISBLANK($G52)),"Reste réel","") | D52: =IF(AND(NOT(ISBLANK($G51)),ISBLANK($G52)),$C$42-$H$40-$F$42,"") | G52: Café Station | H52: 2.7 | I52: x | J52: =IF(I52="x",H52,0) -> 2.7 | K52: Courses
A53: =IF(AND(NOT(ISBLANK(G52)),ISBLANK(G53)),"Reste prévu","") | B53: =IF(AND(NOT(ISBLANK($G52)),ISBLANK($G53)),$C$42-$F$40-$F$42,"") | C53: =IF(AND(NOT(ISBLANK($G52)),ISBLANK($G53)),"Reste réel","") | D53: =IF(AND(NOT(ISBLANK($G52)),ISBLANK($G53)),$C$42-$H$40-$F$42,"") | G53: Café Station | H53: 3.5 | I53: x | J53: =IF(I53="x",H53,0) -> 3.5 | K53: Courses
A54: =IF(AND(NOT(ISBLANK(G53)),ISBLANK(G54)),"Reste prévu","") | B54: =IF(AND(NOT(ISBLANK($G53)),ISBLANK($G54)),$C$42-$F$40-$F$42,"") | C54: =IF(AND(NOT(ISBLANK($G53)),ISBLANK($G54)),"Reste réel","") | D54: =IF(AND(NOT(ISBLANK($G53)),ISBLANK($G54)),$C$42-$H$40-$F$42,"") | G54: Traversée Bac | H54: 11 | I54: x | J54: =IF(I54="x",H54,0) -> 11 | K54: Voiture/Déplacement
A55: =IF(AND(NOT(ISBLANK(G54)),ISBLANK(G55)),"Reste prévu","") | B55: =IF(AND(NOT(ISBLANK($G54)),ISBLANK($G55)),$C$42-$F$40-$F$42,"") | C55: =IF(AND(NOT(ISBLANK($G54)),ISBLANK($G55)),"Reste réel","") | D55: =IF(AND(NOT(ISBLANK($G54)),ISBLANK($G55)),$C$42-$H$40-$F$42,"") | G55: Station | H55: 22.4 | I55: x | J55: =IF(I55="x",H55,0) -> 22.4 | K55: Courses
A56: =IF(AND(NOT(ISBLANK(G55)),ISBLANK(G56)),"Reste prévu","") | B56: =IF(AND(NOT(ISBLANK($G55)),ISBLANK($G56)),$C$42-$F$40-$F$42,"") | C56: =IF(AND(NOT(ISBLANK($G55)),ISBLANK($G56)),"Reste réel","") | D56: =IF(AND(NOT(ISBLANK($G55)),ISBLANK($G56)),$C$42-$H$40-$F$42,"") | G56: Bac Royan | H56: 44 | I56: x | J56: =IF(I56="x",H56,0) -> 44 | K56: Voiture/Déplacement
A57: =IF(AND(NOT(ISBLANK(G56)),ISBLANK(G57)),"Reste prévu","") | B57: =IF(AND(NOT(ISBLANK($G56)),ISBLANK($G57)),$C$42-$F$40-$F$42,"") | C57: =IF(AND(NOT(ISBLANK($G56)),ISBLANK($G57)),"Reste réel","") | D57: =IF(AND(NOT(ISBLANK($G56)),ISBLANK($G57)),$C$42-$H$40-$F$42,"") | G57: Grand Frais | H57: 15.78 | I57: x | J57: =IF(I57="x",H57,0) -> 15.78 | K57: Courses
... A156: =IF(AND(NOT(ISBLANK(G155)),ISBLANK(G156)),"Reste prévu","") | B156: =IF(AND(NOT(ISBLANK($G155)),ISBLANK($G156)),$C$42-$F$40-$F$42,"") | C156: =IF(AND(NOT(ISBLANK($G155)),ISBLANK($G156)),"Reste réel","") | D156: =IF(AND(NOT(ISBLANK($G155)),ISBLANK($G156)),$C$42-$H$40-$F$42,"") | G156: Chocolat | H156: 25.05 | I156: x | J156: =IF(I156="x",H156,0) -> 25.05 | K156: Courses
A157: =IF(AND(NOT(ISBLANK(G156)),ISBLANK(G157)),"Reste prévu","") -> Reste prévu | B157: =IF(AND(NOT(ISBLANK($G156)),ISBLANK($G157)),$C$42-$F$40-$F$42,"") -> #REF! | C157: =IF(AND(NOT(ISBLANK($G156)),ISBLANK($G157)),"Reste réel","") -> Reste réel | D157: =IF(AND(NOT(ISBLANK($G156)),ISBLANK($G157)),$C$42-$H$40-$F$42,"") -> #REF! | J157: =IF(I157="x",H157,0) -> 0
A158: =IF(AND(NOT(ISBLANK(G157)),ISBLANK(G158)),"Reste prévu","") | B158: =IF(AND(NOT(ISBLANK($G157)),ISBLANK($G158)),$C$42-$F$40-$F$42,"") | C158: =IF(AND(NOT(ISBLANK($G157)),ISBLANK($G158)),"Reste réel","") | D158: =IF(AND(NOT(ISBLANK($G157)),ISBLANK($G158)),$C$42-$H$40-$F$42,"") | J158: =IF(I158="x",H158,0) -> 0
A159: =IF(AND(NOT(ISBLANK(G158)),ISBLANK(G159)),"Reste prévu","") | B159: =IF(AND(NOT(ISBLANK($G158)),ISBLANK($G159)),$C$42-$F$40-$F$42,"") | C159: =IF(AND(NOT(ISBLANK($G158)),ISBLANK($G159)),"Reste réel","") | D159: =IF(AND(NOT(ISBLANK($G158)),ISBLANK($G159)),$C$42-$H$40-$F$42,"") | J159: =IF(I159="x",H159,0) -> 0
A160: =IF(AND(NOT(ISBLANK(G159)),ISBLANK(G160)),"Reste prévu","") | B160: =IF(AND(NOT(ISBLANK($G159)),ISBLANK($G160)),$C$42-$F$40-$F$42,"") | C160: =IF(AND(NOT(ISBLANK($G159)),ISBLANK($G160)),"Reste réel","") | D160: =IF(AND(NOT(ISBLANK($G159)),ISBLANK($G160)),$C$42-$H$40-$F$42,"") | J160: =IF(I160="x",H160,0) -> 0
A161: =IF(AND(NOT(ISBLANK(G160)),ISBLANK(G161)),"Reste prévu","") | B161: =IF(AND(NOT(ISBLANK($G160)),ISBLANK($G161)),$C$42-$F$40-$F$42,"") | C161: =IF(AND(NOT(ISBLANK($G160)),ISBLANK($G161)),"Reste réel","") | D161: =IF(AND(NOT(ISBLANK($G160)),ISBLANK($G161)),$C$42-$H$40-$F$42,"") | J161: =IF(I161="x",H161,0) -> 0
A162: =IF(AND(NOT(ISBLANK(G161)),ISBLANK(G162)),"Reste prévu","") | B162: =IF(AND(NOT(ISBLANK($G161)),ISBLANK($G162)),$C$42-$F$40-$F$42,"") | C162: =IF(AND(NOT(ISBLANK($G161)),ISBLANK($G162)),"Reste réel","") | D162: =IF(AND(NOT(ISBLANK($G161)),ISBLANK($G162)),$C$42-$H$40-$F$42,"") | J162: =IF(I162="x",H162,0) -> 0
A163: =IF(AND(NOT(ISBLANK(G162)),ISBLANK(G163)),"Reste prévu","") | B163: =IF(AND(NOT(ISBLANK($G162)),ISBLANK($G163)),$C$42-$F$40-$F$42,"") | C163: =IF(AND(NOT(ISBLANK($G162)),ISBLANK($G163)),"Reste réel","") | D163: =IF(AND(NOT(ISBLANK($G162)),ISBLANK($G163)),$C$42-$H$40-$F$42,"") | J163: =IF(I163="x",H163,0) -> 0
A164: =IF(AND(NOT(ISBLANK(G163)),ISBLANK(G164)),"Reste prévu","") | B164: =IF(AND(NOT(ISBLANK($G163)),ISBLANK($G164)),$C$42-$F$40-$F$42,"") | C164: =IF(AND(NOT(ISBLANK($G163)),ISBLANK($G164)),"Reste réel","") | D164: =IF(AND(NOT(ISBLANK($G163)),ISBLANK($G164)),$C$42-$H$40-$F$42,"") | J164: =IF(I164="x",H164,0) -> 0
A165: =IF(AND(NOT(ISBLANK(G164)),ISBLANK(G165)),"Reste prévu","") | B165: =IF(AND(NOT(ISBLANK($G164)),ISBLANK($G165)),$C$42-$F$40-$F$42,"") | C165: =IF(AND(NOT(ISBLANK($G164)),ISBLANK($G165)),"Reste réel","") | D165: =IF(AND(NOT(ISBLANK($G164)),ISBLANK($G165)),$C$42-$H$40-$F$42,"") | J165: =IF(I165="x",H165,0) -> 0
A166: =IF(AND(NOT(ISBLANK(G165)),ISBLANK(G166)),"Reste prévu","") | B166: =IF(AND(NOT(ISBLANK($G165)),ISBLANK($G166)),$C$42-$F$40-$F$42,"") | C166: =IF(AND(NOT(ISBLANK($G165)),ISBLANK($G166)),"Reste réel","") | D166: =IF(AND(NOT(ISBLANK($G165)),ISBLANK($G166)),$C$42-$H$40-$F$42,"") | J166: =IF(I166="x",H166,0) -> 0
A167: =IF(AND(NOT(ISBLANK(G166)),ISBLANK(G167)),"Reste prévu","") | B167: =IF(AND(NOT(ISBLANK($G166)),ISBLANK($G167)),$C$42-$F$40-$F$42,"") | C167: =IF(AND(NOT(ISBLANK($G166)),ISBLANK($G167)),"Reste réel","") | D167: =IF(AND(NOT(ISBLANK($G166)),ISBLANK($G167)),$C$42-$H$40-$F$42,"") | J167: =IF(I167="x",H167,0) -> 0
A168: =IF(AND(NOT(ISBLANK(G167)),ISBLANK(G168)),"Reste prévu","") | B168: =IF(AND(NOT(ISBLANK($G167)),ISBLANK($G168)),$C$42-$F$40-$F$42,"") | C168: =IF(AND(NOT(ISBLANK($G167)),ISBLANK($G168)),"Reste réel","") | D168: =IF(AND(NOT(ISBLANK($G167)),ISBLANK($G168)),$C$42-$H$40-$F$42,"") | J168: =IF(I168="x",H168,0) -> 0
... A213: =IF(AND(NOT(ISBLANK(G212)),ISBLANK(G213)),"Reste prévu","") | B213: =IF(AND(NOT(ISBLANK($G212)),ISBLANK($G213)),$C$42-$F$40-$F$42,"") | C213: =IF(AND(NOT(ISBLANK($G212)),ISBLANK($G213)),"Reste réel","") | D213: =IF(AND(NOT(ISBLANK($G212)),ISBLANK($G213)),$C$42-$H$40-$F$42,"") | J213: =IF(I213="x",H213,0) -> 0
A214: =IF(AND(NOT(ISBLANK(G213)),ISBLANK(G214)),"Reste prévu","") | B214: =IF(AND(NOT(ISBLANK($G213)),ISBLANK($G214)),$C$42-$F$40-$F$42,"") | C214: =IF(AND(NOT(ISBLANK($G213)),ISBLANK($G214)),"Reste réel","") | D214: =IF(AND(NOT(ISBLANK($G213)),ISBLANK($G214)),$C$42-$H$40-$F$42,"")
A215: =IF(AND(NOT(ISBLANK(G214)),ISBLANK(G215)),"Reste prévu","") | B215: =IF(AND(NOT(ISBLANK($G214)),ISBLANK($G215)),$C$42-$F$40-$F$42,"") | C215: =IF(AND(NOT(ISBLANK($G214)),ISBLANK($G215)),"Reste réel","") | D215: =IF(AND(NOT(ISBLANK($G214)),ISBLANK($G215)),$C$42-$H$40-$F$42,"")
A216: =IF(AND(NOT(ISBLANK(G215)),ISBLANK(G216)),"Reste prévu","") | B216: =IF(AND(NOT(ISBLANK($G215)),ISBLANK($G216)),$C$42-$F$40-$F$42,"") | C216: =IF(AND(NOT(ISBLANK($G215)),ISBLANK($G216)),"Reste réel","") | D216: =IF(AND(NOT(ISBLANK($G215)),ISBLANK($G216)),$C$42-$H$40-$F$42,"")
A217: =IF(AND(NOT(ISBLANK(G216)),ISBLANK(G217)),"Reste prévu","") | B217: =IF(AND(NOT(ISBLANK($G216)),ISBLANK($G217)),$C$42-$F$40-$F$42,"") | C217: =IF(AND(NOT(ISBLANK($G216)),ISBLANK($G217)),"Reste réel","") | D217: =IF(AND(NOT(ISBLANK($G216)),ISBLANK($G217)),$C$42-$H$40-$F$42,"")
A218: =IF(AND(NOT(ISBLANK(G217)),ISBLANK(G218)),"Reste prévu","") | B218: =IF(AND(NOT(ISBLANK($G217)),ISBLANK($G218)),$C$42-$F$40-$F$42,"") | C218: =IF(AND(NOT(ISBLANK($G217)),ISBLANK($G218)),"Reste réel","") | D218: =IF(AND(NOT(ISBLANK($G217)),ISBLANK($G218)),$C$42-$H$40-$F$42,"")
A219: =IF(AND(NOT(ISBLANK(G218)),ISBLANK(G219)),"Reste prévu","") | B219: =IF(AND(NOT(ISBLANK($G218)),ISBLANK($G219)),$C$42-$F$40-$F$42,"") | C219: =IF(AND(NOT(ISBLANK($G218)),ISBLANK($G219)),"Reste réel","") | D219: =IF(AND(NOT(ISBLANK($G218)),ISBLANK($G219)),$C$42-$H$40-$F$42,"")
A220: =IF(AND(NOT(ISBLANK(G219)),ISBLANK(G220)),"Reste prévu","") | B220: =IF(AND(NOT(ISBLANK($G219)),ISBLANK($G220)),$C$42-$F$40-$F$42,"") | C220: =IF(AND(NOT(ISBLANK($G219)),ISBLANK($G220)),"Reste réel","") | D220: =IF(AND(NOT(ISBLANK($G219)),ISBLANK($G220)),$C$42-$H$40-$F$42,"")
A221: =IF(AND(NOT(ISBLANK(G220)),ISBLANK(G221)),"Reste prévu","") | B221: =IF(AND(NOT(ISBLANK($G220)),ISBLANK($G221)),$C$42-$F$40-$F$42,"") | C221: =IF(AND(NOT(ISBLANK($G220)),ISBLANK($G221)),"Reste réel","") | D221: =IF(AND(NOT(ISBLANK($G220)),ISBLANK($G221)),$C$42-$H$40-$F$42,"")
A222: =IF(AND(NOT(ISBLANK(G221)),ISBLANK(G222)),"Reste prévu","") | B222: =IF(AND(NOT(ISBLANK($G221)),ISBLANK($G222)),$C$42-$F$40-$F$42,"") | C222: =IF(AND(NOT(ISBLANK($G221)),ISBLANK($G222)),"Reste réel","") | D222: =IF(AND(NOT(ISBLANK($G221)),ISBLANK($G222)),$C$42-$H$40-$F$42,"")
A223: =IF(AND(NOT(ISBLANK(G222)),ISBLANK(G223)),"Reste prévu","") | B223: =IF(AND(NOT(ISBLANK($G222)),ISBLANK($G223)),$C$42-$F$40-$F$42,"") | C223: =IF(AND(NOT(ISBLANK($G222)),ISBLANK($G223)),"Reste réel","") | D223: =IF(AND(NOT(ISBLANK($G222)),ISBLANK($G223)),$C$42-$H$40-$F$42,"")
A224: =IF(AND(NOT(ISBLANK(G223)),ISBLANK(G224)),"Reste prévu","") | B224: =IF(AND(NOT(ISBLANK($G223)),ISBLANK($G224)),$C$42-$F$40-$F$42,"") | C224: =IF(AND(NOT(ISBLANK($G223)),ISBLANK($G224)),"Reste réel","") | D224: =IF(AND(NOT(ISBLANK($G223)),ISBLANK($G224)),$C$42-$H$40-$F$42,"")
A225: =IF(AND(NOT(ISBLANK(G224)),ISBLANK(G225)),"Reste prévu","") | B225: =IF(AND(NOT(ISBLANK($G224)),ISBLANK($G225)),$C$42-$F$40-$F$42,"") | C225: =IF(AND(NOT(ISBLANK($G224)),ISBLANK($G225)),"Reste réel","") | D225: =IF(AND(NOT(ISBLANK($G224)),ISBLANK($G225)),$C$42-$H$40-$F$42,"")
... A236: =IF(AND(NOT(ISBLANK(G235)),ISBLANK(G236)),"Reste prévu","") | B236: =IF(AND(NOT(ISBLANK($G235)),ISBLANK($G236)),$C$42-$F$40-$F$42,"") | C236: =IF(AND(NOT(ISBLANK($G235)),ISBLANK($G236)),"Reste réel","") | D236: =IF(AND(NOT(ISBLANK($G235)),ISBLANK($G236)),$C$42-$H$40-$F$42,"")

Sheet Avril 2026
B1: Recettes | E1: Dépenses | K1: Cadeau
B3: Salaire Pierre | C3: 6365.48 | E3: Loyer Elouen | F3: 669.7 | G3: x | H3: =IF(G3="x",F3,0) -> 669.7 | K3: Logement
B4: Salaire Sterenn | C4: 1828.73 | E4: Argent de poche Elouen | H4: =IF(G4="x",F4,0) -> 0 | K4: Charges
B5: CAF | C5: 113.3 | E5: Engie Elouen | F5: 70 | G5: x | H5: =IF(G5="x",F5,0) -> 70 | K5: Charges
E6: Argent de poche Arthur | F6: 164.99 | G6: x | H6: =IF(G6="x",F6,0) -> 164.99 | K6: Charges
E7: Prêt 25 | F7: 995.15 | G7: x | H7: =IF(G7="x",F7,0) -> 995.15 | K7: Logement
B8: Virement Mamou | C8: 150 | E8: Prêt 15 | F8: 883.42 | G8: x | H8: =IF(G8="x",F8,0) -> 883.42 | K8: Logement
B9: Note de Frais Igienair | C9: 121.83 | E9: Assurances prêt | F9: 11.46 | G9: x | H9: =IF(G9="x",F9,0) -> 11.46 | K9: Logement
B10: Stephanie Charrier | C10: 21 | E10: Assurances prêt | F10: 32.57 | G10: x | H10: =IF(G10="x",F10,0) -> 32.57 | K10: Logement
B11: Remboursement Suravenir | C11: 2.18 | E11: Assurances prêt | F11: 79.98 | G11: x | H11: =IF(G11="x",F11,0) -> 79.98 | K11: Logement
B12: Remboursement Suravenir | C12: 4.97 | E12: Assurances prêt | F12: 28.49 | G12: x | H12: =IF(G12="x",F12,0) -> 28.49 | K12: Logement
E13: Disney | F13: 6.99 | G13: x | H13: =IF(G13="x",F13,0) -> 6.99 | K13: Internet/Téléphone
E14: EDF Arthur | F14: 65 | G14: x | H14: =IF(G14="x",F14,0) -> 65 | K14: Charges
E15: EkWateur | F15: 208 | G15: x | H15: =IF(G15="x",F15,0) -> 208 | K15: Charges
E16: Sosh Maison | F16: 24.99 | G16: x | H16: =IF(G16="x",F16,0) -> 24.99 | K16: Internet/Téléphone
E17: Sosh Arthur | F17: 14.99 | G17: x | H17: =IF(G17="x",F17,0) -> 14.99 | K17: Internet/Téléphone
E18: Sosh Ael | F18: 14.99 | G18: x | H18: =IF(G18="x",F18,0) -> 14.99 | K18: Internet/Téléphone
E19: Sosh Elouen | F19: 14.99 | H19: =IF(G19="x",F19,0) -> 0 | K19: Internet/Téléphone
E20: Sosh Sterenn | F20: 10.99 | G20: x | H20: =IF(G20="x",F20,0) -> 10.99 | K20: Internet/Téléphone
E21: Mutuelle | F21: 104.98 | G21: x | H21: =IF(G21="x",F21,0) -> 104.98 | K21: Assurances/Mutuelle
E23: Suravenir Habitation | F23: 60.09 | G23: x | H23: =IF(G23="x",F23,0) -> 60.09 | K23: Assurances/Mutuelle
E24: VW LDD | F24: 331.65 | G24: x | H24: =IF(G24="x",F24,0) -> 331.65 | K24: Voiture/Déplacement
E25: Suravenir Voiture | F25: 133.7 | G25: x | H25: =IF(G25="x",F25,0) -> 133.7 | K25: Assurances/Mutuelle
E26: Suravenir Garanties Vie | F26: 29.97 | G26: x | H26: =IF(G26="x",F26,0) -> 29.97 | K26: Assurances/Mutuelle
E27: Joséphine | F27: 20 | G27: x | H27: =IF(G27="x",F27,0) -> 20 | K27: Divers
E28: Canal Plus | F28: 21.99 | G28: x | H28: =IF(G28="x",F28,0) -> 21.99 | K28: Internet/Téléphone
H29: =IF(G29="x",F29,0) -> 0 | K29: Voiture/Déplacement
E30: Keolis Elouen | F30: 21.4 | G30: x | H30: =IF(G30="x",F30,0) -> 21.4 | K30: Voiture/Déplacement
E31: Apple | F31: 0.99 | G31: x | H31: =IF(G31="x",F31,0) -> 0.99 | K31: Internet/Téléphone
E32: Apple | F32: 16.99 | G32: x | H32: =IF(G32="x",F32,0) -> 16.99 | K32: Internet/Téléphone
E33: St Charles | F33: 178.3 | G33: x | H33: =IF(G33="x",F33,0) -> 178.3 | K33: Scolarité
E34: Ménage | F34: 170 | G34: x | H34: =IF(G34="x",F34,0) -> 170 | K34: Logement
E35: Urssaaf | F35: 78.43 | G35: x | H35: =IF(G35="x",F35,0) -> 78.43 | K35: Logement
E36: Cotisation Eurocompte | F36: 16.85 | G36: x | H36: =IF(G36="x",F36,0) -> 16.85 | K36: Charges
E37: Indivision | F37: 33.89 | G37: x | H37: =IF(G37="x",F37,0) -> 33.89 | K37: Charges
A39: Etat mois précédent | C39: ='Mars 2026'!D43 -> #REF!
A40: Recettes fixes | C40: =SUM(C2:C6) -> 8307.51 | E40: Somme dépenses prévues | F40: =SUM(F2:F38) -> 4515.93 | G40: Somme dépenses réelles | H40: =SUM(H2:H38) -> 4500.94 | I40: Delta moins les exceptions
A41: Recettes additionnelles du mois | C41: =SUM(C8:C35) -> 299.98 | E41: Reste previsionnel | F41: =C42-F40 -> #REF! | G41: Delta du mois | H41: =C39+C40+C41-H40-F42 -> #REF!
A42: Total Recettes | C42: =SUM(C39:C41) -> #REF! | E42: Somme dépenses non prévues | F42: =SUM(J44:J246) -> 3979.86
A43: Reste prévu | B43: =$C$42-$F$40-$F$42 -> #REF! | C43: Reste réel | D43: =$C$42-$H$40-$F$42 -> #REF!
A44: =IF(AND(NOT(ISBLANK(#REF!)),ISBLANK(G44)),"Reste prévu","") -> Reste prévu | B44: =IF(AND(NOT(ISBLANK(#REF!)),ISBLANK($G44)),$C$42-$F$40-$F$42,"") -> #REF! | C44: =IF(AND(NOT(ISBLANK(#REF!)),ISBLANK($G44)),"Reste réel","") -> Reste réel | D44: =IF(AND(NOT(ISBLANK(#REF!)),ISBLANK($G44)),$C$42-$H$40-$F$42,"") -> #REF! | J44: =IF(I44="x",H44,0) -> 0 | K44: Loisirs
A45: =IF(AND(NOT(ISBLANK(G44)),ISBLANK(G45)),"Reste prévu","") | B45: =IF(AND(NOT(ISBLANK($G44)),ISBLANK($G45)),$C$42-$F$40-$F$42,"") | C45: =IF(AND(NOT(ISBLANK($G44)),ISBLANK($G45)),"Reste réel","") | D45: =IF(AND(NOT(ISBLANK($G44)),ISBLANK($G45)),$C$42-$H$40-$F$42,"") | G45: Cafran Trégeux (Eau Igienair) | H45: 96.83 | I45: x | J45: =IF(I45="x",H45,0) -> 96.83 | K45: Divers
A46: =IF(AND(NOT(ISBLANK(G45)),ISBLANK(G46)),"Reste prévu","") | B46: =IF(AND(NOT(ISBLANK($G45)),ISBLANK($G46)),$C$42-$F$40-$F$42,"") | C46: =IF(AND(NOT(ISBLANK($G45)),ISBLANK($G46)),"Reste réel","") | D46: =IF(AND(NOT(ISBLANK($G45)),ISBLANK($G46)),$C$42-$H$40-$F$42,"") | G46: Docteur Apel | H46: 30 | I46: x | J46: =IF(I46="x",H46,0) -> 30 | K46: Soins
A47: =IF(AND(NOT(ISBLANK(G46)),ISBLANK(G47)),"Reste prévu","") | B47: =IF(AND(NOT(ISBLANK($G46)),ISBLANK($G47)),$C$42-$F$40-$F$42,"") | C47: =IF(AND(NOT(ISBLANK($G46)),ISBLANK($G47)),"Reste réel","") | D47: =IF(AND(NOT(ISBLANK($G46)),ISBLANK($G47)),$C$42-$H$40-$F$42,"") | G47: Leclerc | H47: 252.37 | I47: x | J47: =IF(I47="x",H47,0) -> 252.37 | K47: Courses
A48: =IF(AND(NOT(ISBLANK(G47)),ISBLANK(G48)),"Reste prévu","") | B48: =IF(AND(NOT(ISBLANK($G47)),ISBLANK($G48)),$C$42-$F$40-$F$42,"") | C48: =IF(AND(NOT(ISBLANK($G47)),ISBLANK($G48)),"Reste réel","") | D48: =IF(AND(NOT(ISBLANK($G47)),ISBLANK($G48)),$C$42-$H$40-$F$42,"") | G48: Train Arthur | H48: 9 | I48: x | J48: =IF(I48="x",H48,0) -> 9 | K48: Voiture/Déplacement
A49: =IF(AND(NOT(ISBLANK(G48)),ISBLANK(G49)),"Reste prévu","") | B49: =IF(AND(NOT(ISBLANK($G48)),ISBLANK($G49)),$C$42-$F$40-$F$42,"") | C49: =IF(AND(NOT(ISBLANK($G48)),ISBLANK($G49)),"Reste réel","") | D49: =IF(AND(NOT(ISBLANK($G48)),ISBLANK($G49)),$C$42-$H$40-$F$42,"") | G49: Leclerc | H49: 20.84 | I49: x | J49: =IF(I49="x",H49,0) -> 20.84 | K49: Courses
A50: =IF(AND(NOT(ISBLANK(G49)),ISBLANK(G50)),"Reste prévu","") | B50: =IF(AND(NOT(ISBLANK($G49)),ISBLANK($G50)),$C$42-$F$40-$F$42,"") | C50: =IF(AND(NOT(ISBLANK($G49)),ISBLANK($G50)),"Reste réel","") | D50: =IF(AND(NOT(ISBLANK($G49)),ISBLANK($G50)),$C$42-$H$40-$F$42,"") | G50: Divers | H50: 49 | I50: x | J50: =IF(I50="x",H50,0) -> 49 | K50: Cadeau
A51: =IF(AND(NOT(ISBLANK(G50)),ISBLANK(G51)),"Reste prévu","") | B51: =IF(AND(NOT(ISBLANK($G50)),ISBLANK($G51)),$C$42-$F$40-$F$42,"") | C51: =IF(AND(NOT(ISBLANK($G50)),ISBLANK($G51)),"Reste réel","") | D51: =IF(AND(NOT(ISBLANK($G50)),ISBLANK($G51)),$C$42-$H$40-$F$42,"") | G51: Divers | H51: 75 | I51: x | J51: =IF(I51="x",H51,0) -> 75 | K51: Cadeau
A52: =IF(AND(NOT(ISBLANK(G51)),ISBLANK(G52)),"Reste prévu","") | B52: =IF(AND(NOT(ISBLANK($G51)),ISBLANK($G52)),$C$42-$F$40-$F$42,"") | C52: =IF(AND(NOT(ISBLANK($G51)),ISBLANK($G52)),"Reste réel","") | D52: =IF(AND(NOT(ISBLANK($G51)),ISBLANK($G52)),$C$42-$H$40-$F$42,"") | G52: Amazon | H52: 9.99 | I52: x | J52: =IF(I52="x",H52,0) -> 9.99 | K52: Internet/Téléphone
A53: =IF(AND(NOT(ISBLANK(G52)),ISBLANK(G53)),"Reste prévu","") | B53: =IF(AND(NOT(ISBLANK($G52)),ISBLANK($G53)),$C$42-$F$40-$F$42,"") | C53: =IF(AND(NOT(ISBLANK($G52)),ISBLANK($G53)),"Reste réel","") | D53: =IF(AND(NOT(ISBLANK($G52)),ISBLANK($G53)),$C$42-$H$40-$F$42,"") | G53: Intermarché Trégeux | H53: 33.75 | I53: x | J53: =IF(I53="x",H53,0) -> 33.75 | K53: Courses
A54: =IF(AND(NOT(ISBLANK(G53)),ISBLANK(G54)),"Reste prévu","") | B54: =IF(AND(NOT(ISBLANK($G53)),ISBLANK($G54)),$C$42-$F$40-$F$42,"") | C54: =IF(AND(NOT(ISBLANK($G53)),ISBLANK($G54)),"Reste réel","") | D54: =IF(AND(NOT(ISBLANK($G53)),ISBLANK($G54)),$C$42-$H$40-$F$42,"") | G54: Atelier Saint Cast | H54: 18 | I54: x | J54: =IF(I54="x",H54,0) -> 18 | K54: Cadeau
A55: =IF(AND(NOT(ISBLANK(G54)),ISBLANK(G55)),"Reste prévu","") | B55: =IF(AND(NOT(ISBLANK($G54)),ISBLANK($G55)),$C$42-$F$40-$F$42,"") | C55: =IF(AND(NOT(ISBLANK($G54)),ISBLANK($G55)),"Reste réel","") | D55: =IF(AND(NOT(ISBLANK($G54)),ISBLANK($G55)),$C$42-$H$40-$F$42,"") | G55: Metro Rennes | H55: 3.4 | I55: x | J55: =IF(I55="x",H55,0) -> 3.4 | K55: Voiture/Déplacement
A56: =IF(AND(NOT(ISBLANK(G55)),ISBLANK(G56)),"Reste prévu","") | B56: =IF(AND(NOT(ISBLANK($G55)),ISBLANK($G56)),$C$42-$F$40-$F$42,"") | C56: =IF(AND(NOT(ISBLANK($G55)),ISBLANK($G56)),"Reste réel","") | D56: =IF(AND(NOT(ISBLANK($G55)),ISBLANK($G56)),$C$42-$H$40-$F$42,"") | G56: Gouter Rennes | H56: 6.7 | I56: x | J56: =IF(I56="x",H56,0) -> 6.7 | K56: Courses
... A129: =IF(AND(NOT(ISBLANK(G128)),ISBLANK(G129)),"Reste prévu","") | B129: =IF(AND(NOT(ISBLANK($G128)),ISBLANK($G129)),$C$42-$F$40-$F$42,"") | C129: =IF(AND(NOT(ISBLANK($G128)),ISBLANK($G129)),"Reste réel","") | D129: =IF(AND(NOT(ISBLANK($G128)),ISBLANK($G129)),$C$42-$H$40-$F$42,"") | G129: Leclerc | H129: 25.5 | I129: x | J129: =IF(I129="x",H129,0) -> 25.5 | K129: Courses
A130: =IF(AND(NOT(ISBLANK(G129)),ISBLANK(G130)),"Reste prévu","") -> Reste prévu | B130: =IF(AND(NOT(ISBLANK($G129)),ISBLANK($G130)),$C$42-$F$40-$F$42,"") -> #REF! | C130: =IF(AND(NOT(ISBLANK($G129)),ISBLANK($G130)),"Reste réel","") -> Reste réel | D130: =IF(AND(NOT(ISBLANK($G129)),ISBLANK($G130)),$C$42-$H$40-$F$42,"") -> #REF! | J130: =IF(I130="x",H130,0) -> 0 | K130: Cadeau
A131: =IF(AND(NOT(ISBLANK(G130)),ISBLANK(G131)),"Reste prévu","") | B131: =IF(AND(NOT(ISBLANK($G130)),ISBLANK($G131)),$C$42-$F$40-$F$42,"") | C131: =IF(AND(NOT(ISBLANK($G130)),ISBLANK($G131)),"Reste réel","") | D131: =IF(AND(NOT(ISBLANK($G130)),ISBLANK($G131)),$C$42-$H$40-$F$42,"") | J131: =IF(I131="x",H131,0) -> 0 | K131: Courses
A132: =IF(AND(NOT(ISBLANK(G131)),ISBLANK(G132)),"Reste prévu","") | B132: =IF(AND(NOT(ISBLANK($G131)),ISBLANK($G132)),$C$42-$F$40-$F$42,"") | C132: =IF(AND(NOT(ISBLANK($G131)),ISBLANK($G132)),"Reste réel","") | D132: =IF(AND(NOT(ISBLANK($G131)),ISBLANK($G132)),$C$42-$H$40-$F$42,"") | J132: =IF(I132="x",H132,0) -> 0 | K132: Courses
A133: =IF(AND(NOT(ISBLANK(G132)),ISBLANK(G133)),"Reste prévu","") | B133: =IF(AND(NOT(ISBLANK($G132)),ISBLANK($G133)),$C$42-$F$40-$F$42,"") | C133: =IF(AND(NOT(ISBLANK($G132)),ISBLANK($G133)),"Reste réel","") | D133: =IF(AND(NOT(ISBLANK($G132)),ISBLANK($G133)),$C$42-$H$40-$F$42,"") | J133: =IF(I133="x",H133,0) -> 0 | K133: Divers
A134: =IF(AND(NOT(ISBLANK(G133)),ISBLANK(G134)),"Reste prévu","") | B134: =IF(AND(NOT(ISBLANK($G133)),ISBLANK($G134)),$C$42-$F$40-$F$42,"") | C134: =IF(AND(NOT(ISBLANK($G133)),ISBLANK($G134)),"Reste réel","") | D134: =IF(AND(NOT(ISBLANK($G133)),ISBLANK($G134)),$C$42-$H$40-$F$42,"") | J134: =IF(I134="x",H134,0) -> 0 | K134: Cadeau
A135: =IF(AND(NOT(ISBLANK(G134)),ISBLANK(G135)),"Reste prévu","") | B135: =IF(AND(NOT(ISBLANK($G134)),ISBLANK($G135)),$C$42-$F$40-$F$42,"") | C135: =IF(AND(NOT(ISBLANK($G134)),ISBLANK($G135)),"Reste réel","") | D135: =IF(AND(NOT(ISBLANK($G134)),ISBLANK($G135)),$C$42-$H$40-$F$42,"") | J135: =IF(I135="x",H135,0) -> 0 | K135: Courses
A136: =IF(AND(NOT(ISBLANK(G135)),ISBLANK(G136)),"Reste prévu","") | B136: =IF(AND(NOT(ISBLANK($G135)),ISBLANK($G136)),$C$42-$F$40-$F$42,"") | C136: =IF(AND(NOT(ISBLANK($G135)),ISBLANK($G136)),"Reste réel","") | D136: =IF(AND(NOT(ISBLANK($G135)),ISBLANK($G136)),$C$42-$H$40-$F$42,"") | J136: =IF(I136="x",H136,0) -> 0 | K136: Voiture/Déplacement
A137: =IF(AND(NOT(ISBLANK(G136)),ISBLANK(G137)),"Reste prévu","") | B137: =IF(AND(NOT(ISBLANK($G136)),ISBLANK($G137)),$C$42-$F$40-$F$42,"") | C137: =IF(AND(NOT(ISBLANK($G136)),ISBLANK($G137)),"Reste réel","") | D137: =IF(AND(NOT(ISBLANK($G136)),ISBLANK($G137)),$C$42-$H$40-$F$42,"") | J137: =IF(I137="x",H137,0) -> 0 | K137: Courses
A138: =IF(AND(NOT(ISBLANK(G137)),ISBLANK(G138)),"Reste prévu","") | B138: =IF(AND(NOT(ISBLANK($G137)),ISBLANK($G138)),$C$42-$F$40-$F$42,"") | C138: =IF(AND(NOT(ISBLANK($G137)),ISBLANK($G138)),"Reste réel","") | D138: =IF(AND(NOT(ISBLANK($G137)),ISBLANK($G138)),$C$42-$H$40-$F$42,"") | J138: =IF(I138="x",H138,0) -> 0 | K138: Courses
A139: =IF(AND(NOT(ISBLANK(G138)),ISBLANK(G139)),"Reste prévu","") | B139: =IF(AND(NOT(ISBLANK($G138)),ISBLANK($G139)),$C$42-$F$40-$F$42,"") | C139: =IF(AND(NOT(ISBLANK($G138)),ISBLANK($G139)),"Reste réel","") | D139: =IF(AND(NOT(ISBLANK($G138)),ISBLANK($G139)),$C$42-$H$40-$F$42,"") | J139: =IF(I139="x",H139,0) -> 0 | K139: Divers
A140: =IF(AND(NOT(ISBLANK(G139)),ISBLANK(G140)),"Reste prévu","") | B140: =IF(AND(NOT(ISBLANK($G139)),ISBLANK($G140)),$C$42-$F$40-$F$42,"") | C140: =IF(AND(NOT(ISBLANK($G139)),ISBLANK($G140)),"Reste réel","") | D140: =IF(AND(NOT(ISBLANK($G139)),ISBLANK($G140)),$C$42-$H$40-$F$42,"") | J140: =IF(I140="x",H140,0) -> 0 | K140: Courses
A141: =IF(AND(NOT(ISBLANK(G140)),ISBLANK(G141)),"Reste prévu","") | B141: =IF(AND(NOT(ISBLANK($G140)),ISBLANK($G141)),$C$42-$F$40-$F$42,"") | C141: =IF(AND(NOT(ISBLANK($G140)),ISBLANK($G141)),"Reste réel","") | D141: =IF(AND(NOT(ISBLANK($G140)),ISBLANK($G141)),$C$42-$H$40-$F$42,"") | J141: =IF(I141="x",H141,0) -> 0 | K141: Cadeau
... A146: =IF(AND(NOT(ISBLANK(G145)),ISBLANK(G146)),"Reste prévu","") | B146: =IF(AND(NOT(ISBLANK($G145)),ISBLANK($G146)),$C$42-$F$40-$F$42,"") | C146: =IF(AND(NOT(ISBLANK($G145)),ISBLANK($G146)),"Reste réel","") | D146: =IF(AND(NOT(ISBLANK($G145)),ISBLANK($G146)),$C$42-$H$40-$F$42,"") | J146: =IF(I146="x",H146,0) -> 0 | K146: Cadeau
A147: =IF(AND(NOT(ISBLANK(G146)),ISBLANK(G147)),"Reste prévu","") | B147: =IF(AND(NOT(ISBLANK($G146)),ISBLANK($G147)),$C$42-$F$40-$F$42,"") | C147: =IF(AND(NOT(ISBLANK($G146)),ISBLANK($G147)),"Reste réel","") | D147: =IF(AND(NOT(ISBLANK($G146)),ISBLANK($G147)),$C$42-$H$40-$F$42,"") | J147: =IF(I147="x",H147,0) -> 0
A148: =IF(AND(NOT(ISBLANK(G147)),ISBLANK(G148)),"Reste prévu","") | B148: =IF(AND(NOT(ISBLANK($G147)),ISBLANK($G148)),$C$42-$F$40-$F$42,"") | C148: =IF(AND(NOT(ISBLANK($G147)),ISBLANK($G148)),"Reste réel","") | D148: =IF(AND(NOT(ISBLANK($G147)),ISBLANK($G148)),$C$42-$H$40-$F$42,"") | J148: =IF(I148="x",H148,0) -> 0
A149: =IF(AND(NOT(ISBLANK(G148)),ISBLANK(G149)),"Reste prévu","") | B149: =IF(AND(NOT(ISBLANK($G148)),ISBLANK($G149)),$C$42-$F$40-$F$42,"") | C149: =IF(AND(NOT(ISBLANK($G148)),ISBLANK($G149)),"Reste réel","") | D149: =IF(AND(NOT(ISBLANK($G148)),ISBLANK($G149)),$C$42-$H$40-$F$42,"") | J149: =IF(I149="x",H149,0) -> 0
A150: =IF(AND(NOT(ISBLANK(G149)),ISBLANK(G150)),"Reste prévu","") | B150: =IF(AND(NOT(ISBLANK($G149)),ISBLANK($G150)),$C$42-$F$40-$F$42,"") | C150: =IF(AND(NOT(ISBLANK($G149)),ISBLANK($G150)),"Reste réel","") | D150: =IF(AND(NOT(ISBLANK($G149)),ISBLANK($G150)),$C$42-$H$40-$F$42,"") | J150: =IF(I150="x",H150,0) -> 0
A151: =IF(AND(NOT(ISBLANK(G150)),ISBLANK(G151)),"Reste prévu","") | B151: =IF(AND(NOT(ISBLANK($G150)),ISBLANK($G151)),$C$42-$F$40-$F$42,"") | C151: =IF(AND(NOT(ISBLANK($G150)),ISBLANK($G151)),"Reste réel","") | D151: =IF(AND(NOT(ISBLANK($G150)),ISBLANK($G151)),$C$42-$H$40-$F$42,"") | J151: =IF(I151="x",H151,0) -> 0
A152: =IF(AND(NOT(ISBLANK(G151)),ISBLANK(G152)),"Reste prévu","") | B152: =IF(AND(NOT(ISBLANK($G151)),ISBLANK($G152)),$C$42-$F$40-$F$42,"") | C152: =IF(AND(NOT(ISBLANK($G151)),ISBLANK($G152)),"Reste réel","") | D152: =IF(AND(NOT(ISBLANK($G151)),ISBLANK($G152)),$C$42-$H$40-$F$42,"") | J152: =IF(I152="x",H152,0) -> 0
A153: =IF(AND(NOT(ISBLANK(G152)),ISBLANK(G153)),"Reste prévu","") | B153: =IF(AND(NOT(ISBLANK($G152)),ISBLANK($G153)),$C$42-$F$40-$F$42,"") | C153: =IF(AND(NOT(ISBLANK($G152)),ISBLANK($G153)),"Reste réel","") | D153: =IF(AND(NOT(ISBLANK($G152)),ISBLANK($G153)),$C$42-$H$40-$F$42,"") | J153: =IF(I153="x",H153,0) -> 0
A154: =IF(AND(NOT(ISBLANK(G153)),ISBLANK(G154)),"Reste prévu","") | B154: =IF(AND(NOT(ISBLANK($G153)),ISBLANK($G154)),$C$42-$F$40-$F$42,"") | C154: =IF(AND(NOT(ISBLANK($G153)),ISBLANK($G154)),"Reste réel","") | D154: =IF(AND(NOT(ISBLANK($G153)),ISBLANK($G154)),$C$42-$H$40-$F$42,"") | J154: =IF(I154="x",H154,0) -> 0
A155: =IF(AND(NOT(ISBLANK(G154)),ISBLANK(G155)),"Reste prévu","") | B155: =IF(AND(NOT(ISBLANK($G154)),ISBLANK($G155)),$C$42-$F$40-$F$42,"") | C155: =IF(AND(NOT(ISBLANK($G154)),ISBLANK($G155)),"Reste réel","") | D155: =IF(AND(NOT(ISBLANK($G154)),ISBLANK($G155)),$C$42-$H$40-$F$42,"") | J155: =IF(I155="x",H155,0) -> 0
A156: =IF(AND(NOT(ISBLANK(G155)),ISBLANK(G156)),"Reste prévu","") | B156: =IF(AND(NOT(ISBLANK($G155)),ISBLANK($G156)),$C$42-$F$40-$F$42,"") | C156: =IF(AND(NOT(ISBLANK($G155)),ISBLANK($G156)),"Reste réel","") | D156: =IF(AND(NOT(ISBLANK($G155)),ISBLANK($G156)),$C$42-$H$40-$F$42,"") | J156: =IF(I156="x",H156,0) -> 0
A157: =IF(AND(NOT(ISBLANK(G156)),ISBLANK(G157)),"Reste prévu","") | B157: =IF(AND(NOT(ISBLANK($G156)),ISBLANK($G157)),$C$42-$F$40-$F$42,"") | C157: =IF(AND(NOT(ISBLANK($G156)),ISBLANK($G157)),"Reste réel","") | D157: =IF(AND(NOT(ISBLANK($G156)),ISBLANK($G157)),$C$42-$H$40-$F$42,"") | J157: =IF(I157="x",H157,0) -> 0
A158: =IF(AND(NOT(ISBLANK(G157)),ISBLANK(G158)),"Reste prévu","") | B158: =IF(AND(NOT(ISBLANK($G157)),ISBLANK($G158)),$C$42-$F$40-$F$42,"") | C158: =IF(AND(NOT(ISBLANK($G157)),ISBLANK($G158)),"Reste réel","") | D158: =IF(AND(NOT(ISBLANK($G157)),ISBLANK($G158)),$C$42-$H$40-$F$42,"") | J158: =IF(I158="x",H158,0) -> 0
... A213: =IF(AND(NOT(ISBLANK(G212)),ISBLANK(G213)),"Reste prévu","") | B213: =IF(AND(NOT(ISBLANK($G212)),ISBLANK($G213)),$C$42-$F$40-$F$42,"") | C213: =IF(AND(NOT(ISBLANK($G212)),ISBLANK($G213)),"Reste réel","") | D213: =IF(AND(NOT(ISBLANK($G212)),ISBLANK($G213)),$C$42-$H$40-$F$42,"") | J213: =IF(I213="x",H213,0) -> 0
A214: =IF(AND(NOT(ISBLANK(G213)),ISBLANK(G214)),"Reste prévu","") | B214: =IF(AND(NOT(ISBLANK($G213)),ISBLANK($G214)),$C$42-$F$40-$F$42,"") | C214: =IF(AND(NOT(ISBLANK($G213)),ISBLANK($G214)),"Reste réel","") | D214: =IF(AND(NOT(ISBLANK($G213)),ISBLANK($G214)),$C$42-$H$40-$F$42,"")
A215: =IF(AND(NOT(ISBLANK(G214)),ISBLANK(G215)),"Reste prévu","") | B215: =IF(AND(NOT(ISBLANK($G214)),ISBLANK($G215)),$C$42-$F$40-$F$42,"") | C215: =IF(AND(NOT(ISBLANK($G214)),ISBLANK($G215)),"Reste réel","") | D215: =IF(AND(NOT(ISBLANK($G214)),ISBLANK($G215)),$C$42-$H$40-$F$42,"")
A216: =IF(AND(NOT(ISBLANK(G215)),ISBLANK(G216)),"Reste prévu","") | B216: =IF(AND(NOT(ISBLANK($G215)),ISBLANK($G216)),$C$42-$F$40-$F$42,"") | C216: =IF(AND(NOT(ISBLANK($G215)),ISBLANK($G216)),"Reste réel","") | D216: =IF(AND(NOT(ISBLANK($G215)),ISBLANK($G216)),$C$42-$H$40-$F$42,"")
A217: =IF(AND(NOT(ISBLANK(G216)),ISBLANK(G217)),"Reste prévu","") | B217: =IF(AND(NOT(ISBLANK($G216)),ISBLANK($G217)),$C$42-$F$40-$F$42,"") | C217: =IF(AND(NOT(ISBLANK($G216)),ISBLANK($G217)),"Reste réel","") | D217: =IF(AND(NOT(ISBLANK($G216)),ISBLANK($G217)),$C$42-$H$40-$F$42,"")
A218: =IF(AND(NOT(ISBLANK(G217)),ISBLANK(G218)),"Reste prévu","") | B218: =IF(AND(NOT(ISBLANK($G217)),ISBLANK($G218)),$C$42-$F$40-$F$42,"") | C218: =IF(AND(NOT(ISBLANK($G217)),ISBLANK($G218)),"Reste réel","") | D218: =IF(AND(NOT(ISBLANK($G217)),ISBLANK($G218)),$C$42-$H$40-$F$42,"")
A219: =IF(AND(NOT(ISBLANK(G218)),ISBLANK(G219)),"Reste prévu","") | B219: =IF(AND(NOT(ISBLANK($G218)),ISBLANK($G219)),$C$42-$F$40-$F$42,"") | C219: =IF(AND(NOT(ISBLANK($G218)),ISBLANK($G219)),"Reste réel","") | D219: =IF(AND(NOT(ISBLANK($G218)),ISBLANK($G219)),$C$42-$H$40-$F$42,"")
A220: =IF(AND(NOT(ISBLANK(G219)),ISBLANK(G220)),"Reste prévu","") | B220: =IF(AND(NOT(ISBLANK($G219)),ISBLANK($G220)),$C$42-$F$40-$F$42,"") | C220: =IF(AND(NOT(ISBLANK($G219)),ISBLANK($G220)),"Reste réel","") | D220: =IF(AND(NOT(ISBLANK($G219)),ISBLANK($G220)),$C$42-$H$40-$F$42,"")
A221: =IF(AND(NOT(ISBLANK(G220)),ISBLANK(G221)),"Reste prévu","") | B221: =IF(AND(NOT(ISBLANK($G220)),ISBLANK($G221)),$C$42-$F$40-$F$42,"") | C221: =IF(AND(NOT(ISBLANK($G220)),ISBLANK($G221)),"Reste réel","") | D221: =IF(AND(NOT(ISBLANK($G220)),ISBLANK($G221)),$C$42-$H$40-$F$42,"")
A222: =IF(AND(NOT(ISBLANK(G221)),ISBLANK(G222)),"Reste prévu","") | B222: =IF(AND(NOT(ISBLANK($G221)),ISBLANK($G222)),$C$42-$F$40-$F$42,"") | C222: =IF(AND(NOT(ISBLANK($G221)),ISBLANK($G222)),"Reste réel","") | D222: =IF(AND(NOT(ISBLANK($G221)),ISBLANK($G222)),$C$42-$H$40-$F$42,"")
A223: =IF(AND(NOT(ISBLANK(G222)),ISBLANK(G223)),"Reste prévu","") | B223: =IF(AND(NOT(ISBLANK($G222)),ISBLANK($G223)),$C$42-$F$40-$F$42,"") | C223: =IF(AND(NOT(ISBLANK($G222)),ISBLANK($G223)),"Reste réel","") | D223: =IF(AND(NOT(ISBLANK($G222)),ISBLANK($G223)),$C$42-$H$40-$F$42,"")
A224: =IF(AND(NOT(ISBLANK(G223)),ISBLANK(G224)),"Reste prévu","") | B224: =IF(AND(NOT(ISBLANK($G223)),ISBLANK($G224)),$C$42-$F$40-$F$42,"") | C224: =IF(AND(NOT(ISBLANK($G223)),ISBLANK($G224)),"Reste réel","") | D224: =IF(AND(NOT(ISBLANK($G223)),ISBLANK($G224)),$C$42-$H$40-$F$42,"")
A225: =IF(AND(NOT(ISBLANK(G224)),ISBLANK(G225)),"Reste prévu","") | B225: =IF(AND(NOT(ISBLANK($G224)),ISBLANK($G225)),$C$42-$F$40-$F$42,"") | C225: =IF(AND(NOT(ISBLANK($G224)),ISBLANK($G225)),"Reste réel","") | D225: =IF(AND(NOT(ISBLANK($G224)),ISBLANK($G225)),$C$42-$H$40-$F$42,"")
... A236: =IF(AND(NOT(ISBLANK(G235)),ISBLANK(G236)),"Reste prévu","") | B236: =IF(AND(NOT(ISBLANK($G235)),ISBLANK($G236)),$C$42-$F$40-$F$42,"") | C236: =IF(AND(NOT(ISBLANK($G235)),ISBLANK($G236)),"Reste réel","") | D236: =IF(AND(NOT(ISBLANK($G235)),ISBLANK($G236)),$C$42-$H$40-$F$42,"")

Sheet Mars 2026
B1: Recettes | E1: Dépenses | K1: Cadeau
B3: Salaire Pierre | C3: 5258.61 | E3: Loyer Elouen | F3: 669.7 | G3: x | H3: =IF(G3="x",F3,0) -> 669.7 | K3: Logement
B4: Salaire Sterenn | C4: 1828.73 | E4: Argent de poche Elouen | H4: =IF(G4="x",F4,0) -> 0 | K4: Charges
B5: CAF | C5: 113.3 | E5: Engie Elouen | F5: 70 | G5: x | H5: =IF(G5="x",F5,0) -> 70 | K5: Charges
E6: Argent de poche Arthur | F6: 164.99 | G6: x | H6: =IF(G6="x",F6,0) -> 164.99 | K6: Charges
E7: Prêt 25 | F7: 995.15 | G7: x | H7: =IF(G7="x",F7,0) -> 995.15 | K7: Logement
E8: Prêt 15 | F8: 883.42 | G8: x | H8: =IF(G8="x",F8,0) -> 883.42 | K8: Logement
B9: Frais Igienair | C9: 93.15 | E9: Assurances prêt | F9: 11.46 | G9: x | H9: =IF(G9="x",F9,0) -> 11.46 | K9: Logement
B10: Mutuelle | C10: 10.5 | E10: Assurances prêt | F10: 32.57 | G10: x | H10: =IF(G10="x",F10,0) -> 32.57 | K10: Logement
B11: Epargne Travaux | C11: 599.17 | E11: Assurances prêt | F11: 79.98 | G11: x | H11: =IF(G11="x",F11,0) -> 79.98 | K11: Logement
B12: Remboursement Mitigeur Lidl | C12: 26.99 | E12: Assurances prêt | F12: 28.49 | G12: x | H12: =IF(G12="x",F12,0) -> 28.49 | K12: Logement
B13: CPAM | C13: 4 | E13: Disney | F13: 6.99 | G13: x | H13: =IF(G13="x",F13,0) -> 6.99 | K13: Internet/Téléphone
B14: Epargne Travaux | C14: 450 | E14: EDF Arthur | F14: 65 | G14: x | H14: =IF(G14="x",F14,0) -> 65 | K14: Charges
B15: Edouard Padel | C15: 4.2 | E15: EkWateur | F15: 208 | G15: x | H15: =IF(G15="x",F15,0) -> 208 | K15: Charges
B16: Jean Marie Raclette | C16: 15.67 | E16: Sosh Maison | F16: 24.99 | G16: x | H16: =IF(G16="x",F16,0) -> 24.99 | K16: Internet/Téléphone
B17: Epargne Travaux | C17: 178.72 | E17: Sosh Arthur | F17: 14.99 | G17: x | H17: =IF(G17="x",F17,0) -> 14.99 | K17: Internet/Téléphone
E18: Sosh Ael | F18: 14.99 | G18: x | H18: =IF(G18="x",F18,0) -> 14.99 | K18: Internet/Téléphone
E19: Sosh Elouen | F19: 14.99 | G19: x | H19: =IF(G19="x",F19,0) -> 14.99 | K19: Internet/Téléphone
E20: Sosh Sterenn | F20: 10.99 | G20: x | H20: =IF(G20="x",F20,0) -> 10.99 | K20: Internet/Téléphone
E21: Mutuelle | F21: 104.98 | G21: x | H21: =IF(G21="x",F21,0) -> 104.98 | K21: Assurances/Mutuelle
E23: Suravenir Habitation | F23: 60.09 | G23: x | H23: =IF(G23="x",F23,0) -> 60.09 | K23: Assurances/Mutuelle
E24: VW LDD | F24: 331.65 | G24: x | H24: =IF(G24="x",F24,0) -> 331.65 | K24: Voiture/Déplacement
E25: Suravenir Voiture | F25: 133.7 | G25: x | H25: =IF(G25="x",F25,0) -> 133.7 | K25: Assurances/Mutuelle
E26: Suravenir Garanties Vie | F26: 29.97 | G26: x | H26: =IF(G26="x",F26,0) -> 29.97 | K26: Assurances/Mutuelle
E27: Joséphine | F27: 20 | G27: x | H27: =IF(G27="x",F27,0) -> 20 | K27: Divers
E28: Canal Plus | F28: 21.99 | G28: x | H28: =IF(G28="x",F28,0) -> 21.99 | K28: Internet/Téléphone
H29: =IF(G29="x",F29,0) -> 0 | K29: Voiture/Déplacement
E30: Keolis Elouen | F30: 21.4 | G30: x | H30: =IF(G30="x",F30,0) -> 21.4 | K30: Voiture/Déplacement
E31: Apple | F31: 0.99 | G31: x | H31: =IF(G31="x",F31,0) -> 0.99 | K31: Internet/Téléphone
E32: Apple | F32: 16.99 | G32: x | H32: =IF(G32="x",F32,0) -> 16.99 | K32: Internet/Téléphone
E33: St Charles | F33: 178.3 | G33: x | H33: =IF(G33="x",F33,0) -> 178.3 | K33: Scolarité
E34: Ménage | F34: 102 | G34: x | H34: =IF(G34="x",F34,0) -> 102 | K34: Logement
E35: Urssaaf | F35: 104.6 | G35: x | H35: =IF(G35="x",F35,0) -> 104.6 | K35: Logement
E36: Cotisation Eurocompte | F36: 19.03 | G36: x | H36: =IF(G36="x",F36,0) -> 19.03
E37: Indivision | F37: 33.89 | G37: x | H37: =IF(G37="x",F37,0) -> 33.89
A39: Etat mois précédent | C39: ='Fevrier 2026'!D43 -> #REF!
A40: Recettes fixes | C40: =SUM(C2:C6) -> 7200.64 | E40: Somme dépenses prévues | F40: =SUM(F2:F38) -> 4476.28 | G40: Somme dépenses réelles | H40: =SUM(H2:H38) -> 4476.28 | I40: Delta moins les exceptions
A41: Recettes additionnelles du mois | C41: =SUM(C8:C35) -> 1382.4 | E41: Reste previsionnel | F41: =C42-F40 -> #REF! | G41: Delta du mois | H41: =C39+C40+C41-H40-F42 -> #REF!
A42: Total Recettes | C42: =SUM(C39:C41) -> #REF! | E42: Somme dépenses non prévues | F42: =SUM(J44:J246) -> 3943.44
A43: Reste prévu | B43: =$C$42-$F$40-$F$42 -> #REF! | C43: Reste réel | D43: =$C$42-$H$40-$F$42 -> #REF!
A44: =IF(AND(NOT(ISBLANK(#REF!)),ISBLANK(G44)),"Reste prévu","") | B44: =IF(AND(NOT(ISBLANK(#REF!)),ISBLANK($G44)),$C$42-$F$40-$F$42,"") | C44: =IF(AND(NOT(ISBLANK(#REF!)),ISBLANK($G44)),"Reste réel","") | D44: =IF(AND(NOT(ISBLANK(#REF!)),ISBLANK($G44)),$C$42-$H$40-$F$42,"") | G44: Soirée Hand | H44: 11.5 | I44: x | J44: =IF(I44="x",H44,0) -> 11.5 | K44: Loisirs
A45: =IF(AND(NOT(ISBLANK(G44)),ISBLANK(G45)),"Reste prévu","") | B45: =IF(AND(NOT(ISBLANK($G44)),ISBLANK($G45)),$C$42-$F$40-$F$42,"") | C45: =IF(AND(NOT(ISBLANK($G44)),ISBLANK($G45)),"Reste réel","") | D45: =IF(AND(NOT(ISBLANK($G44)),ISBLANK($G45)),$C$42-$H$40-$F$42,"") | G45: Boucherie | H45: 21.02 | I45: x | J45: =IF(I45="x",H45,0) -> 21.02 | K45: Courses
A46: =IF(AND(NOT(ISBLANK(G45)),ISBLANK(G46)),"Reste prévu","") | B46: =IF(AND(NOT(ISBLANK($G45)),ISBLANK($G46)),$C$42-$F$40-$F$42,"") | C46: =IF(AND(NOT(ISBLANK($G45)),ISBLANK($G46)),"Reste réel","") | D46: =IF(AND(NOT(ISBLANK($G45)),ISBLANK($G46)),$C$42-$H$40-$F$42,"") | G46: Leclerc | H46: 205.56 | I46: x | J46: =IF(I46="x",H46,0) -> 205.56 | K46: Courses
A47: =IF(AND(NOT(ISBLANK(G46)),ISBLANK(G47)),"Reste prévu","") | B47: =IF(AND(NOT(ISBLANK($G46)),ISBLANK($G47)),$C$42-$F$40-$F$42,"") | C47: =IF(AND(NOT(ISBLANK($G46)),ISBLANK($G47)),"Reste réel","") | D47: =IF(AND(NOT(ISBLANK($G46)),ISBLANK($G47)),$C$42-$H$40-$F$42,"") | G47: Mr Bricolage | H47: 209.7 | I47: x | J47: =IF(I47="x",H47,0) -> 209.7 | K47: Bricolage/Travaux
A48: =IF(AND(NOT(ISBLANK(G47)),ISBLANK(G48)),"Reste prévu","") | B48: =IF(AND(NOT(ISBLANK($G47)),ISBLANK($G48)),$C$42-$F$40-$F$42,"") | C48: =IF(AND(NOT(ISBLANK($G47)),ISBLANK($G48)),"Reste réel","") | D48: =IF(AND(NOT(ISBLANK($G47)),ISBLANK($G48)),$C$42-$H$40-$F$42,"") | G48: Pharmacie | H48: 28.65 | I48: x | J48: =IF(I48="x",H48,0) -> 28.65 | K48: Medical
A49: =IF(AND(NOT(ISBLANK(G48)),ISBLANK(G49)),"Reste prévu","") | B49: =IF(AND(NOT(ISBLANK($G48)),ISBLANK($G49)),$C$42-$F$40-$F$42,"") | C49: =IF(AND(NOT(ISBLANK($G48)),ISBLANK($G49)),"Reste réel","") | D49: =IF(AND(NOT(ISBLANK($G48)),ISBLANK($G49)),$C$42-$H$40-$F$42,"") | G49: Train Arthur | H49: 9 | I49: x | J49: =IF(I49="x",H49,0) -> 9 | K49: Voiture/Déplacement
A50: =IF(AND(NOT(ISBLANK(G49)),ISBLANK(G50)),"Reste prévu","") | B50: =IF(AND(NOT(ISBLANK($G49)),ISBLANK($G50)),$C$42-$F$40-$F$42,"") | C50: =IF(AND(NOT(ISBLANK($G49)),ISBLANK($G50)),"Reste réel","") | D50: =IF(AND(NOT(ISBLANK($G49)),ISBLANK($G50)),$C$42-$H$40-$F$42,"") | G50: ChargeMap | H50: 115.4 | I50: x | J50: =IF(I50="x",H50,0) -> 115.4 | K50: Voiture/Déplacement
A51: =IF(AND(NOT(ISBLANK(G50)),ISBLANK(G51)),"Reste prévu","") | B51: =IF(AND(NOT(ISBLANK($G50)),ISBLANK($G51)),$C$42-$F$40-$F$42,"") | C51: =IF(AND(NOT(ISBLANK($G50)),ISBLANK($G51)),"Reste réel","") | D51: =IF(AND(NOT(ISBLANK($G50)),ISBLANK($G51)),$C$42-$H$40-$F$42,"") | G51: Cireuse qui ne marche pas Amazon | H51: 105.9 | I51: x | J51: =IF(I51="x",H51,0) -> 105.9 | K51: Bricolage/Travaux
A52: =IF(AND(NOT(ISBLANK(G51)),ISBLANK(G52)),"Reste prévu","") | B52: =IF(AND(NOT(ISBLANK($G51)),ISBLANK($G52)),$C$42-$F$40-$F$42,"") | C52: =IF(AND(NOT(ISBLANK($G51)),ISBLANK($G52)),"Reste réel","") | D52: =IF(AND(NOT(ISBLANK($G51)),ISBLANK($G52)),$C$42-$H$40-$F$42,"") | G52: Leclerc | H52: 5.18 | I52: x | J52: =IF(I52="x",H52,0) -> 5.18 | K52: Courses
A53: =IF(AND(NOT(ISBLANK(G52)),ISBLANK(G53)),"Reste prévu","") | B53: =IF(AND(NOT(ISBLANK($G52)),ISBLANK($G53)),$C$42-$F$40-$F$42,"") | C53: =IF(AND(NOT(ISBLANK($G52)),ISBLANK($G53)),"Reste réel","") | D53: =IF(AND(NOT(ISBLANK($G52)),ISBLANK($G53)),$C$42-$H$40-$F$42,"") | G53: Train Arthur | H53: 9 | I53: x | J53: =IF(I53="x",H53,0) -> 9 | K53: Voiture/Déplacement
A54: =IF(AND(NOT(ISBLANK(G53)),ISBLANK(G54)),"Reste prévu","") | B54: =IF(AND(NOT(ISBLANK($G53)),ISBLANK($G54)),$C$42-$F$40-$F$42,"") | C54: =IF(AND(NOT(ISBLANK($G53)),ISBLANK($G54)),"Reste réel","") | D54: =IF(AND(NOT(ISBLANK($G53)),ISBLANK($G54)),$C$42-$H$40-$F$42,"") | G54: Lavage Voiture | H54: 14 | I54: x | J54: =IF(I54="x",H54,0) -> 14 | K54: Voiture/Déplacement
A55: =IF(AND(NOT(ISBLANK(G54)),ISBLANK(G55)),"Reste prévu","") | B55: =IF(AND(NOT(ISBLANK($G54)),ISBLANK($G55)),$C$42-$F$40-$F$42,"") | C55: =IF(AND(NOT(ISBLANK($G54)),ISBLANK($G55)),"Reste réel","") | D55: =IF(AND(NOT(ISBLANK($G54)),ISBLANK($G55)),$C$42-$H$40-$F$42,"") | G55: Pharmacie | H55: 3.46 | I55: x | J55: =IF(I55="x",H55,0) -> 3.46 | K55: Medical
A56: =IF(AND(NOT(ISBLANK(G55)),ISBLANK(G56)),"Reste prévu","") | B56: =IF(AND(NOT(ISBLANK($G55)),ISBLANK($G56)),$C$42-$F$40-$F$42,"") | C56: =IF(AND(NOT(ISBLANK($G55)),ISBLANK($G56)),"Reste réel","") | D56: =IF(AND(NOT(ISBLANK($G55)),ISBLANK($G56)),$C$42-$H$40-$F$42,"") | G56: Pharmacie | H56: 67.28 | I56: x | J56: =IF(I56="x",H56,0) -> 67.28 | K56: Medical
... A136: =IF(AND(NOT(ISBLANK(G135)),ISBLANK(G136)),"Reste prévu","") | B136: =IF(AND(NOT(ISBLANK($G135)),ISBLANK($G136)),$C$42-$F$40-$F$42,"") | C136: =IF(AND(NOT(ISBLANK($G135)),ISBLANK($G136)),"Reste réel","") | D136: =IF(AND(NOT(ISBLANK($G135)),ISBLANK($G136)),$C$42-$H$40-$F$42,"") | G136: Amende stationnement (Igienair) | H136: 25 | I136: x | J136: =IF(I136="x",H136,0) -> 25 | K136: Voiture/Déplacement
A137: =IF(AND(NOT(ISBLANK(G136)),ISBLANK(G137)),"Reste prévu","") -> Reste prévu | B137: =IF(AND(NOT(ISBLANK($G136)),ISBLANK($G137)),$C$42-$F$40-$F$42,"") -> #REF! | C137: =IF(AND(NOT(ISBLANK($G136)),ISBLANK($G137)),"Reste réel","") -> Reste réel | D137: =IF(AND(NOT(ISBLANK($G136)),ISBLANK($G137)),$C$42-$H$40-$F$42,"") -> #REF! | J137: =IF(I137="x",H137,0) -> 0 | K137: Courses
A138: =IF(AND(NOT(ISBLANK(G137)),ISBLANK(G138)),"Reste prévu","") | B138: =IF(AND(NOT(ISBLANK($G137)),ISBLANK($G138)),$C$42-$F$40-$F$42,"") | C138: =IF(AND(NOT(ISBLANK($G137)),ISBLANK($G138)),"Reste réel","") | D138: =IF(AND(NOT(ISBLANK($G137)),ISBLANK($G138)),$C$42-$H$40-$F$42,"") | J138: =IF(I138="x",H138,0) -> 0 | K138: Courses
A139: =IF(AND(NOT(ISBLANK(G138)),ISBLANK(G139)),"Reste prévu","") | B139: =IF(AND(NOT(ISBLANK($G138)),ISBLANK($G139)),$C$42-$F$40-$F$42,"") | C139: =IF(AND(NOT(ISBLANK($G138)),ISBLANK($G139)),"Reste réel","") | D139: =IF(AND(NOT(ISBLANK($G138)),ISBLANK($G139)),$C$42-$H$40-$F$42,"") | J139: =IF(I139="x",H139,0) -> 0 | K139: Divers
A140: =IF(AND(NOT(ISBLANK(G139)),ISBLANK(G140)),"Reste prévu","") | B140: =IF(AND(NOT(ISBLANK($G139)),ISBLANK($G140)),$C$42-$F$40-$F$42,"") | C140: =IF(AND(NOT(ISBLANK($G139)),ISBLANK($G140)),"Reste réel","") | D140: =IF(AND(NOT(ISBLANK($G139)),ISBLANK($G140)),$C$42-$H$40-$F$42,"") | J140: =IF(I140="x",H140,0) -> 0 | K140: Courses
A141: =IF(AND(NOT(ISBLANK(G140)),ISBLANK(G141)),"Reste prévu","") | B141: =IF(AND(NOT(ISBLANK($G140)),ISBLANK($G141)),$C$42-$F$40-$F$42,"") | C141: =IF(AND(NOT(ISBLANK($G140)),ISBLANK($G141)),"Reste réel","") | D141: =IF(AND(NOT(ISBLANK($G140)),ISBLANK($G141)),$C$42-$H$40-$F$42,"") | J141: =IF(I141="x",H141,0) -> 0 | K141: Cadeau
A142: =IF(AND(NOT(ISBLANK(G141)),ISBLANK(G142)),"Reste prévu","") | B142: =IF(AND(NOT(ISBLANK($G141)),ISBLANK($G142)),$C$42-$F$40-$F$42,"") | C142: =IF(AND(NOT(ISBLANK($G141)),ISBLANK($G142)),"Reste réel","") | D142: =IF(AND(NOT(ISBLANK($G141)),ISBLANK($G142)),$C$42-$H$40-$F$42,"") | J142: =IF(I142="x",H142,0) -> 0 | K142: Cadeau
A143: =IF(AND(NOT(ISBLANK(G142)),ISBLANK(G143)),"Reste prévu","") | B143: =IF(AND(NOT(ISBLANK($G142)),ISBLANK($G143)),$C$42-$F$40-$F$42,"") | C143: =IF(AND(NOT(ISBLANK($G142)),ISBLANK($G143)),"Reste réel","") | D143: =IF(AND(NOT(ISBLANK($G142)),ISBLANK($G143)),$C$42-$H$40-$F$42,"") | J143: =IF(I143="x",H143,0) -> 0 | K143: Cadeau
A144: =IF(AND(NOT(ISBLANK(G143)),ISBLANK(G144)),"Reste prévu","") | B144: =IF(AND(NOT(ISBLANK($G143)),ISBLANK($G144)),$C$42-$F$40-$F$42,"") | C144: =IF(AND(NOT(ISBLANK($G143)),ISBLANK($G144)),"Reste réel","") | D144: =IF(AND(NOT(ISBLANK($G143)),ISBLANK($G144)),$C$42-$H$40-$F$42,"") | J144: =IF(I144="x",H144,0) -> 0 | K144: Cadeau
A145: =IF(AND(NOT(ISBLANK(G144)),ISBLANK(G145)),"Reste prévu","") | B145: =IF(AND(NOT(ISBLANK($G144)),ISBLANK($G145)),$C$42-$F$40-$F$42,"") | C145: =IF(AND(NOT(ISBLANK($G144)),ISBLANK($G145)),"Reste réel","") | D145: =IF(AND(NOT(ISBLANK($G144)),ISBLANK($G145)),$C$42-$H$40-$F$42,"") | J145: =IF(I145="x",H145,0) -> 0 | K145: Courses
A146: =IF(AND(NOT(ISBLANK(G145)),ISBLANK(G146)),"Reste prévu","") | B146: =IF(AND(NOT(ISBLANK($G145)),ISBLANK($G146)),$C$42-$F$40-$F$42,"") | C146: =IF(AND(NOT(ISBLANK($G145)),ISBLANK($G146)),"Reste réel","") | D146: =IF(AND(NOT(ISBLANK($G145)),ISBLANK($G146)),$C$42-$H$40-$F$42,"") | J146: =IF(I146="x",H146,0) -> 0 | K146: Cadeau
A147: =IF(AND(NOT(ISBLANK(G146)),ISBLANK(G147)),"Reste prévu","") | B147: =IF(AND(NOT(ISBLANK($G146)),ISBLANK($G147)),$C$42-$F$40-$F$42,"") | C147: =IF(AND(NOT(ISBLANK($G146)),ISBLANK($G147)),"Reste réel","") | D147: =IF(AND(NOT(ISBLANK($G146)),ISBLANK($G147)),$C$42-$H$40-$F$42,"") | J147: =IF(I147="x",H147,0) -> 0
A148: =IF(AND(NOT(ISBLANK(G147)),ISBLANK(G148)),"Reste prévu","") | B148: =IF(AND(NOT(ISBLANK($G147)),ISBLANK($G148)),$C$42-$F$40-$F$42,"") | C148: =IF(AND(NOT(ISBLANK($G147)),ISBLANK($G148)),"Reste réel","") | D148: =IF(AND(NOT(ISBLANK($G147)),ISBLANK($G148)),$C$42-$H$40-$F$42,"") | J148: =IF(I148="x",H148,0) -> 0
A149: =IF(AND(NOT(ISBLANK(G148)),ISBLANK(G149)),"Reste prévu","") | B149: =IF(AND(NOT(ISBLANK($G148)),ISBLANK($G149)),$C$42-$F$40-$F$42,"") | C149: =IF(AND(NOT(ISBLANK($G148)),ISBLANK($G149)),"Reste réel","") | D149: =IF(AND(NOT(ISBLANK($G148)),ISBLANK($G149)),$C$42-$H$40-$F$42,"") | J149: =IF(I149="x",H149,0) -> 0
A150: =IF(AND(NOT(ISBLANK(G149)),ISBLANK(G150)),"Reste prévu","") | B150: =IF(AND(NOT(ISBLANK($G149)),ISBLANK($G150)),$C$42-$F$40-$F$42,"") | C150: =IF(AND(NOT(ISBLANK($G149)),ISBLANK($G150)),"Reste réel","") | D150: =IF(AND(NOT(ISBLANK($G149)),ISBLANK($G150)),$C$42-$H$40-$F$42,"") | J150: =IF(I150="x",H150,0) -> 0
A151: =IF(AND(NOT(ISBLANK(G150)),ISBLANK(G151)),"Reste prévu","") | B151: =IF(AND(NOT(ISBLANK($G150)),ISBLANK($G151)),$C$42-$F$40-$F$42,"") | C151: =IF(AND(NOT(ISBLANK($G150)),ISBLANK($G151)),"Reste réel","") | D151: =IF(AND(NOT(ISBLANK($G150)),ISBLANK($G151)),$C$42-$H$40-$F$42,"") | J151: =IF(I151="x",H151,0) -> 0
A152: =IF(AND(NOT(ISBLANK(G151)),ISBLANK(G152)),"Reste prévu","") | B152: =IF(AND(NOT(ISBLANK($G151)),ISBLANK($G152)),$C$42-$F$40-$F$42,"") | C152: =IF(AND(NOT(ISBLANK($G151)),ISBLANK($G152)),"Reste réel","") | D152: =IF(AND(NOT(ISBLANK($G151)),ISBLANK($G152)),$C$42-$H$40-$F$42,"") | J152: =IF(I152="x",H152,0) -> 0
A153: =IF(AND(NOT(ISBLANK(G152)),ISBLANK(G153)),"Reste prévu","") | B153: =IF(AND(NOT(ISBLANK($G152)),ISBLANK($G153)),$C$42-$F$40-$F$42,"") | C153: =IF(AND(NOT(ISBLANK($G152)),ISBLANK($G153)),"Reste réel","") | D153: =IF(AND(NOT(ISBLANK($G152)),ISBLANK($G153)),$C$42-$H$40-$F$42,"") | J153: =IF(I153="x",H153,0) -> 0
A154: =IF(AND(NOT(ISBLANK(G153)),ISBLANK(G154)),"Reste prévu","") | B154: =IF(AND(NOT(ISBLANK($G153)),ISBLANK($G154)),$C$42-$F$40-$F$42,"") | C154: =IF(AND(NOT(ISBLANK($G153)),ISBLANK($G154)),"Reste réel","") | D154: =IF(AND(NOT(ISBLANK($G153)),ISBLANK($G154)),$C$42-$H$40-$F$42,"") | J154: =IF(I154="x",H154,0) -> 0
A155: =IF(AND(NOT(ISBLANK(G154)),ISBLANK(G155)),"Reste prévu","") | B155: =IF(AND(NOT(ISBLANK($G154)),ISBLANK($G155)),$C$42-$F$40-$F$42,"") | C155: =IF(AND(NOT(ISBLANK($G154)),ISBLANK($G155)),"Reste réel","") | D155: =IF(AND(NOT(ISBLANK($G154)),ISBLANK($G155)),$C$42-$H$40-$F$42,"") | J155: =IF(I155="x",H155,0) -> 0
A156: =IF(AND(NOT(ISBLANK(G155)),ISBLANK(G156)),"Reste prévu","") | B156: =IF(AND(NOT(ISBLANK($G155)),ISBLANK($G156)),$C$42-$F$40-$F$42,"") | C156: =IF(AND(NOT(ISBLANK($G155)),ISBLANK($G156)),"Reste réel","") | D156: =IF(AND(NOT(ISBLANK($G155)),ISBLANK($G156)),$C$42-$H$40-$F$42,"") | J156: =IF(I156="x",H156,0) -> 0
A157: =IF(AND(NOT(ISBLANK(G156)),ISBLANK(G157)),"Reste prévu","") | B157: =IF(AND(NOT(ISBLANK($G156)),ISBLANK($G157)),$C$42-$F$40-$F$42,"") | C157: =IF(AND(NOT(ISBLANK($G156)),ISBLANK($G157)),"Reste réel","") | D157: =IF(AND(NOT(ISBLANK($G156)),ISBLANK($G157)),$C$42-$H$40-$F$42,"") | J157: =IF(I157="x",H157,0) -> 0
A158: =IF(AND(NOT(ISBLANK(G157)),ISBLANK(G158)),"Reste prévu","") | B158: =IF(AND(NOT(ISBLANK($G157)),ISBLANK($G158)),$C$42-$F$40-$F$42,"") | C158: =IF(AND(NOT(ISBLANK($G157)),ISBLANK($G158)),"Reste réel","") | D158: =IF(AND(NOT(ISBLANK($G157)),ISBLANK($G158)),$C$42-$H$40-$F$42,"") | J158: =IF(I158="x",H158,0) -> 0
... A213: =IF(AND(NOT(ISBLANK(G212)),ISBLANK(G213)),"Reste prévu","") | B213: =IF(AND(NOT(ISBLANK($G212)),ISBLANK($G213)),$C$42-$F$40-$F$42,"") | C213: =IF(AND(NOT(ISBLANK($G212)),ISBLANK($G213)),"Reste réel","") | D213: =IF(AND(NOT(ISBLANK($G212)),ISBLANK($G213)),$C$42-$H$40-$F$42,"") | J213: =IF(I213="x",H213,0) -> 0
A214: =IF(AND(NOT(ISBLANK(G213)),ISBLANK(G214)),"Reste prévu","") | B214: =IF(AND(NOT(ISBLANK($G213)),ISBLANK($G214)),$C$42-$F$40-$F$42,"") | C214: =IF(AND(NOT(ISBLANK($G213)),ISBLANK($G214)),"Reste réel","") | D214: =IF(AND(NOT(ISBLANK($G213)),ISBLANK($G214)),$C$42-$H$40-$F$42,"")
A215: =IF(AND(NOT(ISBLANK(G214)),ISBLANK(G215)),"Reste prévu","") | B215: =IF(AND(NOT(ISBLANK($G214)),ISBLANK($G215)),$C$42-$F$40-$F$42,"") | C215: =IF(AND(NOT(ISBLANK($G214)),ISBLANK($G215)),"Reste réel","") | D215: =IF(AND(NOT(ISBLANK($G214)),ISBLANK($G215)),$C$42-$H$40-$F$42,"")
A216: =IF(AND(NOT(ISBLANK(G215)),ISBLANK(G216)),"Reste prévu","") | B216: =IF(AND(NOT(ISBLANK($G215)),ISBLANK($G216)),$C$42-$F$40-$F$42,"") | C216: =IF(AND(NOT(ISBLANK($G215)),ISBLANK($G216)),"Reste réel","") | D216: =IF(AND(NOT(ISBLANK($G215)),ISBLANK($G216)),$C$42-$H$40-$F$42,"")
A217: =IF(AND(NOT(ISBLANK(G216)),ISBLANK(G217)),"Reste prévu","") | B217: =IF(AND(NOT(ISBLANK($G216)),ISBLANK($G217)),$C$42-$F$40-$F$42,"") | C217: =IF(AND(NOT(ISBLANK($G216)),ISBLANK($G217)),"Reste réel","") | D217: =IF(AND(NOT(ISBLANK($G216)),ISBLANK($G217)),$C$42-$H$40-$F$42,"")
A218: =IF(AND(NOT(ISBLANK(G217)),ISBLANK(G218)),"Reste prévu","") | B218: =IF(AND(NOT(ISBLANK($G217)),ISBLANK($G218)),$C$42-$F$40-$F$42,"") | C218: =IF(AND(NOT(ISBLANK($G217)),ISBLANK($G218)),"Reste réel","") | D218: =IF(AND(NOT(ISBLANK($G217)),ISBLANK($G218)),$C$42-$H$40-$F$42,"")
A219: =IF(AND(NOT(ISBLANK(G218)),ISBLANK(G219)),"Reste prévu","") | B219: =IF(AND(NOT(ISBLANK($G218)),ISBLANK($G219)),$C$42-$F$40-$F$42,"") | C219: =IF(AND(NOT(ISBLANK($G218)),ISBLANK($G219)),"Reste réel","") | D219: =IF(AND(NOT(ISBLANK($G218)),ISBLANK($G219)),$C$42-$H$40-$F$42,"")
A220: =IF(AND(NOT(ISBLANK(G219)),ISBLANK(G220)),"Reste prévu","") | B220: =IF(AND(NOT(ISBLANK($G219)),ISBLANK($G220)),$C$42-$F$40-$F$42,"") | C220: =IF(AND(NOT(ISBLANK($G219)),ISBLANK($G220)),"Reste réel","") | D220: =IF(AND(NOT(ISBLANK($G219)),ISBLANK($G220)),$C$42-$H$40-$F$42,"")
A221: =IF(AND(NOT(ISBLANK(G220)),ISBLANK(G221)),"Reste prévu","") | B221: =IF(AND(NOT(ISBLANK($G220)),ISBLANK($G221)),$C$42-$F$40-$F$42,"") | C221: =IF(AND(NOT(ISBLANK($G220)),ISBLANK($G221)),"Reste réel","") | D221: =IF(AND(NOT(ISBLANK($G220)),ISBLANK($G221)),$C$42-$H$40-$F$42,"")
A222: =IF(AND(NOT(ISBLANK(G221)),ISBLANK(G222)),"Reste prévu","") | B222: =IF(AND(NOT(ISBLANK($G221)),ISBLANK($G222)),$C$42-$F$40-$F$42,"") | C222: =IF(AND(NOT(ISBLANK($G221)),ISBLANK($G222)),"Reste réel","") | D222: =IF(AND(NOT(ISBLANK($G221)),ISBLANK($G222)),$C$42-$H$40-$F$42,"")
A223: =IF(AND(NOT(ISBLANK(G222)),ISBLANK(G223)),"Reste prévu","") | B223: =IF(AND(NOT(ISBLANK($G222)),ISBLANK($G223)),$C$42-$F$40-$F$42,"") | C223: =IF(AND(NOT(ISBLANK($G222)),ISBLANK($G223)),"Reste réel","") | D223: =IF(AND(NOT(ISBLANK($G222)),ISBLANK($G223)),$C$42-$H$40-$F$42,"")
A224: =IF(AND(NOT(ISBLANK(G223)),ISBLANK(G224)),"Reste prévu","") | B224: =IF(AND(NOT(ISBLANK($G223)),ISBLANK($G224)),$C$42-$F$40-$F$42,"") | C224: =IF(AND(NOT(ISBLANK($G223)),ISBLANK($G224)),"Reste réel","") | D224: =IF(AND(NOT(ISBLANK($G223)),ISBLANK($G224)),$C$42-$H$40-$F$42,"")
A225: =IF(AND(NOT(ISBLANK(G224)),ISBLANK(G225)),"Reste prévu","") | B225: =IF(AND(NOT(ISBLANK($G224)),ISBLANK($G225)),$C$42-$F$40-$F$42,"") | C225: =IF(AND(NOT(ISBLANK($G224)),ISBLANK($G225)),"Reste réel","") | D225: =IF(AND(NOT(ISBLANK($G224)),ISBLANK($G225)),$C$42-$H$40-$F$42,"")
... A236: =IF(AND(NOT(ISBLANK(G235)),ISBLANK(G236)),"Reste prévu","") | B236: =IF(AND(NOT(ISBLANK($G235)),ISBLANK($G236)),$C$42-$F$40-$F$42,"") | C236: =IF(AND(NOT(ISBLANK($G235)),ISBLANK($G236)),"Reste réel","") | D236: =IF(AND(NOT(ISBLANK($G235)),ISBLANK($G236)),$C$42-$H$40-$F$42,"")

Sheet Fevrier 2026
B1: Recettes | E1: Dépenses | K1: Cadeau
B3: Salaire Pierre | C3: 5245.11 | E3: Loyer Elouen | F3: 669.7 | G3: x | H3: =IF(G3="x",F3,0) -> 669.7 | K3: Logement
B4: Salaire Sterenn | C4: 1828.73 | E4: Argent de poche Elouen | H4: =IF(G4="x",F4,0) -> 0 | K4: Charges
B5: CAF | C5: 113.3 | E5: Engie Elouen | F5: 70 | G5: x | H5: =IF(G5="x",F5,0) -> 70 | K5: Charges
E6: Argent de poche Arthur | F6: 164.99 | G6: x | H6: =IF(G6="x",F6,0) -> 164.99 | K6: Charges
E7: Prêt 25 | F7: 995.15 | G7: x | H7: =IF(G7="x",F7,0) -> 995.15 | K7: Logement
B8: CPAM | C8: 19 | E8: Prêt 15 | F8: 883.42 | G8: x | H8: =IF(G8="x",F8,0) -> 883.42 | K8: Logement
B9: Note de Frais | C9: 72.32 | E9: Assurances prêt | F9: 11.46 | G9: x | H9: =IF(G9="x",F9,0) -> 11.46 | K9: Logement
B10: Titouan | C10: 16 | E10: Assurances prêt | F10: 32.57 | G10: x | H10: =IF(G10="x",F10,0) -> 32.57 | K10: Logement
B11: Mateo | C11: 16 | E11: Assurances prêt | F11: 79.98 | G11: x | H11: =IF(G11="x",F11,0) -> 79.98 | K11: Logement
B12: Aurel | C12: 16 | E12: Assurances prêt | F12: 28.49 | G12: x | H12: =IF(G12="x",F12,0) -> 28.49 | K12: Logement
B13: Sandrine | C13: 16 | E13: Disney | F13: 6.99 | G13: x | H13: =IF(G13="x",F13,0) -> 6.99 | K13: Internet/Téléphone
B14: Fred | C14: 15.67 | E14: EDF Arthur | F14: 43.96 | G14: x | H14: =IF(G14="x",F14,0) -> 43.96 | K14: Charges
B15: Edouard | C15: 15.67 | E15: EkWateur | F15: 208 | G15: x | H15: =IF(G15="x",F15,0) -> 208 | K15: Charges
B16: Sebastien | C16: 16 | E16: Sosh Maison | F16: 24.99 | G16: x | H16: =IF(G16="x",F16,0) -> 24.99 | K16: Internet/Téléphone
B17: Mutuelle | C17: 9 | E17: Sosh Arthur | F17: 14.99 | G17: x | H17: =IF(G17="x",F17,0) -> 14.99 | K17: Internet/Téléphone
B18: Telephone Ael | C18: 85 | E18: Sosh Ael | F18: 14.99 | H18: =IF(G18="x",F18,0) -> 0 | K18: Internet/Téléphone
E19: Sosh Elouen | F19: 14.99 | H19: =IF(G19="x",F19,0) -> 0 | K19: Internet/Téléphone
E20: Sosh Sterenn | F20: 10.99 | G20: x | H20: =IF(G20="x",F20,0) -> 10.99 | K20: Internet/Téléphone
E21: Mutuelle | F21: 104.98 | G21: x | H21: =IF(G21="x",F21,0) -> 104.98 | K21: Assurances/Mutuelle
E23: Suravenir Habitation | F23: 60.09 | G23: x | H23: =IF(G23="x",F23,0) -> 60.09 | K23: Assurances/Mutuelle
E24: VW LDD | F24: 331.65 | G24: x | H24: =IF(G24="x",F24,0) -> 331.65 | K24: Voiture/Déplacement
E25: Suravenir Voiture | F25: 133.7 | G25: x | H25: =IF(G25="x",F25,0) -> 133.7 | K25: Assurances/Mutuelle
E26: Suravenir Garanties Vie | F26: 29.97 | G26: x | H26: =IF(G26="x",F26,0) -> 29.97 | K26: Assurances/Mutuelle
E27: Joséphine | F27: 20 | G27: x | H27: =IF(G27="x",F27,0) -> 20 | K27: Divers
E28: Canal Plus | F28: 21.99 | G28: x | H28: =IF(G28="x",F28,0) -> 21.99 | K28: Internet/Téléphone
H29: =IF(G29="x",F29,0) -> 0 | K29: Voiture/Déplacement
E30: Keolis Elouen | F30: 21.4 | G30: x | H30: =IF(G30="x",F30,0) -> 21.4 | K30: Voiture/Déplacement
E31: Apple | F31: 0.99 | G31: x | H31: =IF(G31="x",F31,0) -> 0.99 | K31: Internet/Téléphone
E32: Apple | F32: 16.99 | G32: x | H32: =IF(G32="x",F32,0) -> 16.99 | K32: Internet/Téléphone
E33: St Charles | F33: 172.1 | G33: x | H33: =IF(G33="x",F33,0) -> 172.1 | K33: Scolarité
E34: Ménage | F34: 68 | H34: =IF(G34="x",F34,0) -> 0 | K34: Logement
E35: Urssaaf | F35: 104.66 | G35: x | H35: =IF(G35="x",F35,0) -> 104.66 | K35: Logement
E36: Cotisation Eurocompte | F36: 19.03 | G36: x | H36: =IF(G36="x",F36,0) -> 19.03
E37: Indivision | F37: 33.89 | G37: x | H37: =IF(G37="x",F37,0) -> 33.89
A39: Etat mois précédent | C39: ='Janvier 2026'!D43 -> #REF!
A40: Recettes fixes | C40: =SUM(C2:C6) -> 7187.14 | E40: Somme dépenses prévues | F40: =SUM(F2:F38) -> 4415.1 | G40: Somme dépenses réelles | H40: =SUM(H2:H38) -> 4317.12 | I40: Delta moins les exceptions
A41: Recettes additionnelles du mois | C41: =SUM(C8:C35) -> 296.66 | E41: Reste previsionnel | F41: =C42-F40 -> #REF! | G41: Delta du mois | H41: =C39+C40+C41-H40-F42 -> #REF!
A42: Total Recettes | C42: =SUM(C39:C41) -> #REF! | E42: Somme dépenses non prévues | F42: =SUM(J44:J246) -> 3724.67
A43: Reste prévu | B43: =$C$42-$F$40-$F$42 -> #REF! | C43: Reste réel | D43: =$C$42-$H$40-$F$42 -> #REF!
A44: =IF(AND(NOT(ISBLANK(#REF!)),ISBLANK(G44)),"Reste prévu","") | B44: =IF(AND(NOT(ISBLANK(#REF!)),ISBLANK($G44)),$C$42-$F$40-$F$42,"") | C44: =IF(AND(NOT(ISBLANK(#REF!)),ISBLANK($G44)),"Reste réel","") | D44: =IF(AND(NOT(ISBLANK(#REF!)),ISBLANK($G44)),$C$42-$H$40-$F$42,"") | G44: Fournil du port | H44: 7.55 | I44: x | J44: =IF(I44="x",H44,0) -> 7.55 | K44: Courses
A45: =IF(AND(NOT(ISBLANK(G44)),ISBLANK(G45)),"Reste prévu","") | B45: =IF(AND(NOT(ISBLANK($G44)),ISBLANK($G45)),$C$42-$F$40-$F$42,"") | C45: =IF(AND(NOT(ISBLANK($G44)),ISBLANK($G45)),"Reste réel","") | D45: =IF(AND(NOT(ISBLANK($G44)),ISBLANK($G45)),$C$42-$H$40-$F$42,"") | G45: Tartapain | H45: 18.1 | I45: x | J45: =IF(I45="x",H45,0) -> 18.1 | K45: Courses
A46: =IF(AND(NOT(ISBLANK(G45)),ISBLANK(G46)),"Reste prévu","") | B46: =IF(AND(NOT(ISBLANK($G45)),ISBLANK($G46)),$C$42-$F$40-$F$42,"") | C46: =IF(AND(NOT(ISBLANK($G45)),ISBLANK($G46)),"Reste réel","") | D46: =IF(AND(NOT(ISBLANK($G45)),ISBLANK($G46)),$C$42-$H$40-$F$42,"") | G46: Pharmacie | H46: 28.08 | I46: x | J46: =IF(I46="x",H46,0) -> 28.08 | K46: Medical
A47: =IF(AND(NOT(ISBLANK(G46)),ISBLANK(G47)),"Reste prévu","") | B47: =IF(AND(NOT(ISBLANK($G46)),ISBLANK($G47)),$C$42-$F$40-$F$42,"") | C47: =IF(AND(NOT(ISBLANK($G46)),ISBLANK($G47)),"Reste réel","") | D47: =IF(AND(NOT(ISBLANK($G46)),ISBLANK($G47)),$C$42-$H$40-$F$42,"") | G47: Boucherie | H47: 40.02 | I47: x | J47: =IF(I47="x",H47,0) -> 40.02 | K47: Courses
A48: =IF(AND(NOT(ISBLANK(G47)),ISBLANK(G48)),"Reste prévu","") | B48: =IF(AND(NOT(ISBLANK($G47)),ISBLANK($G48)),$C$42-$F$40-$F$42,"") | C48: =IF(AND(NOT(ISBLANK($G47)),ISBLANK($G48)),"Reste réel","") | D48: =IF(AND(NOT(ISBLANK($G47)),ISBLANK($G48)),$C$42-$H$40-$F$42,"") | G48: La Voile | H48: 93.5 | I48: x | J48: =IF(I48="x",H48,0) -> 93.5 | K48: Loisirs
A49: =IF(AND(NOT(ISBLANK(G48)),ISBLANK(G49)),"Reste prévu","") | B49: =IF(AND(NOT(ISBLANK($G48)),ISBLANK($G49)),$C$42-$F$40-$F$42,"") | C49: =IF(AND(NOT(ISBLANK($G48)),ISBLANK($G49)),"Reste réel","") | D49: =IF(AND(NOT(ISBLANK($G48)),ISBLANK($G49)),$C$42-$H$40-$F$42,"") | G49: Train Arthur | H49: 9 | I49: x | J49: =IF(I49="x",H49,0) -> 9 | K49: Voiture/Déplacement
A50: =IF(AND(NOT(ISBLANK(G49)),ISBLANK(G50)),"Reste prévu","") | B50: =IF(AND(NOT(ISBLANK($G49)),ISBLANK($G50)),$C$42-$F$40-$F$42,"") | C50: =IF(AND(NOT(ISBLANK($G49)),ISBLANK($G50)),"Reste réel","") | D50: =IF(AND(NOT(ISBLANK($G49)),ISBLANK($G50)),$C$42-$H$40-$F$42,"") | G50: Train Arthur | H50: 9 | I50: x | J50: =IF(I50="x",H50,0) -> 9 | K50: Voiture/Déplacement
A51: =IF(AND(NOT(ISBLANK(G50)),ISBLANK(G51)),"Reste prévu","") | B51: =IF(AND(NOT(ISBLANK($G50)),ISBLANK($G51)),$C$42-$F$40-$F$42,"") | C51: =IF(AND(NOT(ISBLANK($G50)),ISBLANK($G51)),"Reste réel","") | D51: =IF(AND(NOT(ISBLANK($G50)),ISBLANK($G51)),$C$42-$H$40-$F$42,"") | G51: Leclerc | H51: 19.08 | I51: x | J51: =IF(I51="x",H51,0) -> 19.08 | K51: Courses
A52: =IF(AND(NOT(ISBLANK(G51)),ISBLANK(G52)),"Reste prévu","") | B52: =IF(AND(NOT(ISBLANK($G51)),ISBLANK($G52)),$C$42-$F$40-$F$42,"") | C52: =IF(AND(NOT(ISBLANK($G51)),ISBLANK($G52)),"Reste réel","") | D52: =IF(AND(NOT(ISBLANK($G51)),ISBLANK($G52)),$C$42-$H$40-$F$42,"") | G52: Leclerc | H52: 37.79 | I52: x | J52: =IF(I52="x",H52,0) -> 37.79 | K52: Courses
A53: =IF(AND(NOT(ISBLANK(G52)),ISBLANK(G53)),"Reste prévu","") | B53: =IF(AND(NOT(ISBLANK($G52)),ISBLANK($G53)),$C$42-$F$40-$F$42,"") | C53: =IF(AND(NOT(ISBLANK($G52)),ISBLANK($G53)),"Reste réel","") | D53: =IF(AND(NOT(ISBLANK($G52)),ISBLANK($G53)),$C$42-$H$40-$F$42,"") | G53: Menage | H53: 136 | I53: Comptabilisé Janvier | J53: =IF(I53="x",H53,0) -> 0 | K53: Charges
A54: =IF(AND(NOT(ISBLANK(G53)),ISBLANK(G54)),"Reste prévu","") | B54: =IF(AND(NOT(ISBLANK($G53)),ISBLANK($G54)),$C$42-$F$40-$F$42,"") | C54: =IF(AND(NOT(ISBLANK($G53)),ISBLANK($G54)),"Reste réel","") | D54: =IF(AND(NOT(ISBLANK($G53)),ISBLANK($G54)),$C$42-$H$40-$F$42,"") | G54: Tartapain | H54: 7.12 | I54: x | J54: =IF(I54="x",H54,0) -> 7.12 | K54: Courses
A55: =IF(AND(NOT(ISBLANK(G54)),ISBLANK(G55)),"Reste prévu","") | B55: =IF(AND(NOT(ISBLANK($G54)),ISBLANK($G55)),$C$42-$F$40-$F$42,"") | C55: =IF(AND(NOT(ISBLANK($G54)),ISBLANK($G55)),"Reste réel","") | D55: =IF(AND(NOT(ISBLANK($G54)),ISBLANK($G55)),$C$42-$H$40-$F$42,"") | G55: Dr Apel | H55: 30 | I55: x | J55: =IF(I55="x",H55,0) -> 30 | K55: Medical
A56: =IF(AND(NOT(ISBLANK(G55)),ISBLANK(G56)),"Reste prévu","") | B56: =IF(AND(NOT(ISBLANK($G55)),ISBLANK($G56)),$C$42-$F$40-$F$42,"") | C56: =IF(AND(NOT(ISBLANK($G55)),ISBLANK($G56)),"Reste réel","") | D56: =IF(AND(NOT(ISBLANK($G55)),ISBLANK($G56)),$C$42-$H$40-$F$42,"") | G56: Assurance Appart Arthur | H56: 74.13 | I56: x | J56: =IF(I56="x",H56,0) -> 74.13 | K56: Charges
... A133: =IF(AND(NOT(ISBLANK(G132)),ISBLANK(G133)),"Reste prévu","") | B133: =IF(AND(NOT(ISBLANK($G132)),ISBLANK($G133)),$C$42-$F$40-$F$42,"") | C133: =IF(AND(NOT(ISBLANK($G132)),ISBLANK($G133)),"Reste réel","") | D133: =IF(AND(NOT(ISBLANK($G132)),ISBLANK($G133)),$C$42-$H$40-$F$42,"") | G133: Veterinaire | H133: 150.5 | I133: x | J133: =IF(I133="x",H133,0) -> 150.5 | K133: Divers
A134: =IF(AND(NOT(ISBLANK(G133)),ISBLANK(G134)),"Reste prévu","") -> Reste prévu | B134: =IF(AND(NOT(ISBLANK($G133)),ISBLANK($G134)),$C$42-$F$40-$F$42,"") -> #REF! | C134: =IF(AND(NOT(ISBLANK($G133)),ISBLANK($G134)),"Reste réel","") -> Reste réel | D134: =IF(AND(NOT(ISBLANK($G133)),ISBLANK($G134)),$C$42-$H$40-$F$42,"") -> #REF! | J134: =IF(I134="x",H134,0) -> 0 | K134: Cadeau
A135: =IF(AND(NOT(ISBLANK(G134)),ISBLANK(G135)),"Reste prévu","") | B135: =IF(AND(NOT(ISBLANK($G134)),ISBLANK($G135)),$C$42-$F$40-$F$42,"") | C135: =IF(AND(NOT(ISBLANK($G134)),ISBLANK($G135)),"Reste réel","") | D135: =IF(AND(NOT(ISBLANK($G134)),ISBLANK($G135)),$C$42-$H$40-$F$42,"") | J135: =IF(I135="x",H135,0) -> 0 | K135: Courses
A136: =IF(AND(NOT(ISBLANK(G135)),ISBLANK(G136)),"Reste prévu","") | B136: =IF(AND(NOT(ISBLANK($G135)),ISBLANK($G136)),$C$42-$F$40-$F$42,"") | C136: =IF(AND(NOT(ISBLANK($G135)),ISBLANK($G136)),"Reste réel","") | D136: =IF(AND(NOT(ISBLANK($G135)),ISBLANK($G136)),$C$42-$H$40-$F$42,"") | J136: =IF(I136="x",H136,0) -> 0 | K136: Voiture/Déplacement
A137: =IF(AND(NOT(ISBLANK(G136)),ISBLANK(G137)),"Reste prévu","") | B137: =IF(AND(NOT(ISBLANK($G136)),ISBLANK($G137)),$C$42-$F$40-$F$42,"") | C137: =IF(AND(NOT(ISBLANK($G136)),ISBLANK($G137)),"Reste réel","") | D137: =IF(AND(NOT(ISBLANK($G136)),ISBLANK($G137)),$C$42-$H$40-$F$42,"") | J137: =IF(I137="x",H137,0) -> 0 | K137: Courses
A138: =IF(AND(NOT(ISBLANK(G137)),ISBLANK(G138)),"Reste prévu","") | B138: =IF(AND(NOT(ISBLANK($G137)),ISBLANK($G138)),$C$42-$F$40-$F$42,"") | C138: =IF(AND(NOT(ISBLANK($G137)),ISBLANK($G138)),"Reste réel","") | D138: =IF(AND(NOT(ISBLANK($G137)),ISBLANK($G138)),$C$42-$H$40-$F$42,"") | J138: =IF(I138="x",H138,0) -> 0 | K138: Courses
A139: =IF(AND(NOT(ISBLANK(G138)),ISBLANK(G139)),"Reste prévu","") | B139: =IF(AND(NOT(ISBLANK($G138)),ISBLANK($G139)),$C$42-$F$40-$F$42,"") | C139: =IF(AND(NOT(ISBLANK($G138)),ISBLANK($G139)),"Reste réel","") | D139: =IF(AND(NOT(ISBLANK($G138)),ISBLANK($G139)),$C$42-$H$40-$F$42,"") | J139: =IF(I139="x",H139,0) -> 0 | K139: Divers
A140: =IF(AND(NOT(ISBLANK(G139)),ISBLANK(G140)),"Reste prévu","") | B140: =IF(AND(NOT(ISBLANK($G139)),ISBLANK($G140)),$C$42-$F$40-$F$42,"") | C140: =IF(AND(NOT(ISBLANK($G139)),ISBLANK($G140)),"Reste réel","") | D140: =IF(AND(NOT(ISBLANK($G139)),ISBLANK($G140)),$C$42-$H$40-$F$42,"") | J140: =IF(I140="x",H140,0) -> 0 | K140: Courses
A141: =IF(AND(NOT(ISBLANK(G140)),ISBLANK(G141)),"Reste prévu","") | B141: =IF(AND(NOT(ISBLANK($G140)),ISBLANK($G141)),$C$42-$F$40-$F$42,"") | C141: =IF(AND(NOT(ISBLANK($G140)),ISBLANK($G141)),"Reste réel","") | D141: =IF(AND(NOT(ISBLANK($G140)),ISBLANK($G141)),$C$42-$H$40-$F$42,"") | J141: =IF(I141="x",H141,0) -> 0 | K141: Cadeau
A142: =IF(AND(NOT(ISBLANK(G141)),ISBLANK(G142)),"Reste prévu","") | B142: =IF(AND(NOT(ISBLANK($G141)),ISBLANK($G142)),$C$42-$F$40-$F$42,"") | C142: =IF(AND(NOT(ISBLANK($G141)),ISBLANK($G142)),"Reste réel","") | D142: =IF(AND(NOT(ISBLANK($G141)),ISBLANK($G142)),$C$42-$H$40-$F$42,"") | J142: =IF(I142="x",H142,0) -> 0 | K142: Cadeau
A143: =IF(AND(NOT(ISBLANK(G142)),ISBLANK(G143)),"Reste prévu","") | B143: =IF(AND(NOT(ISBLANK($G142)),ISBLANK($G143)),$C$42-$F$40-$F$42,"") | C143: =IF(AND(NOT(ISBLANK($G142)),ISBLANK($G143)),"Reste réel","") | D143: =IF(AND(NOT(ISBLANK($G142)),ISBLANK($G143)),$C$42-$H$40-$F$42,"") | J143: =IF(I143="x",H143,0) -> 0 | K143: Cadeau
A144: =IF(AND(NOT(ISBLANK(G143)),ISBLANK(G144)),"Reste prévu","") | B144: =IF(AND(NOT(ISBLANK($G143)),ISBLANK($G144)),$C$42-$F$40-$F$42,"") | C144: =IF(AND(NOT(ISBLANK($G143)),ISBLANK($G144)),"Reste réel","") | D144: =IF(AND(NOT(ISBLANK($G143)),ISBLANK($G144)),$C$42-$H$40-$F$42,"") | J144: =IF(I144="x",H144,0) -> 0 | K144: Cadeau
A145: =IF(AND(NOT(ISBLANK(G144)),ISBLANK(G145)),"Reste prévu","") | B145: =IF(AND(NOT(ISBLANK($G144)),ISBLANK($G145)),$C$42-$F$40-$F$42,"") | C145: =IF(AND(NOT(ISBLANK($G144)),ISBLANK($G145)),"Reste réel","") | D145: =IF(AND(NOT(ISBLANK($G144)),ISBLANK($G145)),$C$42-$H$40-$F$42,"") | J145: =IF(I145="x",H145,0) -> 0 | K145: Courses
A146: =IF(AND(NOT(ISBLANK(G145)),ISBLANK(G146)),"Reste prévu","") | B146: =IF(AND(NOT(ISBLANK($G145)),ISBLANK($G146)),$C$42-$F$40-$F$42,"") | C146: =IF(AND(NOT(ISBLANK($G145)),ISBLANK($G146)),"Reste réel","") | D146: =IF(AND(NOT(ISBLANK($G145)),ISBLANK($G146)),$C$42-$H$40-$F$42,"") | J146: =IF(I146="x",H146,0) -> 0 | K146: Cadeau
A147: =IF(AND(NOT(ISBLANK(G146)),ISBLANK(G147)),"Reste prévu","") | B147: =IF(AND(NOT(ISBLANK($G146)),ISBLANK($G147)),$C$42-$F$40-$F$42,"") | C147: =IF(AND(NOT(ISBLANK($G146)),ISBLANK($G147)),"Reste réel","") | D147: =IF(AND(NOT(ISBLANK($G146)),ISBLANK($G147)),$C$42-$H$40-$F$42,"") | J147: =IF(I147="x",H147,0) -> 0
A148: =IF(AND(NOT(ISBLANK(G147)),ISBLANK(G148)),"Reste prévu","") | B148: =IF(AND(NOT(ISBLANK($G147)),ISBLANK($G148)),$C$42-$F$40-$F$42,"") | C148: =IF(AND(NOT(ISBLANK($G147)),ISBLANK($G148)),"Reste réel","") | D148: =IF(AND(NOT(ISBLANK($G147)),ISBLANK($G148)),$C$42-$H$40-$F$42,"") | J148: =IF(I148="x",H148,0) -> 0
A149: =IF(AND(NOT(ISBLANK(G148)),ISBLANK(G149)),"Reste prévu","") | B149: =IF(AND(NOT(ISBLANK($G148)),ISBLANK($G149)),$C$42-$F$40-$F$42,"") | C149: =IF(AND(NOT(ISBLANK($G148)),ISBLANK($G149)),"Reste réel","") | D149: =IF(AND(NOT(ISBLANK($G148)),ISBLANK($G149)),$C$42-$H$40-$F$42,"") | J149: =IF(I149="x",H149,0) -> 0
A150: =IF(AND(NOT(ISBLANK(G149)),ISBLANK(G150)),"Reste prévu","") | B150: =IF(AND(NOT(ISBLANK($G149)),ISBLANK($G150)),$C$42-$F$40-$F$42,"") | C150: =IF(AND(NOT(ISBLANK($G149)),ISBLANK($G150)),"Reste réel","") | D150: =IF(AND(NOT(ISBLANK($G149)),ISBLANK($G150)),$C$42-$H$40-$F$42,"") | J150: =IF(I150="x",H150,0) -> 0
A151: =IF(AND(NOT(ISBLANK(G150)),ISBLANK(G151)),"Reste prévu","") | B151: =IF(AND(NOT(ISBLANK($G150)),ISBLANK($G151)),$C$42-$F$40-$F$42,"") | C151: =IF(AND(NOT(ISBLANK($G150)),ISBLANK($G151)),"Reste réel","") | D151: =IF(AND(NOT(ISBLANK($G150)),ISBLANK($G151)),$C$42-$H$40-$F$42,"") | J151: =IF(I151="x",H151,0) -> 0
A152: =IF(AND(NOT(ISBLANK(G151)),ISBLANK(G152)),"Reste prévu","") | B152: =IF(AND(NOT(ISBLANK($G151)),ISBLANK($G152)),$C$42-$F$40-$F$42,"") | C152: =IF(AND(NOT(ISBLANK($G151)),ISBLANK($G152)),"Reste réel","") | D152: =IF(AND(NOT(ISBLANK($G151)),ISBLANK($G152)),$C$42-$H$40-$F$42,"") | J152: =IF(I152="x",H152,0) -> 0
A153: =IF(AND(NOT(ISBLANK(G152)),ISBLANK(G153)),"Reste prévu","") | B153: =IF(AND(NOT(ISBLANK($G152)),ISBLANK($G153)),$C$42-$F$40-$F$42,"") | C153: =IF(AND(NOT(ISBLANK($G152)),ISBLANK($G153)),"Reste réel","") | D153: =IF(AND(NOT(ISBLANK($G152)),ISBLANK($G153)),$C$42-$H$40-$F$42,"") | J153: =IF(I153="x",H153,0) -> 0
A154: =IF(AND(NOT(ISBLANK(G153)),ISBLANK(G154)),"Reste prévu","") | B154: =IF(AND(NOT(ISBLANK($G153)),ISBLANK($G154)),$C$42-$F$40-$F$42,"") | C154: =IF(AND(NOT(ISBLANK($G153)),ISBLANK($G154)),"Reste réel","") | D154: =IF(AND(NOT(ISBLANK($G153)),ISBLANK($G154)),$C$42-$H$40-$F$42,"") | J154: =IF(I154="x",H154,0) -> 0
A155: =IF(AND(NOT(ISBLANK(G154)),ISBLANK(G155)),"Reste prévu","") | B155: =IF(AND(NOT(ISBLANK($G154)),ISBLANK($G155)),$C$42-$F$40-$F$42,"") | C155: =IF(AND(NOT(ISBLANK($G154)),ISBLANK($G155)),"Reste réel","") | D155: =IF(AND(NOT(ISBLANK($G154)),ISBLANK($G155)),$C$42-$H$40-$F$42,"") | J155: =IF(I155="x",H155,0) -> 0
A156: =IF(AND(NOT(ISBLANK(G155)),ISBLANK(G156)),"Reste prévu","") | B156: =IF(AND(NOT(ISBLANK($G155)),ISBLANK($G156)),$C$42-$F$40-$F$42,"") | C156: =IF(AND(NOT(ISBLANK($G155)),ISBLANK($G156)),"Reste réel","") | D156: =IF(AND(NOT(ISBLANK($G155)),ISBLANK($G156)),$C$42-$H$40-$F$42,"") | J156: =IF(I156="x",H156,0) -> 0
A157: =IF(AND(NOT(ISBLANK(G156)),ISBLANK(G157)),"Reste prévu","") | B157: =IF(AND(NOT(ISBLANK($G156)),ISBLANK($G157)),$C$42-$F$40-$F$42,"") | C157: =IF(AND(NOT(ISBLANK($G156)),ISBLANK($G157)),"Reste réel","") | D157: =IF(AND(NOT(ISBLANK($G156)),ISBLANK($G157)),$C$42-$H$40-$F$42,"") | J157: =IF(I157="x",H157,0) -> 0
A158: =IF(AND(NOT(ISBLANK(G157)),ISBLANK(G158)),"Reste prévu","") | B158: =IF(AND(NOT(ISBLANK($G157)),ISBLANK($G158)),$C$42-$F$40-$F$42,"") | C158: =IF(AND(NOT(ISBLANK($G157)),ISBLANK($G158)),"Reste réel","") | D158: =IF(AND(NOT(ISBLANK($G157)),ISBLANK($G158)),$C$42-$H$40-$F$42,"") | J158: =IF(I158="x",H158,0) -> 0
... A213: =IF(AND(NOT(ISBLANK(G212)),ISBLANK(G213)),"Reste prévu","") | B213: =IF(AND(NOT(ISBLANK($G212)),ISBLANK($G213)),$C$42-$F$40-$F$42,"") | C213: =IF(AND(NOT(ISBLANK($G212)),ISBLANK($G213)),"Reste réel","") | D213: =IF(AND(NOT(ISBLANK($G212)),ISBLANK($G213)),$C$42-$H$40-$F$42,"") | J213: =IF(I213="x",H213,0) -> 0
A214: =IF(AND(NOT(ISBLANK(G213)),ISBLANK(G214)),"Reste prévu","") | B214: =IF(AND(NOT(ISBLANK($G213)),ISBLANK($G214)),$C$42-$F$40-$F$42,"") | C214: =IF(AND(NOT(ISBLANK($G213)),ISBLANK($G214)),"Reste réel","") | D214: =IF(AND(NOT(ISBLANK($G213)),ISBLANK($G214)),$C$42-$H$40-$F$42,"")
A215: =IF(AND(NOT(ISBLANK(G214)),ISBLANK(G215)),"Reste prévu","") | B215: =IF(AND(NOT(ISBLANK($G214)),ISBLANK($G215)),$C$42-$F$40-$F$42,"") | C215: =IF(AND(NOT(ISBLANK($G214)),ISBLANK($G215)),"Reste réel","") | D215: =IF(AND(NOT(ISBLANK($G214)),ISBLANK($G215)),$C$42-$H$40-$F$42,"")
A216: =IF(AND(NOT(ISBLANK(G215)),ISBLANK(G216)),"Reste prévu","") | B216: =IF(AND(NOT(ISBLANK($G215)),ISBLANK($G216)),$C$42-$F$40-$F$42,"") | C216: =IF(AND(NOT(ISBLANK($G215)),ISBLANK($G216)),"Reste réel","") | D216: =IF(AND(NOT(ISBLANK($G215)),ISBLANK($G216)),$C$42-$H$40-$F$42,"")
A217: =IF(AND(NOT(ISBLANK(G216)),ISBLANK(G217)),"Reste prévu","") | B217: =IF(AND(NOT(ISBLANK($G216)),ISBLANK($G217)),$C$42-$F$40-$F$42,"") | C217: =IF(AND(NOT(ISBLANK($G216)),ISBLANK($G217)),"Reste réel","") | D217: =IF(AND(NOT(ISBLANK($G216)),ISBLANK($G217)),$C$42-$H$40-$F$42,"")
A218: =IF(AND(NOT(ISBLANK(G217)),ISBLANK(G218)),"Reste prévu","") | B218: =IF(AND(NOT(ISBLANK($G217)),ISBLANK($G218)),$C$42-$F$40-$F$42,"") | C218: =IF(AND(NOT(ISBLANK($G217)),ISBLANK($G218)),"Reste réel","") | D218: =IF(AND(NOT(ISBLANK($G217)),ISBLANK($G218)),$C$42-$H$40-$F$42,"")
A219: =IF(AND(NOT(ISBLANK(G218)),ISBLANK(G219)),"Reste prévu","") | B219: =IF(AND(NOT(ISBLANK($G218)),ISBLANK($G219)),$C$42-$F$40-$F$42,"") | C219: =IF(AND(NOT(ISBLANK($G218)),ISBLANK($G219)),"Reste réel","") | D219: =IF(AND(NOT(ISBLANK($G218)),ISBLANK($G219)),$C$42-$H$40-$F$42,"")
A220: =IF(AND(NOT(ISBLANK(G219)),ISBLANK(G220)),"Reste prévu","") | B220: =IF(AND(NOT(ISBLANK($G219)),ISBLANK($G220)),$C$42-$F$40-$F$42,"") | C220: =IF(AND(NOT(ISBLANK($G219)),ISBLANK($G220)),"Reste réel","") | D220: =IF(AND(NOT(ISBLANK($G219)),ISBLANK($G220)),$C$42-$H$40-$F$42,"")
A221: =IF(AND(NOT(ISBLANK(G220)),ISBLANK(G221)),"Reste prévu","") | B221: =IF(AND(NOT(ISBLANK($G220)),ISBLANK($G221)),$C$42-$F$40-$F$42,"") | C221: =IF(AND(NOT(ISBLANK($G220)),ISBLANK($G221)),"Reste réel","") | D221: =IF(AND(NOT(ISBLANK($G220)),ISBLANK($G221)),$C$42-$H$40-$F$42,"")
A222: =IF(AND(NOT(ISBLANK(G221)),ISBLANK(G222)),"Reste prévu","") | B222: =IF(AND(NOT(ISBLANK($G221)),ISBLANK($G222)),$C$42-$F$40-$F$42,"") | C222: =IF(AND(NOT(ISBLANK($G221)),ISBLANK($G222)),"Reste réel","") | D222: =IF(AND(NOT(ISBLANK($G221)),ISBLANK($G222)),$C$42-$H$40-$F$42,"")
A223: =IF(AND(NOT(ISBLANK(G222)),ISBLANK(G223)),"Reste prévu","") | B223: =IF(AND(NOT(ISBLANK($G222)),ISBLANK($G223)),$C$42-$F$40-$F$42,"") | C223: =IF(AND(NOT(ISBLANK($G222)),ISBLANK($G223)),"Reste réel","") | D223: =IF(AND(NOT(ISBLANK($G222)),ISBLANK($G223)),$C$42-$H$40-$F$42,"")
A224: =IF(AND(NOT(ISBLANK(G223)),ISBLANK(G224)),"Reste prévu","") | B224: =IF(AND(NOT(ISBLANK($G223)),ISBLANK($G224)),$C$42-$F$40-$F$42,"") | C224: =IF(AND(NOT(ISBLANK($G223)),ISBLANK($G224)),"Reste réel","") | D224: =IF(AND(NOT(ISBLANK($G223)),ISBLANK($G224)),$C$42-$H$40-$F$42,"")
A225: =IF(AND(NOT(ISBLANK(G224)),ISBLANK(G225)),"Reste prévu","") | B225: =IF(AND(NOT(ISBLANK($G224)),ISBLANK($G225)),$C$42-$F$40-$F$42,"") | C225: =IF(AND(NOT(ISBLANK($G224)),ISBLANK($G225)),"Reste réel","") | D225: =IF(AND(NOT(ISBLANK($G224)),ISBLANK($G225)),$C$42-$H$40-$F$42,"")
... A236: =IF(AND(NOT(ISBLANK(G235)),ISBLANK(G236)),"Reste prévu","") | B236: =IF(AND(NOT(ISBLANK($G235)),ISBLANK($G236)),$C$42-$F$40-$F$42,"") | C236: =IF(AND(NOT(ISBLANK($G235)),ISBLANK($G236)),"Reste réel","") | D236: =IF(AND(NOT(ISBLANK($G235)),ISBLANK($G236)),$C$42-$H$40-$F$42,"")

Sheet Janvier 2026
B1: Recettes | E1: Dépenses | K1: Cadeau
B3: Salaire Pierre | C3: 5441.88 | E3: Loyer Elouen | F3: 669.7 | G3: x | H3: =IF(G3="x",F3,0) -> 669.7 | K3: Logement
B4: Salaire Sterenn | C4: 1938.46 | E4: Argent de poche Elouen | F4: 200 | G4: x | H4: =IF(G4="x",F4,0) -> 200 | K4: Charges
B5: CAF | C5: 113.3 | E5: Engie Elouen | F5: 70 | G5: x | H5: =IF(G5="x",F5,0) -> 70 | K5: Charges
E6: Argent de poche Arthur | F6: 164.99 | G6: x | H6: =IF(G6="x",F6,0) -> 164.99 | K6: Charges
E7: Prêt 25 | F7: 995.15 | G7: x | H7: =IF(G7="x",F7,0) -> 995.15 | K7: Logement
B8: CPAM | C8: 21 | E8: Prêt 15 | F8: 883.42 | G8: x | H8: =IF(G8="x",F8,0) -> 883.42 | K8: Logement
B9: Regularisation Engie | C9: 509.85 | E9: Assurances prêt | F9: 11.46 | G9: x | H9: =IF(G9="x",F9,0) -> 11.46 | K9: Logement
B10: Crédit Impots | C10: 449 | E10: Assurances prêt | F10: 32.57 | G10: x | H10: =IF(G10="x",F10,0) -> 32.57 | K10: Logement
B11: Epargne Travaux | C11: 328.24 | E11: Assurances prêt | F11: 84.98 | G11: x | H11: =IF(G11="x",F11,0) -> 84.98 | K11: Logement
B12: Ael Telephone | C12: 576.99 | E12: Assurances prêt | F12: 33.49 | G12: x | H12: =IF(G12="x",F12,0) -> 33.49 | K12: Logement
B13: Ael Coque | C13: 51.59 | E13: Disney | F13: 6.99 | G13: x | H13: =IF(G13="x",F13,0) -> 6.99 | K13: Internet/Téléphone
B14: CPAM | C14: 26.15 | E14: EDF Arthur | F14: 43.96 | G14: x | H14: =IF(G14="x",F14,0) -> 43.96 | K14: Charges
E15: EkWateur | F15: 208 | G15: x | H15: =IF(G15="x",F15,0) -> 208 | K15: Charges
E16: Sosh Maison | F16: 24.99 | G16: x | H16: =IF(G16="x",F16,0) -> 24.99 | K16: Internet/Téléphone
E17: Sosh Arthur | F17: 14.99 | G17: x | H17: =IF(G17="x",F17,0) -> 14.99 | K17: Internet/Téléphone
E18: Sosh Ael | F18: 14.99 | G18: x | H18: =IF(G18="x",F18,0) -> 14.99 | K18: Internet/Téléphone
E19: Sosh Elouen | F19: 14.99 | H19: =IF(G19="x",F19,0) -> 0 | K19: Internet/Téléphone
E20: Sosh Sterenn | F20: 10.99 | G20: x | H20: =IF(G20="x",F20,0) -> 10.99 | K20: Internet/Téléphone
E21: Mutuelle | F21: 102.87 | G21: No prélevé départ Vivinter | H21: =IF(G21="x",F21,0) -> 0 | K21: Assurances/Mutuelle
E22: Mutuelle (Vivinter) | F22: 104.98 | G22: x | H22: =IF(G22="x",F22,0) -> 104.98 | K22: Assurances/Mutuelle
E23: Suravenir Habitation | F23: 53.22 | G23: x | H23: =IF(G23="x",F23,0) -> 53.22 | K23: Assurances/Mutuelle
E24: VW LDD | F24: 331.65 | G24: x | H24: =IF(G24="x",F24,0) -> 331.65 | K24: Voiture/Déplacement
E25: Suravenir Voiture | F25: 94.22 | G25: x | H25: =IF(G25="x",F25,0) -> 94.22 | K25: Assurances/Mutuelle
E26: Suravenir Garanties Vie | F26: 28.58 | G26: x | H26: =IF(G26="x",F26,0) -> 28.58 | K26: Assurances/Mutuelle
E27: Joséphine | F27: 20 | G27: x | H27: =IF(G27="x",F27,0) -> 20 | K27: Divers
E28: Canal Plus | F28: 21.99 | G28: x | H28: =IF(G28="x",F28,0) -> 21.99 | K28: Internet/Téléphone
H29: =IF(G29="x",F29,0) -> 0 | K29: Voiture/Déplacement
E30: Keolis Elouen | F30: 21.4 | G30: x | H30: =IF(G30="x",F30,0) -> 21.4 | K30: Voiture/Déplacement
E31: Apple | F31: 0.99 | G31: x | H31: =IF(G31="x",F31,0) -> 0.99 | K31: Internet/Téléphone
E32: Apple | F32: 16.99 | G32: x | H32: =IF(G32="x",F32,0) -> 16.99 | K32: Internet/Téléphone
E33: St Charles | F33: 178.3 | G33: x | H33: =IF(G33="x",F33,0) -> 178.3 | K33: Scolarité
E34: Ménage | F34: 136 | G34: x | H34: =IF(G34="x",F34,0) -> 136 | K34: Logement
E35: Urssaaf | F35: 52.34 | G35: x | H35: =IF(G35="x",F35,0) -> 52.34 | K35: Logement
E36: Cotisation Eurocompte | F36: 19.03 | G36: x | H36: =IF(G36="x",F36,0) -> 19.03
E37: Indivision | F37: 33.89 | G37: x | H37: =IF(G37="x",F37,0) -> 33.89
A39: Etat mois précédent | C39: =#REF! -> #REF!
A40: Recettes fixes | C40: =SUM(C2:C6) -> 7493.64 | E40: Somme dépenses prévues | F40: =SUM(F2:F38) -> 4702.11 | G40: Somme dépenses réelles | H40: =SUM(H2:H38) -> 4584.25 | I40: Delta moins les exceptions
A41: Recettes additionnelles du mois | C41: =SUM(C8:C35) -> 1962.82 | E41: Reste previsionnel | F41: =C42-F40 -> #REF! | G41: Delta du mois | H41: =C39+C40+C41-H40-F42 -> #REF!
A42: Total Recettes | C42: =SUM(C39:C41) -> #REF! | E42: Somme dépenses non prévues | F42: =SUM(J44:J246) -> 4923.1
A43: Reste prévu | B43: =$C$42-$F$40-$F$42 -> #REF! | C43: Reste réel | D43: =$C$42-$H$40-$F$42 -> #REF!
A44: =IF(AND(NOT(ISBLANK(#REF!)),ISBLANK(G44)),"Reste prévu","") | B44: =IF(AND(NOT(ISBLANK(#REF!)),ISBLANK($G44)),$C$42-$F$40-$F$42,"") | C44: =IF(AND(NOT(ISBLANK(#REF!)),ISBLANK($G44)),"Reste réel","") | D44: =IF(AND(NOT(ISBLANK(#REF!)),ISBLANK($G44)),$C$42-$H$40-$F$42,"") | G44: Fournil du port | H44: 7.35 | I44: x | J44: =IF(I44="x",H44,0) -> 7.35 | K44: Courses
A45: =IF(AND(NOT(ISBLANK(G44)),ISBLANK(G45)),"Reste prévu","") | B45: =IF(AND(NOT(ISBLANK($G44)),ISBLANK($G45)),$C$42-$F$40-$F$42,"") | C45: =IF(AND(NOT(ISBLANK($G44)),ISBLANK($G45)),"Reste réel","") | D45: =IF(AND(NOT(ISBLANK($G44)),ISBLANK($G45)),$C$42-$H$40-$F$42,"") | G45: Leclerc | H45: 15.65 | I45: x | J45: =IF(I45="x",H45,0) -> 15.65 | K45: Courses
A46: =IF(AND(NOT(ISBLANK(G45)),ISBLANK(G46)),"Reste prévu","") | B46: =IF(AND(NOT(ISBLANK($G45)),ISBLANK($G46)),$C$42-$F$40-$F$42,"") | C46: =IF(AND(NOT(ISBLANK($G45)),ISBLANK($G46)),"Reste réel","") | D46: =IF(AND(NOT(ISBLANK($G45)),ISBLANK($G46)),$C$42-$H$40-$F$42,"") | G46: Leclerc | H46: 39.06 | I46: x | J46: =IF(I46="x",H46,0) -> 39.06 | K46: Courses
A47: =IF(AND(NOT(ISBLANK(G46)),ISBLANK(G47)),"Reste prévu","") | B47: =IF(AND(NOT(ISBLANK($G46)),ISBLANK($G47)),$C$42-$F$40-$F$42,"") | C47: =IF(AND(NOT(ISBLANK($G46)),ISBLANK($G47)),"Reste réel","") | D47: =IF(AND(NOT(ISBLANK($G46)),ISBLANK($G47)),$C$42-$H$40-$F$42,"") | G47: Le Quartaut Jeff | H47: 45 | I47: x | J47: =IF(I47="x",H47,0) -> 45 | K47: Cadeau
A48: =IF(AND(NOT(ISBLANK(G47)),ISBLANK(G48)),"Reste prévu","") | B48: =IF(AND(NOT(ISBLANK($G47)),ISBLANK($G48)),$C$42-$F$40-$F$42,"") | C48: =IF(AND(NOT(ISBLANK($G47)),ISBLANK($G48)),"Reste réel","") | D48: =IF(AND(NOT(ISBLANK($G47)),ISBLANK($G48)),$C$42-$H$40-$F$42,"") | G48: Pharmacie | H48: 71.4 | I48: x | J48: =IF(I48="x",H48,0) -> 71.4 | K48: Medical
A49: =IF(AND(NOT(ISBLANK(G48)),ISBLANK(G49)),"Reste prévu","") | B49: =IF(AND(NOT(ISBLANK($G48)),ISBLANK($G49)),$C$42-$F$40-$F$42,"") | C49: =IF(AND(NOT(ISBLANK($G48)),ISBLANK($G49)),"Reste réel","") | D49: =IF(AND(NOT(ISBLANK($G48)),ISBLANK($G49)),$C$42-$H$40-$F$42,"") | G49: Charge Voiture | H49: 11.76 | I49: x | J49: =IF(I49="x",H49,0) -> 11.76 | K49: Voiture/Déplacement
A50: =IF(AND(NOT(ISBLANK(G49)),ISBLANK(G50)),"Reste prévu","") | B50: =IF(AND(NOT(ISBLANK($G49)),ISBLANK($G50)),$C$42-$F$40-$F$42,"") | C50: =IF(AND(NOT(ISBLANK($G49)),ISBLANK($G50)),"Reste réel","") | D50: =IF(AND(NOT(ISBLANK($G49)),ISBLANK($G50)),$C$42-$H$40-$F$42,"") | G50: BioCoop | H50: 45.58 | I50: x | J50: =IF(I50="x",H50,0) -> 45.58 | K50: Courses
A51: =IF(AND(NOT(ISBLANK(G50)),ISBLANK(G51)),"Reste prévu","") | B51: =IF(AND(NOT(ISBLANK($G50)),ISBLANK($G51)),$C$42-$F$40-$F$42,"") | C51: =IF(AND(NOT(ISBLANK($G50)),ISBLANK($G51)),"Reste réel","") | D51: =IF(AND(NOT(ISBLANK($G50)),ISBLANK($G51)),$C$42-$H$40-$F$42,"") | G51: Feuillate Repas Galette | H51: 53.2 | I51: x | J51: =IF(I51="x",H51,0) -> 53.2 | K51: Courses
A52: =IF(AND(NOT(ISBLANK(G51)),ISBLANK(G52)),"Reste prévu","") | B52: =IF(AND(NOT(ISBLANK($G51)),ISBLANK($G52)),$C$42-$F$40-$F$42,"") | C52: =IF(AND(NOT(ISBLANK($G51)),ISBLANK($G52)),"Reste réel","") | D52: =IF(AND(NOT(ISBLANK($G51)),ISBLANK($G52)),$C$42-$H$40-$F$42,"") | G52: Cigarettes | H52: 13 | I52: x | J52: =IF(I52="x",H52,0) -> 13 | K52: Divers
A53: =IF(AND(NOT(ISBLANK(G52)),ISBLANK(G53)),"Reste prévu","") | B53: =IF(AND(NOT(ISBLANK($G52)),ISBLANK($G53)),$C$42-$F$40-$F$42,"") | C53: =IF(AND(NOT(ISBLANK($G52)),ISBLANK($G53)),"Reste réel","") | D53: =IF(AND(NOT(ISBLANK($G52)),ISBLANK($G53)),$C$42-$H$40-$F$42,"") | G53: Cultura | H53: 5.97 | I53: x | J53: =IF(I53="x",H53,0) -> 5.97 | K53: Loisirs
A54: =IF(AND(NOT(ISBLANK(G53)),ISBLANK(G54)),"Reste prévu","") | B54: =IF(AND(NOT(ISBLANK($G53)),ISBLANK($G54)),$C$42-$F$40-$F$42,"") | C54: =IF(AND(NOT(ISBLANK($G53)),ISBLANK($G54)),"Reste réel","") | D54: =IF(AND(NOT(ISBLANK($G53)),ISBLANK($G54)),$C$42-$H$40-$F$42,"") | G54: Leclerc | H54: 34.01 | I54: x | J54: =IF(I54="x",H54,0) -> 34.01 | K54: Courses
A55: =IF(AND(NOT(ISBLANK(G54)),ISBLANK(G55)),"Reste prévu","") | B55: =IF(AND(NOT(ISBLANK($G54)),ISBLANK($G55)),$C$42-$F$40-$F$42,"") | C55: =IF(AND(NOT(ISBLANK($G54)),ISBLANK($G55)),"Reste réel","") | D55: =IF(AND(NOT(ISBLANK($G54)),ISBLANK($G55)),$C$42-$H$40-$F$42,"") | G55: ChargeMap | H55: 105.7 | I55: x | J55: =IF(I55="x",H55,0) -> 105.7 | K55: Voiture/Déplacement
A56: =IF(AND(NOT(ISBLANK(G55)),ISBLANK(G56)),"Reste prévu","") | B56: =IF(AND(NOT(ISBLANK($G55)),ISBLANK($G56)),$C$42-$F$40-$F$42,"") | C56: =IF(AND(NOT(ISBLANK($G55)),ISBLANK($G56)),"Reste réel","") | D56: =IF(AND(NOT(ISBLANK($G55)),ISBLANK($G56)),$C$42-$H$40-$F$42,"") | G56: Courses Arthur | H56: 26.82 | I56: x | J56: =IF(I56="x",H56,0) -> 26.82 | K56: Courses
... A119: =IF(AND(NOT(ISBLANK(G118)),ISBLANK(G119)),"Reste prévu","") | B119: =IF(AND(NOT(ISBLANK($G118)),ISBLANK($G119)),$C$42-$F$40-$F$42,"") | C119: =IF(AND(NOT(ISBLANK($G118)),ISBLANK($G119)),"Reste réel","") | D119: =IF(AND(NOT(ISBLANK($G118)),ISBLANK($G119)),$C$42-$H$40-$F$42,"") | G119: Virement Elouen | H119: 315.4 | I119: x | J119: =IF(I119="x",H119,0) -> 315.4 | K119: Charges
A120: =IF(AND(NOT(ISBLANK(G119)),ISBLANK(G120)),"Reste prévu","") -> Reste prévu | B120: =IF(AND(NOT(ISBLANK($G119)),ISBLANK($G120)),$C$42-$F$40-$F$42,"") -> #REF! | C120: =IF(AND(NOT(ISBLANK($G119)),ISBLANK($G120)),"Reste réel","") -> Reste réel | D120: =IF(AND(NOT(ISBLANK($G119)),ISBLANK($G120)),$C$42-$H$40-$F$42,"") -> #REF! | J120: =IF(I120="x",H120,0) -> 0 | K120: Logement
A121: =IF(AND(NOT(ISBLANK(G120)),ISBLANK(G121)),"Reste prévu","") | B121: =IF(AND(NOT(ISBLANK($G120)),ISBLANK($G121)),$C$42-$F$40-$F$42,"") | C121: =IF(AND(NOT(ISBLANK($G120)),ISBLANK($G121)),"Reste réel","") | D121: =IF(AND(NOT(ISBLANK($G120)),ISBLANK($G121)),$C$42-$H$40-$F$42,"") | J121: =IF(I121="x",H121,0) -> 0 | K121: Bricolage/Travaux
A122: =IF(AND(NOT(ISBLANK(G121)),ISBLANK(G122)),"Reste prévu","") | B122: =IF(AND(NOT(ISBLANK($G121)),ISBLANK($G122)),$C$42-$F$40-$F$42,"") | C122: =IF(AND(NOT(ISBLANK($G121)),ISBLANK($G122)),"Reste réel","") | D122: =IF(AND(NOT(ISBLANK($G121)),ISBLANK($G122)),$C$42-$H$40-$F$42,"") | J122: =IF(I122="x",H122,0) -> 0 | K122: Bricolage/Travaux
A123: =IF(AND(NOT(ISBLANK(G122)),ISBLANK(G123)),"Reste prévu","") | B123: =IF(AND(NOT(ISBLANK($G122)),ISBLANK($G123)),$C$42-$F$40-$F$42,"") | C123: =IF(AND(NOT(ISBLANK($G122)),ISBLANK($G123)),"Reste réel","") | D123: =IF(AND(NOT(ISBLANK($G122)),ISBLANK($G123)),$C$42-$H$40-$F$42,"") | J123: =IF(I123="x",H123,0) -> 0 | K123: Courses
A124: =IF(AND(NOT(ISBLANK(G123)),ISBLANK(G124)),"Reste prévu","") | B124: =IF(AND(NOT(ISBLANK($G123)),ISBLANK($G124)),$C$42-$F$40-$F$42,"") | C124: =IF(AND(NOT(ISBLANK($G123)),ISBLANK($G124)),"Reste réel","") | D124: =IF(AND(NOT(ISBLANK($G123)),ISBLANK($G124)),$C$42-$H$40-$F$42,"") | J124: =IF(I124="x",H124,0) -> 0 | K124: Courses
A125: =IF(AND(NOT(ISBLANK(G124)),ISBLANK(G125)),"Reste prévu","") | B125: =IF(AND(NOT(ISBLANK($G124)),ISBLANK($G125)),$C$42-$F$40-$F$42,"") | C125: =IF(AND(NOT(ISBLANK($G124)),ISBLANK($G125)),"Reste réel","") | D125: =IF(AND(NOT(ISBLANK($G124)),ISBLANK($G125)),$C$42-$H$40-$F$42,"") | J125: =IF(I125="x",H125,0) -> 0 | K125: Voiture/Déplacement
A126: =IF(AND(NOT(ISBLANK(G125)),ISBLANK(G126)),"Reste prévu","") | B126: =IF(AND(NOT(ISBLANK($G125)),ISBLANK($G126)),$C$42-$F$40-$F$42,"") | C126: =IF(AND(NOT(ISBLANK($G125)),ISBLANK($G126)),"Reste réel","") | D126: =IF(AND(NOT(ISBLANK($G125)),ISBLANK($G126)),$C$42-$H$40-$F$42,"") | J126: =IF(I126="x",H126,0) -> 0 | K126: Bricolage/Travaux
A127: =IF(AND(NOT(ISBLANK(G126)),ISBLANK(G127)),"Reste prévu","") | B127: =IF(AND(NOT(ISBLANK($G126)),ISBLANK($G127)),$C$42-$F$40-$F$42,"") | C127: =IF(AND(NOT(ISBLANK($G126)),ISBLANK($G127)),"Reste réel","") | D127: =IF(AND(NOT(ISBLANK($G126)),ISBLANK($G127)),$C$42-$H$40-$F$42,"") | J127: =IF(I127="x",H127,0) -> 0 | K127: Cadeau
